Workbook
Name data: Financials!$C$9:$AU$232
Name data_column: Financials!$C$1:$AU$1
Name data_row: Financials!$A$9:$A$232
Name rCP: Valuation!$H$23

Sheet Summary
A1: Summary | C1: =Financials!G1 -> FY2016 | D1: =Financials!L1 -> FY2017 | E1: =Financials!Q1 -> FY2018 | F1: =Financials!V1 -> FY2019 | G1: =Financials!AA1 -> FY2020 | H1: =Financials!AF1 -> FY2021 | I1: =Financials!AK1 -> FY2022 | J1: =Financials!AP1 -> FY2023 | K1: =Financials!AU1 -> FY2024
C2: =Financials!G3 -> A | D2: =Financials!L3 -> A | E2: =Financials!Q3 -> A | F2: =Financials!V3 -> F | G2: =Financials!AA3 -> F | H2: =Financials!AF3 -> F | I2: =Financials!AK3 -> F | J2: =Financials!AP3 -> F | K2: =Financials!AU3 -> F
A4: Income Statement
A6: Revenue | B6: INR Mn | C6: =INDEX(data,MATCH($A6,data_row,0),MATCH(C$1,data_column,0)) -> 53694.5 | D6: =INDEX(data,MATCH($A6,data_row,0),MATCH(D$1,data_column,0)) -> 56167.9 | E6: =INDEX(data,MATCH($A6,data_row,0),MATCH(E$1,data_column,0)) -> 60870 | F6: =INDEX(data,MATCH($A6,data_row,0),MATCH(F$1,data_column,0)) -> 72138.537 | G6: =INDEX(data,MATCH($A6,data_row,0),MATCH(G$1,data_column,0)) -> 77147.989 | H6: =INDEX(data,MATCH($A6,data_row,0),MATCH(H$1,data_column,0)) -> 84365.219 | I6: =INDEX(data,MATCH($A6,data_row,0),MATCH(I$1,data_column,0)) -> 90224.691 | J6: =INDEX(data,MATCH($A6,data_row,0),MATCH(J$1,data_column,0)) -> 96507.612 | K6: =INDEX(data,MATCH($A6,data_row,0),MATCH(K$1,data_column,0)) -> 103245.54
A7: Gross Profit | B7: INR Mn | C7: =INDEX(data,MATCH($A7,data_row,0),MATCH(C$1,data_column,0)) -> 27831.5 | D7: =INDEX(data,MATCH($A7,data_row,0),MATCH(D$1,data_column,0)) -> 29772.3 | E7: =INDEX(data,MATCH($A7,data_row,0),MATCH(E$1,data_column,0)) -> 31993.5 | F7: =INDEX(data,MATCH($A7,data_row,0),MATCH(F$1,data_column,0)) -> 35544.92 | G7: =INDEX(data,MATCH($A7,data_row,0),MATCH(G$1,data_column,0)) -> 39345.475 | H7: =INDEX(data,MATCH($A7,data_row,0),MATCH(H$1,data_column,0)) -> 43026.262 | I7: =INDEX(data,MATCH($A7,data_row,0),MATCH(I$1,data_column,0)) -> 46916.84 | J7: =INDEX(data,MATCH($A7,data_row,0),MATCH(J$1,data_column,0)) -> 50183.958 | K7: =INDEX(data,MATCH($A7,data_row,0),MATCH(K$1,data_column,0)) -> 53687.682
A8: EBITDA | B8: INR Mn | C8: =INDEX(data,MATCH($A8,data_row,0),MATCH(C$1,data_column,0)) -> 11787.1 | D8: =INDEX(data,MATCH($A8,data_row,0),MATCH(D$1,data_column,0)) -> 12656 | E8: =INDEX(data,MATCH($A8,data_row,0),MATCH(E$1,data_column,0)) -> 13412.2 | F8: =INDEX(data,MATCH($A8,data_row,0),MATCH(F$1,data_column,0)) -> 14323.98 | G8: =INDEX(data,MATCH($A8,data_row,0),MATCH(G$1,data_column,0)) -> 15439.733 | H8: =INDEX(data,MATCH($A8,data_row,0),MATCH(H$1,data_column,0)) -> 16819.741 | I8: =INDEX(data,MATCH($A8,data_row,0),MATCH(I$1,data_column,0)) -> 17984.137 | J8: =INDEX(data,MATCH($A8,data_row,0),MATCH(J$1,data_column,0)) -> 19236.753 | K8: =INDEX(data,MATCH($A8,data_row,0),MATCH(K$1,data_column,0)) -> 20580.356
A9: EBIT | B9: INR Mn | C9: =INDEX(data,MATCH($A9,data_row,0),MATCH(C$1,data_column,0)) -> 10455.8 | D9: =INDEX(data,MATCH($A9,data_row,0),MATCH(D$1,data_column,0)) -> 11504.6 | E9: =INDEX(data,MATCH($A9,data_row,0),MATCH(E$1,data_column,0)) -> 12213.4 | F9: =INDEX(data,MATCH($A9,data_row,0),MATCH(F$1,data_column,0)) -> 13062.091 | G9: =INDEX(data,MATCH($A9,data_row,0),MATCH(G$1,data_column,0)) -> 14139.303 | H9: =INDEX(data,MATCH($A9,data_row,0),MATCH(H$1,data_column,0)) -> 15447.223 | I9: =INDEX(data,MATCH($A9,data_row,0),MATCH(I$1,data_column,0)) -> 16546.54 | J9: =INDEX(data,MATCH($A9,data_row,0),MATCH(J$1,data_column,0)) -> 17739.964 | K9: =INDEX(data,MATCH($A9,data_row,0),MATCH(K$1,data_column,0)) -> 19020.737
A10: PAT to equity shareholders | B10: INR Mn | C10: =INDEX(data,MATCH($A10,data_row,0),MATCH(C$1,data_column,0)) -> 7555.5 | D10: =INDEX(data,MATCH($A10,data_row,0),MATCH(D$1,data_column,0)) -> 8599.9 | E10: =INDEX(data,MATCH($A10,data_row,0),MATCH(E$1,data_column,0)) -> 9623.5 | F10: =INDEX(data,MATCH($A10,data_row,0),MATCH(F$1,data_column,0)) -> 9289.6963 | G10: =INDEX(data,MATCH($A10,data_row,0),MATCH(G$1,data_column,0)) -> 10405.061 | H10: =INDEX(data,MATCH($A10,data_row,0),MATCH(H$1,data_column,0)) -> 11307.301 | I10: =INDEX(data,MATCH($A10,data_row,0),MATCH(I$1,data_column,0)) -> 12064.544 | J10: =INDEX(data,MATCH($A10,data_row,0),MATCH(J$1,data_column,0)) -> 12886.05 | K10: =INDEX(data,MATCH($A10,data_row,0),MATCH(K$1,data_column,0)) -> 13767.551
A11: Adjusted PAT | B11: INR Mn | C11: =Financials!G49-Financials!G38 -> 7603.6 | D11: =Financials!L49-Financials!L38 -> 8658 | E11: =Financials!Q49-Financials!Q38 -> 9623.5 | F11: =Financials!V49-Financials!V38 -> 9289.6963 | G11: =Financials!AA49-Financials!AA38 -> 10405.061 | H11: =Financials!AF49-Financials!AF38 -> 11307.301 | I11: =Financials!AK49-Financials!AK38 -> 12064.544 | J11: =Financials!AP49-Financials!AP38 -> 12886.05 | K11: =Financials!AU49-Financials!AU38 -> 13767.551
A12: Adjusted diluted EPS | B12: INR/share | C12: =C11/Financials!G55 -> 14.830505 | D12: =D11/Financials!L55 -> 16.881397 | E12: =E11/Financials!Q55 -> 18.813352 | F12: =F11/Financials!V55 -> 18.289504 | G12: =G11/Financials!AA55 -> 20.482404 | H12: =H11/Financials!AF55 -> 22.258466 | I12: =I11/Financials!AK55 -> 23.749102 | J12: =J11/Financials!AP55 -> 25.36624 | K12: =K11/Financials!AU55 -> 27.101479
A14: Balance Sheet
A16: Cash and Cash Equivalents | B16: INR Mn | C16: =INDEX(data,MATCH($A16,data_row,0),MATCH(C$1,data_column,0)) -> 1319.4 | D16: =INDEX(data,MATCH($A16,data_row,0),MATCH(D$1,data_column,0)) -> 999.4 | E16: =INDEX(data,MATCH($A16,data_row,0),MATCH(E$1,data_column,0)) -> 1635.8 | F16: =INDEX(data,MATCH($A16,data_row,0),MATCH(F$1,data_column,0)) -> 7413.7113 | G16: =INDEX(data,MATCH($A16,data_row,0),MATCH(G$1,data_column,0)) -> 13113.522 | H16: =INDEX(data,MATCH($A16,data_row,0),MATCH(H$1,data_column,0)) -> 18935.507 | I16: =INDEX(data,MATCH($A16,data_row,0),MATCH(I$1,data_column,0)) -> 26211.863 | J16: =INDEX(data,MATCH($A16,data_row,0),MATCH(J$1,data_column,0)) -> 33424.517 | K16: =INDEX(data,MATCH($A16,data_row,0),MATCH(K$1,data_column,0)) -> 41388.039
A17: Fixed Assets | B17: INR Mn | C17: =INDEX(data,MATCH($A17,data_row,0),MATCH(C$1,data_column,0)) -> 15074.8 | D17: =INDEX(data,MATCH($A17,data_row,0),MATCH(D$1,data_column,0)) -> 9368.3 | E17: =INDEX(data,MATCH($A17,data_row,0),MATCH(E$1,data_column,0)) -> 10303.2 | F17: =INDEX(data,MATCH($A17,data_row,0),MATCH(F$1,data_column,0)) -> 10941.311 | G17: =INDEX(data,MATCH($A17,data_row,0),MATCH(G$1,data_column,0)) -> 11740.881 | H17: =INDEX(data,MATCH($A17,data_row,0),MATCH(H$1,data_column,0)) -> 12468.363 | I17: =INDEX(data,MATCH($A17,data_row,0),MATCH(I$1,data_column,0)) -> 13130.766 | J17: =INDEX(data,MATCH($A17,data_row,0),MATCH(J$1,data_column,0)) -> 13833.977 | K17: =INDEX(data,MATCH($A17,data_row,0),MATCH(K$1,data_column,0)) -> 14474.359
A18: Total Assets | B18: INR Mn | C18: =INDEX(data,MATCH($A18,data_row,0),MATCH(C$1,data_column,0)) -> 39081.9 | D18: =INDEX(data,MATCH($A18,data_row,0),MATCH(D$1,data_column,0)) -> 47741.9 | E18: =INDEX(data,MATCH($A18,data_row,0),MATCH(E$1,data_column,0)) -> 52044.6 | F18: =INDEX(data,MATCH($A18,data_row,0),MATCH(F$1,data_column,0)) -> 59853.76 | G18: =INDEX(data,MATCH($A18,data_row,0),MATCH(G$1,data_column,0)) -> 67736.621 | H18: =INDEX(data,MATCH($A18,data_row,0),MATCH(H$1,data_column,0)) -> 76774.048 | I18: =INDEX(data,MATCH($A18,data_row,0),MATCH(I$1,data_column,0)) -> 86029.828 | J18: =INDEX(data,MATCH($A18,data_row,0),MATCH(J$1,data_column,0)) -> 95943.539 | K18: =INDEX(data,MATCH($A18,data_row,0),MATCH(K$1,data_column,0)) -> 106548.37
A19: Short term borrowings | B19: INR Mn | C19: =INDEX(data,MATCH($A19,data_row,0),MATCH(C$1,data_column,0)) -> 749.2 | D19: =INDEX(data,MATCH($A19,data_row,0),MATCH(D$1,data_column,0)) -> 926.6 | E19: =INDEX(data,MATCH($A19,data_row,0),MATCH(E$1,data_column,0)) -> 1154.4 | F19: =INDEX(data,MATCH($A19,data_row,0),MATCH(F$1,data_column,0)) -> 1154.4 | G19: =INDEX(data,MATCH($A19,data_row,0),MATCH(G$1,data_column,0)) -> 1154.4 | H19: =INDEX(data,MATCH($A19,data_row,0),MATCH(H$1,data_column,0)) -> 1154.4 | I19: =INDEX(data,MATCH($A19,data_row,0),MATCH(I$1,data_column,0)) -> 1154.4 | J19: =INDEX(data,MATCH($A19,data_row,0),MATCH(J$1,data_column,0)) -> 1154.4 | K19: =INDEX(data,MATCH($A19,data_row,0),MATCH(K$1,data_column,0)) -> 1154.4
A20: Long term borrowings | B20: INR Mn | C20: =INDEX(data,MATCH($A20,data_row,0),MATCH(C$1,data_column,0)) -> 93.6 | D20: =INDEX(data,MATCH($A20,data_row,0),MATCH(D$1,data_column,0)) -> 48.5 | E20: =INDEX(data,MATCH($A20,data_row,0),MATCH(E$1,data_column,0)) -> 71.1 | F20: =INDEX(data,MATCH($A20,data_row,0),MATCH(F$1,data_column,0)) -> 71.1 | G20: =INDEX(data,MATCH($A20,data_row,0),MATCH(G$1,data_column,0)) -> 71.1 | H20: =INDEX(data,MATCH($A20,data_row,0),MATCH(H$1,data_column,0)) -> 71.1 | I20: =INDEX(data,MATCH($A20,data_row,0),MATCH(I$1,data_column,0)) -> 71.1 | J20: =INDEX(data,MATCH($A20,data_row,0),MATCH(J$1,data_column,0)) -> 71.1 | K20: =INDEX(data,MATCH($A20,data_row,0),MATCH(K$1,data_column,0)) -> 71.1
A21: Total Liabilities | B21: INR Mn | C21: =INDEX(data,MATCH($A21,data_row,0),MATCH(C$1,data_column,0)) -> 10825.5 | D21: =INDEX(data,MATCH($A21,data_row,0),MATCH(D$1,data_column,0)) -> 11759.6 | E21: =INDEX(data,MATCH($A21,data_row,0),MATCH(E$1,data_column,0)) -> 14554.1 | F21: =INDEX(data,MATCH($A21,data_row,0),MATCH(F$1,data_column,0)) -> 16093.724 | G21: =INDEX(data,MATCH($A21,data_row,0),MATCH(G$1,data_column,0)) -> 16642.244 | H21: =INDEX(data,MATCH($A21,data_row,0),MATCH(H$1,data_column,0)) -> 17812.655 | I21: =INDEX(data,MATCH($A21,data_row,0),MATCH(I$1,data_column,0)) -> 18743.385 | J21: =INDEX(data,MATCH($A21,data_row,0),MATCH(J$1,data_column,0)) -> 19760.917 | K21: =INDEX(data,MATCH($A21,data_row,0),MATCH(K$1,data_column,0)) -> 20859.731
A22: Shareholder Equity | B22: INR Mn | C22: =INDEX(data,MATCH($A22,data_row,0),MATCH(C$1,data_column,0)) -> 512.7 | D22: =INDEX(data,MATCH($A22,data_row,0),MATCH(D$1,data_column,0)) -> 512.7 | E22: =INDEX(data,MATCH($A22,data_row,0),MATCH(E$1,data_column,0)) -> 507.8 | F22: =INDEX(data,MATCH($A22,data_row,0),MATCH(F$1,data_column,0)) -> 507.8 | G22: =INDEX(data,MATCH($A22,data_row,0),MATCH(G$1,data_column,0)) -> 507.8 | H22: =INDEX(data,MATCH($A22,data_row,0),MATCH(H$1,data_column,0)) -> 507.8 | I22: =INDEX(data,MATCH($A22,data_row,0),MATCH(I$1,data_column,0)) -> 507.8 | J22: =INDEX(data,MATCH($A22,data_row,0),MATCH(J$1,data_column,0)) -> 507.8 | K22: =INDEX(data,MATCH($A22,data_row,0),MATCH(K$1,data_column,0)) -> 507.8
A23: Total Equity | B23: INR Mn | C23: =INDEX(data,MATCH($A23,data_row,0),MATCH(C$1,data_column,0)) -> 28256.4 | D23: =INDEX(data,MATCH($A23,data_row,0),MATCH(D$1,data_column,0)) -> 35982.3 | E23: =INDEX(data,MATCH($A23,data_row,0),MATCH(E$1,data_column,0)) -> 37490.5 | F23: =INDEX(data,MATCH($A23,data_row,0),MATCH(F$1,data_column,0)) -> 43760.036 | G23: =INDEX(data,MATCH($A23,data_row,0),MATCH(G$1,data_column,0)) -> 51094.377 | H23: =INDEX(data,MATCH($A23,data_row,0),MATCH(H$1,data_column,0)) -> 58961.393 | I23: =INDEX(data,MATCH($A23,data_row,0),MATCH(I$1,data_column,0)) -> 67286.443 | J23: =INDEX(data,MATCH($A23,data_row,0),MATCH(J$1,data_column,0)) -> 76182.622 | K23: =INDEX(data,MATCH($A23,data_row,0),MATCH(K$1,data_column,0)) -> 85688.638
A25: Cash Flow
A27: Cash flow from operations | B27: INR Mn | C27: =INDEX(data,MATCH($A27,data_row,0),MATCH(C$1,data_column,0)) -> 9074.7 | D27: =INDEX(data,MATCH($A27,data_row,0),MATCH(D$1,data_column,0)) -> 7937.5 | E27: =INDEX(data,MATCH($A27,data_row,0),MATCH(E$1,data_column,0)) -> 7964.3 | F27: =INDEX(data,MATCH($A27,data_row,0),MATCH(F$1,data_column,0)) -> 10724.711 | G27: =INDEX(data,MATCH($A27,data_row,0),MATCH(G$1,data_column,0)) -> 10912.319 | H27: =INDEX(data,MATCH($A27,data_row,0),MATCH(H$1,data_column,0)) -> 11407.681 | I27: =INDEX(data,MATCH($A27,data_row,0),MATCH(I$1,data_column,0)) -> 13164.302 | J27: =INDEX(data,MATCH($A27,data_row,0),MATCH(J$1,data_column,0)) -> 13454.276 | K27: =INDEX(data,MATCH($A27,data_row,0),MATCH(K$1,data_column,0)) -> 14480.349
A28: Capital expenditure fixed assets | B28: INR Mn | C28: =INDEX(data,MATCH($A28,data_row,0),MATCH(C$1,data_column,0)) -> -1704.3 | D28: =INDEX(data,MATCH($A28,data_row,0),MATCH(D$1,data_column,0)) -> -1330.6 | E28: =INDEX(data,MATCH($A28,data_row,0),MATCH(E$1,data_column,0)) -> -1768.3 | F28: =INDEX(data,MATCH($A28,data_row,0),MATCH(F$1,data_column,0)) -> -1900 | G28: =INDEX(data,MATCH($A28,data_row,0),MATCH(G$1,data_column,0)) -> -2100 | H28: =INDEX(data,MATCH($A28,data_row,0),MATCH(H$1,data_column,0)) -> -2100 | I28: =INDEX(data,MATCH($A28,data_row,0),MATCH(I$1,data_column,0)) -> -2100 | J28: =INDEX(data,MATCH($A28,data_row,0),MATCH(J$1,data_column,0)) -> -2200 | K28: =INDEX(data,MATCH($A28,data_row,0),MATCH(K$1,data_column,0)) -> -2200
A29: Cash flow from investing activities | B29: INR Mn | C29: =INDEX(data,MATCH($A29,data_row,0),MATCH(C$1,data_column,0)) -> -4911.4 | D29: =INDEX(data,MATCH($A29,data_row,0),MATCH(D$1,data_column,0)) -> -8789.7 | E29: =INDEX(data,MATCH($A29,data_row,0),MATCH(E$1,data_column,0)) -> 392.6 | F29: =INDEX(data,MATCH($A29,data_row,0),MATCH(F$1,data_column,0)) -> -1900 | G29: =INDEX(data,MATCH($A29,data_row,0),MATCH(G$1,data_column,0)) -> -2100 | H29: =INDEX(data,MATCH($A29,data_row,0),MATCH(H$1,data_column,0)) -> -2100 | I29: =INDEX(data,MATCH($A29,data_row,0),MATCH(I$1,data_column,0)) -> -2100 | J29: =INDEX(data,MATCH($A29,data_row,0),MATCH(J$1,data_column,0)) -> -2200 | K29: =INDEX(data,MATCH($A29,data_row,0),MATCH(K$1,data_column,0)) -> -2200
A30: Dividend paid | B30: INR Mn | C30: =INDEX(data,MATCH($A30,data_row,0),MATCH(C$1,data_column,0)) -> -4032.2 | D30: =INDEX(data,MATCH($A30,data_row,0),MATCH(D$1,data_column,0)) -> -316.3 | E30: =INDEX(data,MATCH($A30,data_row,0),MATCH(E$1,data_column,0)) -> -2930 | F30: =INDEX(data,MATCH($A30,data_row,0),MATCH(F$1,data_column,0)) -> -3046.8 | G30: =INDEX(data,MATCH($A30,data_row,0),MATCH(G$1,data_column,0)) -> -3112.5078 | H30: =INDEX(data,MATCH($A30,data_row,0),MATCH(H$1,data_column,0)) -> -3485.6956 | I30: =INDEX(data,MATCH($A30,data_row,0),MATCH(I$1,data_column,0)) -> -3787.9457 | J30: =INDEX(data,MATCH($A30,data_row,0),MATCH(J$1,data_column,0)) -> -4041.6222 | K30: =INDEX(data,MATCH($A30,data_row,0),MATCH(K$1,data_column,0)) -> -4316.8267
A31: Debt issuance/ repayment | B31: INR Mn | C31: =INDEX(data,MATCH($A31,data_row,0),MATCH(C$1,data_column,0)) -> 116.2 | D31: =INDEX(data,MATCH($A31,data_row,0),MATCH(D$1,data_column,0)) -> 55.1 | E31: =INDEX(data,MATCH($A31,data_row,0),MATCH(E$1,data_column,0)) -> -4.3 | F31: =INDEX(data,MATCH($A31,data_row,0),MATCH(F$1,data_column,0)) -> 0 | G31: =INDEX(data,MATCH($A31,data_row,0),MATCH(G$1,data_column,0)) -> 0 | H31: =INDEX(data,MATCH($A31,data_row,0),MATCH(H$1,data_column,0)) -> 0 | I31: =INDEX(data,MATCH($A31,data_row,0),MATCH(I$1,data_column,0)) -> 0 | J31: =INDEX(data,MATCH($A31,data_row,0),MATCH(J$1,data_column,0)) -> 0 | K31: =INDEX(data,MATCH($A31,data_row,0),MATCH(K$1,data_column,0)) -> 0
A32: Cash flow from financing activities | B32: INR Mn | C32: =INDEX(data,MATCH($A32,data_row,0),MATCH(C$1,data_column,0)) -> -3710.6 | D32: =INDEX(data,MATCH($A32,data_row,0),MATCH(D$1,data_column,0)) -> 406.6 | E32: =INDEX(data,MATCH($A32,data_row,0),MATCH(E$1,data_column,0)) -> -7897.5 | F32: =INDEX(data,MATCH($A32,data_row,0),MATCH(F$1,data_column,0)) -> -3046.8 | G32: =INDEX(data,MATCH($A32,data_row,0),MATCH(G$1,data_column,0)) -> -3112.5078 | H32: =INDEX(data,MATCH($A32,data_row,0),MATCH(H$1,data_column,0)) -> -3485.6956 | I32: =INDEX(data,MATCH($A32,data_row,0),MATCH(I$1,data_column,0)) -> -3787.9457 | J32: =INDEX(data,MATCH($A32,data_row,0),MATCH(J$1,data_column,0)) -> -4041.6222 | K32: =INDEX(data,MATCH($A32,data_row,0),MATCH(K$1,data_column,0)) -> -4316.8267
A34: Key Ratios/ Growth rate
A36: Revenue- y-o-y growth | B36: % | C36: na | D36: =IFERROR(D6/C6-1,"na") -> 0.046064308 | E36: =IFERROR(E6/D6-1,"na") -> 0.083715076 | F36: =IFERROR(F6/E6-1,"na") -> 0.18512464 | G36: =IFERROR(G6/F6-1,"na") -> 0.069442112 | H36: =IFERROR(H6/G6-1,"na") -> 0.093550455 | I36: =IFERROR(I6/H6-1,"na") -> 0.06945365 | J36: =IFERROR(J6/I6-1,"na") -> 0.069636378 | K36: =IFERROR(K6/J6-1,"na") -> 0.069817602
A37: Gross margin | B37: % | C37: =IFERROR(C7/C$6,"na") -> 0.51833056 | D37: =IFERROR(D7/D$6,"na") -> 0.53005898 | E37: =IFERROR(E7/E$6,"na") -> 0.52560375 | F37: =IFERROR(F7/F$6,"na") -> 0.49273137 | G37: =IFERROR(G7/G$6,"na") -> 0.51 | H37: =IFERROR(H7/H$6,"na") -> 0.51 | I37: =IFERROR(I7/I$6,"na") -> 0.52 | J37: =IFERROR(J7/J$6,"na") -> 0.52 | K37: =IFERROR(K7/K$6,"na") -> 0.52
A38: EBITDA margin | B38: % | C38: =IFERROR(C8/C$6,"na") -> 0.21952155 | D38: =IFERROR(D8/D$6,"na") -> 0.22532443 | E38: =IFERROR(E8/E$6,"na") -> 0.22034171 | F38: =IFERROR(F8/F$6,"na") -> 0.1985621 | G38: =IFERROR(G8/G$6,"na") -> 0.20013138 | H38: =IFERROR(H8/H$6,"na") -> 0.19936819 | I38: =IFERROR(I8/I$6,"na") -> 0.19932611 | J38: =IFERROR(J8/J$6,"na") -> 0.19932887 | K38: =IFERROR(K8/K$6,"na") -> 0.19933409
A39: EBIT margin | B39: % | C39: =IFERROR(C9/C$6,"na") -> 0.19472758 | D39: =IFERROR(D9/D$6,"na") -> 0.20482518 | E39: =IFERROR(E9/E$6,"na") -> 0.20064728 | F39: =IFERROR(F9/F$6,"na") -> 0.18106953 | G39: =IFERROR(G9/G$6,"na") -> 0.18327507 | H39: =IFERROR(H9/H$6,"na") -> 0.18309942 | I39: =IFERROR(I9/I$6,"na") -> 0.18339259 | J39: =IFERROR(J9/J$6,"na") -> 0.18381933 | K39: =IFERROR(K9/K$6,"na") -> 0.18422817
A40: PAT margin | B40: % | C40: =IFERROR(C10/C$6,"na") -> 0.14071274 | D40: =IFERROR(D10/D$6,"na") -> 0.15311058 | E40: =IFERROR(E10/E$6,"na") -> 0.15809923 | F40: =IFERROR(F10/F$6,"na") -> 0.12877578 | G40: =IFERROR(G10/G$6,"na") -> 0.13487145 | H40: =IFERROR(H10/H$6,"na") -> 0.13402799 | I40: =IFERROR(I10/I$6,"na") -> 0.13371665 | J40: =IFERROR(J10/J$6,"na") -> 0.13352366 | K40: =IFERROR(K10/K$6,"na") -> 0.13334766
A41: Adjusted PAT margin | B41: % | C41: =IFERROR(C11/C$6,"na") -> 0.14160854 | D41: =IFERROR(D11/D$6,"na") -> 0.15414498 | E41: =IFERROR(E11/E$6,"na") -> 0.15809923 | F41: =IFERROR(F11/F$6,"na") -> 0.12877578 | G41: =IFERROR(G11/G$6,"na") -> 0.13487145 | H41: =IFERROR(H11/H$6,"na") -> 0.13402799 | I41: =IFERROR(I11/I$6,"na") -> 0.13371665 | J41: =IFERROR(J11/J$6,"na") -> 0.13352366 | K41: =IFERROR(K11/K$6,"na") -> 0.13334766
A43: Debt/Equity | B43: x | C43: =(C19+C20)/(Financials!G123+Financials!G124) -> 0.030284846 | D43: =(D19+D20)/(Financials!L123+Financials!L124) -> 0.028093497 | E43: =(E19+E20)/(Financials!Q123+Financials!Q124) -> 0.034288928 | F43: =(F19+F20)/(Financials!V123+Financials!V124) -> 0.029190181 | G43: =(G19+G20)/(Financials!AA123+Financials!AA124) -> 0.024870195 | H43: =(H19+H20)/(Financials!AF123+Financials!AF124) -> 0.021463303 | I43: =(I19+I20)/(Financials!AK123+Financials!AK124) -> 0.018745969 | J43: =(J19+J20)/(Financials!AP123+Financials!AP124) -> 0.01651206 | K43: =(K19+K20)/(Financials!AU123+Financials!AU124) -> 0.014646966
A44: Share Price | B44: INR/share | C44: 565.2 | D44: 671.4 | E44: 825.5 | F44: 1086 | G44: =rCP -> 1104 | H44: =rCP -> 1104 | I44: =rCP -> 1104 | J44: =rCP -> 1104 | K44: =rCP -> 1104
A45: Total shares outstanding | B45: Shares | C45: =INDEX(data,MATCH($A45,data_row,0),MATCH(C$1,data_column,0)) -> 512.7 | D45: =INDEX(data,MATCH($A45,data_row,0),MATCH(D$1,data_column,0)) -> 512.7 | E45: =INDEX(data,MATCH($A45,data_row,0),MATCH(E$1,data_column,0)) -> 507.8 | F45: =INDEX(data,MATCH($A45,data_row,0),MATCH(F$1,data_column,0)) -> 508 | G45: =INDEX(data,MATCH($A45,data_row,0),MATCH(G$1,data_column,0)) -> 508 | H45: =INDEX(data,MATCH($A45,data_row,0),MATCH(H$1,data_column,0)) -> 508 | I45: =INDEX(data,MATCH($A45,data_row,0),MATCH(I$1,data_column,0)) -> 508 | J45: =INDEX(data,MATCH($A45,data_row,0),MATCH(J$1,data_column,0)) -> 508 | K45: =INDEX(data,MATCH($A45,data_row,0),MATCH(K$1,data_column,0)) -> 508
A46: Market Captalization | B46: INR Mn | C46: =C44*C45 -> 289778.04 | D46: =D44*D45 -> 344226.78 | E46: =E44*E45 -> 419188.9 | F46: =F44*F45 -> 551688 | G46: =G44*G45 -> 560832 | H46: =H44*H45 -> 560832 | I46: =I44*I45 -> 560832 | J46: =J44*J45 -> 560832 | K46: =K44*K45 -> 560832
A47: Net Debt | B47: INR Mn | C47: =Financials!G100+Financials!G113-Financials!G65 -> -476.6 | D47: =Financials!L100+Financials!L113-Financials!L65 -> -24.3 | E47: =Financials!Q100+Financials!Q113-Financials!Q65 -> -410.3 | F47: =Financials!V100+Financials!V113-Financials!V65 -> -6188.2113 | G47: =Financials!AA100+Financials!AA113-Financials!AA65 -> -11888.022 | H47: =Financials!AF100+Financials!AF113-Financials!AF65 -> -17710.007 | I47: =Financials!AK100+Financials!AK113-Financials!AK65 -> -24986.363 | J47: =Financials!AP100+Financials!AP113-Financials!AP65 -> -32199.017 | K47: =Financials!AU100+Financials!AU113-Financials!AU65 -> -40162.539
A48: Minority Interest | B48: INR Mn | C48: =INDEX(data,MATCH($A48,data_row,0),MATCH(C$1,data_column,0)) -> 427.3 | D48: =INDEX(data,MATCH($A48,data_row,0),MATCH(D$1,data_column,0)) -> 1273.2 | E48: =INDEX(data,MATCH($A48,data_row,0),MATCH(E$1,data_column,0)) -> 1750.1 | F48: =INDEX(data,MATCH($A48,data_row,0),MATCH(F$1,data_column,0)) -> 1776.74 | G48: =INDEX(data,MATCH($A48,data_row,0),MATCH(G$1,data_column,0)) -> 1818.5274 | H48: =INDEX(data,MATCH($A48,data_row,0),MATCH(H$1,data_column,0)) -> 1863.9383 | I48: =INDEX(data,MATCH($A48,data_row,0),MATCH(I$1,data_column,0)) -> 1912.3902 | J48: =INDEX(data,MATCH($A48,data_row,0),MATCH(J$1,data_column,0)) -> 1964.1414 | K48: =INDEX(data,MATCH($A48,data_row,0),MATCH(K$1,data_column,0)) -> 2019.4328
A49: Investment | B49: INR Mn | C49: =Financials!G68+Financials!G86 -> 7467.9 | D49: =Financials!L68+Financials!L86 -> 14858.3 | E49: =Financials!Q68+Financials!Q86 -> 12656.3 | F49: =Financials!V68+Financials!V86 -> 12656.3 | G49: =Financials!AA68+Financials!AA86 -> 12656.3 | H49: =Financials!AF68+Financials!AF86 -> 12656.3 | I49: =Financials!AK68+Financials!AK86 -> 12656.3 | J49: =Financials!AP68+Financials!AP86 -> 12656.3 | K49: =Financials!AU68+Financials!AU86 -> 12656.3
A50: Associates | B50: INR Mn | C50: =Financials!G85 -> 0 | D50: =Financials!L85 -> 0 | E50: =Financials!Q85 -> 250.3 | F50: =Financials!V85 -> 272.7 | G50: =Financials!AA85 -> 312.7 | H50: =Financials!AF85 -> 352.7 | I50: =Financials!AK85 -> 392.7 | J50: =Financials!AP85 -> 432.7 | K50: =Financials!AU85 -> 472.7
A51: Pension Liabilities | B51: INR Mn | C51: =Financials!G115 -> 0 | D51: =Financials!L115 -> 0 | E51: =Financials!Q115 -> 0 | F51: =Financials!V115 -> 0 | G51: =Financials!AA115 -> 0 | H51: =Financials!AF115 -> 0 | I51: =Financials!AK115 -> 0 | J51: =Financials!AP115 -> 0 | K51: =Financials!AU115 -> 0
A52: Other Obligations | B52: INR Mn | C52: =Financials!G114 -> 292.7 | D52: =Financials!L114 -> 327.8 | E52: =Financials!Q114 -> 381.7 | F52: =Financials!V114 -> 381.7 | G52: =Financials!AA114 -> 381.7 | H52: =Financials!AF114 -> 381.7 | I52: =Financials!AK114 -> 381.7 | J52: =Financials!AP114 -> 381.7 | K52: =Financials!AU114 -> 381.7
A53: Enterprise Valuation (EV) | B53: INR Mn | C53: =C46+C47+C48-C49-C50+C51+C52 -> 282553.54 | D53: =D46+D47+D48-D49-D50+D51+D52 -> 330945.18 | E53: =E46+E47+E48-E49-E50+E51+E52 -> 408003.8 | F53: =F46+F47+F48-F49-F50+F51+F52 -> 534729.23 | G53: =G46+G47+G48-G49-G50+G51+G52 -> 538175.21 | H53: =H46+H47+H48-H49-H50+H51+H52 -> 532358.63 | I53: =I46+I47+I48-I49-I50+I51+I52 -> 525090.73 | J53: =J46+J47+J48-J49-J50+J51+J52 -> 517889.82 | K53: =K46+K47+K48-K49-K50+K51+K52 -> 509941.59
A54: EV/EBITDA | B54: x | C54: =C53/C8 -> 23.971421 | D54: =D53/D8 -> 26.149271 | E54: =E53/E8 -> 30.420349 | F54: =F53/F8 -> 37.331052 | G54: =G53/G8 -> 34.856509 | H54: =H53/H8 -> 31.650822 | I54: =I53/I8 -> 29.197439 | J54: =J53/J8 -> 26.921894 | K54: =K53/K8 -> 24.778075
A55: PE | B55: x | C55: =C44/C12 -> 38.110637 | D55: =D44/D12 -> 39.77159 | E55: =E44/E12 -> 43.878411 | F55: =F44/F12 -> 59.378319 | G55: =G44/G12 -> 53.899922 | H55: =H44/H12 -> 49.599106 | I55: =I44/I12 -> 46.485968 | J55: =J44/J12 -> 43.522415 | K55: =K44/K12 -> 40.735784

Sheet Financials
A1: Financials | C1: 1Q2016 | D1: 2Q2016 | E1: 3Q2016 | F1: 4Q2016 | G1: FY2016 | H1: 1Q2017 | I1: 2Q2017 | J1: 3Q2017 | K1: 4Q2017 | L1: FY2017 | M1: 1Q2018 | N1: 2Q2018 | O1: 3Q2018 | P1: 4Q2018 | Q1: FY2018 | R1: 1Q2019 | S1: 2Q2019 | T1: 3Q2019 | U1: 4Q2019 | V1: FY2019 | W1: 1Q2020 | X1: 2Q2020 | Y1: 3Q2020 | Z1: 4Q2020 | AA1: FY2020 | AB1: 1Q2021 | AC1: 2Q2021 | AD1: 3Q2021 | AE1: 4Q2021 | AF1: FY2021 | AG1: 1Q2022 | AH1: 2Q2022 | AI1: 3Q2022 | AJ1: 4Q2022 | AK1: FY2022 | AL1: 1Q2023 | AM1: 2Q2023 | AN1: 3Q2023 | AO1: 4Q2023 | AP1: FY2023 | AQ1: 1Q2024 | AR1: 2Q2024 | AS1: 3Q2024 | AT1: 4Q2024 | AU1: FY2024
C2: 42185 | D2: 42277 | E2: 42369 | F2: 42460 | G2: 42460 | H2: 42551 | I2: 42643 | J2: 42735 | K2: 42825 | L2: 42825 | M2: 42916 | N2: 43008 | O2: 43100 | P2: 43190 | Q2: 43190 | R2: 43281 | S2: 43373 | T2: 43465 | U2: 43555 | V2: 43555 | W2: 43646 | X2: 43738 | Y2: 43830 | Z2: 43921 | AA2: 43921 | AB2: 44012 | AC2: 44104 | AD2: 44196 | AE2: 44286 | AF2: 44286 | AG2: 44377 | AH2: 44469 | AI2: 44561 | AJ2: 44651 | AK2: 44651 | AL2: 44742 | AM2: 44834 | AN2: 44926 | AO2: 45016 | AP2: 45016 | AQ2: 45107 | AR2: 45199 | AS2: 45291 | AT2: 45382 | AU2: 45382
C3: A | D3: A | E3: A | F3: A | G3: A | H3: A | I3: A | J3: A | K3: A | L3: A | M3: A | N3: A | O3: A | P3: A | Q3: A | R3: A | S3: A | T3: A | U3: F | V3: F | W3: F | X3: F | Y3: F | Z3: F | AA3: F | AB3: F | AC3: F | AD3: F | AE3: F | AF3: F | AG3: F | AH3: F | AI3: F | AJ3: F | AK3: F | AL3: F | AM3: F | AN3: F | AO3: F | AP3: F | AQ3: F | AR3: F | AS3: F | AT3: F | AU3: F
A5: No. of days | C5: 91 | D5: =D2-C2 -> 92 | E5: =E2-D2 -> 92 | F5: =F2-E2 -> 91 | G5: =SUM(C5:F5) -> 366 | H5: =H2-F2 -> 91 | I5: =I2-H2 -> 92 | J5: =J2-I2 -> 92 | K5: =K2-J2 -> 90 | L5: =SUM(H5:K5) -> 365 | M5: =M2-K2 -> 91 | N5: =N2-M2 -> 92 | O5: =O2-N2 -> 92 | P5: =P2-O2 -> 90 | Q5: =SUM(M5:P5) -> 365 | R5: =R2-P2 -> 91 | S5: =S2-R2 -> 92 | T5: =T2-S2 -> 92 | U5: =U2-T2 -> 90 | V5: =SUM(R5:U5) -> 365 | W5: =W2-U2 -> 91 | X5: =X2-W2 -> 92 | Y5: =Y2-X2 -> 92 | Z5: =Z2-Y2 -> 91 | AA5: =SUM(W5:Z5) -> 366 | AB5: =AB2-Z2 -> 91 | AC5: =AC2-AB2 -> 92 | AD5: =AD2-AC2 -> 92 | AE5: =AE2-AD2 -> 90 | AF5: =SUM(AB5:AE5) -> 365 | AG5: =AG2-AE2 -> 91 | AH5: =AH2-AG2 -> 92 | AI5: =AI2-AH2 -> 92 | AJ5: =AJ2-AI2 -> 90 | AK5: =SUM(AG5:AJ5) -> 365 | AL5: =AL2-AJ2 -> 91 | AM5: =AM2-AL2 -> 92 | AN5: =AN2-AM2 -> 92 | AO5: =AO2-AN2 -> 90 | AP5: =SUM(AL5:AO5) -> 365 | AQ5: =AQ2-AO2 -> 91 | AR5: =AR2-AQ2 -> 92 | AS5: =AS2-AR2 -> 92 | AT5: =AT2-AS2 -> 91 | AU5: =SUM(AQ5:AT5) -> 366
A7: Income Statement
A9: Revenue | B9: INR Mn | C9: =C11+C12+C13 -> 14694.6 | D9: =D11+D12+D13 -> 13200.6 | E9: =E11+E12+E13 -> 13390.8 | F9: =F11+F12+F13 -> 12408.5 | G9: =G11+G12+G13 -> 53694.5 | H9: =H11+H12+H13 -> 15693.7 | I9: =I11+I12+I13 -> 14176.8 | J9: =J11+J12+J13 -> 13343.5 | ... T9: =T11+T12+T13 -> 18483 | U9: ='Operational Drivers'!U6 -> 17740.437 | V9: =R9+S9+T9+U9 -> 72138.537 | W9: ='Operational Drivers'!W6 -> 19611.711 | X9: ='Operational Drivers'!X6 -> 18792.306 | Y9: ='Operational Drivers'!Y6 -> 19763.872 | Z9: ='Operational Drivers'!Z6 -> 18980.101 | AA9: =W9+X9+Y9+Z9 -> 77147.989 | AB9: ='Operational Drivers'!AB6 -> 21442.956 | AC9: ='Operational Drivers'!AC6 -> 20547.039 | AD9: ='Operational Drivers'!AD6 -> 21609.326 | AE9: ='Operational Drivers'!AE6 -> 20765.898 | AF9: =AB9+AC9+AD9+AE9 -> 84365.219 | AG9: ='Operational Drivers'!AG6 -> 22930.754 | AH9: ='Operational Drivers'!AH6 -> 21972.675 | AI9: ='Operational Drivers'!AI6 -> 23108.667 | AJ9: ='Operational Drivers'!AJ6 -> 22212.595 | AK9: =AG9+AH9+AI9+AJ9 -> 90224.691 | AL9: ='Operational Drivers'!AL6 -> 24525.984 | AM9: ='Operational Drivers'!AM6 -> 23501.254 | AN9: ='Operational Drivers'!AN6 -> 24716.274 | AO9: ='Operational Drivers'!AO6 -> 23764.1 | AP9: =AL9+AM9+AN9+AO9 -> 96507.612 | AQ9: ='Operational Drivers'!AQ6 -> 26236.648 | AR9: ='Operational Drivers'!AR6 -> 25140.444 | AS9: ='Operational Drivers'!AS6 -> 26440.21 | AT9: ='Operational Drivers'!AT6 -> 25428.239 | AU9: =AQ9+AR9+AS9+AT9 -> 103245.54
A10: y-o-y growth | B10: % | C10: na | D10: na | E10: na | F10: na | G10: na | H10: =IFERROR(H9/C9-1,"na") -> 0.067990963 | I10: =IFERROR(I9/D9-1,"na") -> 0.073951184 | J10: =IFERROR(J9/E9-1,"na") -> -0.0035322759 | K10: =IFERROR(K9/F9-1,"na") -> 0.043953741 | L10: =IFERROR(L9/G9-1,"na") -> 0.046064308 | M10: =IFERROR(M9/H9-1,"na") -> -0.025774674 | N10: =IFERROR(N9/I9-1,"na") -> 0.079136335 | O10: =IFERROR(O9/J9-1,"na") -> 0.15629333 | ... AU10: =IFERROR(AU9/AP9-1,"na") -> 0.069817602
A11: Revenue from operations | B11: INR Mn | C11: 14621.5 | D11: 13134.4 | E11: 13323.2 | F11: 12334.7 | G11: =C11+D11+E11+F11 -> 53413.8 | H11: 16838.2 | I11: 15220.4 | J11: 14308.8 | K11: 14043.2 | L11: =H11+I11+J11+K11 -> 60410.6 | M11: 16692.7 | N11: 15298.7 | O11: 15429 | P11: 14853.1 | Q11: =M11+N11+O11+P11 -> 62273.5 | R11: 18340.7 | S11: 17574.4 | T11: 18483
A12: Excise duty | B12: INR Mn | C12: 0 | D12: 0 | E12: 0 | F12: 0 | G12: =C12+D12+E12+F12 -> 0 | H12: -1219.4 | I12: -1118.3 | J12: -1028.2 | K12: -1089.3 | L12: =H12+I12+J12+K12 -> -4455.2 | M12: -1403.5 | N12: 0 | O12: 0 | P12: 0 | Q12: =M12+N12+O12+P12 -> -1403.5 | R12: 0 | S12: 0 | T12: 0
A13: Other operating income | B13: INR Mn | C13: 73.1 | D13: 66.2 | E13: 67.6 | F13: 73.8 | G13: =C13+D13+E13+F13 -> 280.7 | H13: 74.9 | I13: 74.7 | J13: 62.9 | K13: 0 | L13: =H13+I13+J13+K13 -> 212.5 | Q13: =M13+N13+O13+P13 -> 0
A14: Cost of Goods Sold | B14: INR Mn | C14: =C16+C17+C18 -> -7486.4 | D14: =D16+D17+D18 -> -6354.5 | E14: =E16+E17+E18 -> -6474.5 | F14: =F16+F17+F18 -> -5547.6 | G14: =G16+G17+G18 -> -25863 | H14: =H16+H17+H18 -> -7479.1 | I14: =I16+I17+I18 -> -6597.9 | J14: =J16+J17+J18 -> -6245.8 | ... T14: =T16+T17+T18 -> -9752 | U14: =-IFERROR(U9*U15,"na") -> -8876.2167 | V14: =R14+S14+T14+U14 -> -36593.617 | W14: =-IFERROR(W9*W15,"na") -> -9609.7381 | X14: =-IFERROR(X9*X15,"na") -> -9208.2299 | Y14: =-IFERROR(Y9*Y15,"na") -> -9684.2972 | Z14: =-IFERROR(Z9*Z15,"na") -> -9300.2496 | AA14: =W14+X14+Y14+Z14 -> -37802.515 | AB14: =-IFERROR(AB9*AB15,"na") -> -10507.048 | AC14: =-IFERROR(AC9*AC15,"na") -> -10068.049 | AD14: =-IFERROR(AD9*AD15,"na") -> -10588.57 | AE14: =-IFERROR(AE9*AE15,"na") -> -10175.29 | AF14: =AB14+AC14+AD14+AE14 -> -41338.957 | AG14: =-IFERROR(AG9*AG15,"na") -> -11006.762 | AH14: =-IFERROR(AH9*AH15,"na") -> -10546.884 | AI14: =-IFERROR(AI9*AI15,"na") -> -11092.16 | AJ14: =-IFERROR(AJ9*AJ15,"na") -> -10662.046 | AK14: =AG14+AH14+AI14+AJ14 -> -43307.852 | AL14: =-IFERROR(AL9*AL15,"na") -> -11772.472 | AM14: =-IFERROR(AM9*AM15,"na") -> -11280.602 | AN14: =-IFERROR(AN9*AN15,"na") -> -11863.811 | AO14: =-IFERROR(AO9*AO15,"na") -> -11406.768 | AP14: =AL14+AM14+AN14+AO14 -> -46323.654 | AQ14: =-IFERROR(AQ9*AQ15,"na") -> -12593.591 | AR14: =-IFERROR(AR9*AR15,"na") -> -12067.413 | AS14: =-IFERROR(AS9*AS15,"na") -> -12691.301 | AT14: =-IFERROR(AT9*AT15,"na") -> -12205.555 | AU14: =AQ14+AR14+AS14+AT14 -> -49557.86
A15: as a % of sales | B15: % | C15: =IFERROR(-C14/C9,"na") -> 0.50946606 | D15: =IFERROR(-D14/D9,"na") -> 0.48137963 | E15: =IFERROR(-E14/E9,"na") -> 0.4835036 | F15: =IFERROR(-F14/F9,"na") -> 0.44708063 | G15: =IFERROR(-G14/G9,"na") -> 0.48166944 | H15: =IFERROR(-H14/H9,"na") -> 0.47656703 | I15: =IFERROR(-I14/I9,"na") -> 0.46540122 | J15: =IFERROR(-J14/J9,"na") -> 0.46807809 | ... T15: =IFERROR(-T14/T9,"na") -> 0.52761998 | U15: =MEDIAN(P15,R15:T15) -> 0.50033811 | V15: =IFERROR(-V14/V9,"na") -> 0.50726863 | W15: 0.49 | X15: =W15 -> 0.49 | Y15: =X15 -> 0.49 | Z15: =Y15 -> 0.49 | AA15: =IFERROR(-AA14/AA9,"na") -> 0.49 | AB15: =MEDIAN(W15:Z15) -> 0.49 | AC15: =MEDIAN(X15:Z15,AB15) -> 0.49 | AD15: =MEDIAN(Y15:Z15,AB15:AC15) -> 0.49 | AE15: =MEDIAN(Z15,AB15:AD15) -> 0.49 | AF15: =IFERROR(-AF14/AF9,"na") -> 0.49 | AG15: 0.48 | AH15: =AG15 -> 0.48 | AI15: =AH15 -> 0.48 | AJ15: =AI15 -> 0.48 | AK15: =IFERROR(-AK14/AK9,"na") -> 0.48 | AL15: =MEDIAN(AG15:AJ15) -> 0.48 | AM15: =MEDIAN(AH15:AJ15,AL15) -> 0.48 | AN15: =MEDIAN(AI15:AJ15,AL15:AM15) -> 0.48 | AO15: =MEDIAN(AJ15,AL15:AN15) -> 0.48 | AP15: =IFERROR(-AP14/AP9,"na") -> 0.48 | AQ15: =MEDIAN(AL15:AO15) -> 0.48 | AR15: =MEDIAN(AM15:AO15,AQ15) -> 0.48 | AS15: =MEDIAN(AN15:AO15,AQ15:AR15) -> 0.48 | AT15: =MEDIAN(AO15,AQ15:AS15) -> 0.48 | AU15: =IFERROR(-AU14/AU9,"na") -> 0.48
A16: Cost of materials consumed | B16: INR Mn | C16: -6111.3 | D16: -6016.7 | E16: -5513.6 | F16: -5344.6 | G16: =C16+D16+E16+F16 -> -22986.2 | H16: -5853.4 | I16: -5485.6 | J16: -5231.4 | K16: -6133.9 | L16: =H16+I16+J16+K16 -> -22704.3 | M16: -6455.4 | N16: -5519.1 | O16: -6702.8 | P16: -6972.9 | Q16: =M16+N16+O16+P16 -> -25650.2 | R16: -7917.7 | S16: -8083.4 | T16: -8705.2
A17: Purchases of stock-in-trade | B17: INR Mn | C17: -584.1 | D17: -639 | E17: -658.8 | F17: -778 | G17: =C17+D17+E17+F17 -> -2659.9 | H17: -1046.6 | I17: -1082.8 | J17: -992.7 | K17: -876.5 | L17: =H17+I17+J17+K17 -> -3998.6 | M17: -862.4 | N17: -865.4 | O17: -629.3 | P17: -831.5 | Q17: =M17+N17+O17+P17 -> -3188.6 | R17: -1054.6 | S17: -991.3 | T17: -1147.6
A18: Change in inventories of FG, WIP, and SIT | B18: INR Mn | C18: -791 | D18: 301.2 | E18: -302.1 | F18: 575 | G18: =C18+D18+E18+F18 -> -216.9 | H18: -579.1 | I18: -29.5 | J18: -21.7 | K18: 937.6 | L18: =H18+I18+J18+K18 -> 307.3 | M18: -63.3 | N18: -805.3 | O18: 145.7 | P18: 685.2 | Q18: =M18+N18+O18+P18 -> -37.7 | R18: -101.5 | S18: 183.1 | T18: 100.8
A19: Gross Profit | B19: INR Mn | C19: =C9+C14 -> 7208.2 | D19: =D9+D14 -> 6846.1 | E19: =E9+E14 -> 6916.3 | F19: =F9+F14 -> 6860.9 | G19: =G9+G14 -> 27831.5 | H19: =H9+H14 -> 8214.6 | I19: =I9+I14 -> 7578.9 | J19: =J9+J14 -> 7097.7 | ... AU19: =AU9+AU14 -> 53687.682
A20: gross margin | B20: % | C20: =IFERROR(C19/C9,"na") -> 0.49053394 | D20: =IFERROR(D19/D9,"na") -> 0.51862037 | E20: =IFERROR(E19/E9,"na") -> 0.5164964 | F20: =IFERROR(F19/F9,"na") -> 0.55291937 | G20: =IFERROR(G19/G9,"na") -> 0.51833056 | H20: =IFERROR(H19/H9,"na") -> 0.52343297 | I20: =IFERROR(I19/I9,"na") -> 0.53459878 | J20: =IFERROR(J19/J9,"na") -> 0.53192191 | ... AU20: =IFERROR(AU19/AU9,"na") -> 0.52
A21: Selling, General & Administration | B21: INR Mn | C21: -1423 | D21: -1393.3 | E21: -1441.7 | F21: -1485.4 | G21: =C21+D21+E21+F21 -> -5743.4 | H21: -1625.2 | I21: -1562.4 | J21: -1652.6 | K21: -1612.5 | L21: =H21+I21+J21+K21 -> -6452.7 | M21: -1809.2 | N21: -1837 | O21: -1743.3 | P21: -1734.5 | Q21: =M21+N21+O21+P21 -> -7124 | R21: -2071 | S21: -2037 | T21: -2087.4 | U21: =IFERROR((P21*(1+U22)),"na") -> -1954.4155 | V21: =R21+S21+T21+U21 -> -8149.8155 | W21: =IFERROR((R21*(1+W22)),"na") -> -2352.1319 | X21: =IFERROR((S21*(1+X22)),"na") -> -2304.3928 | Y21: =IFERROR((T21*(1+Y22)),"na") -> -2366.0834 | Z21: =IFERROR((U21*(1+Z22)),"na") -> -2213.1561 | AA21: =W21+X21+Y21+Z21 -> -9235.7643 | AB21: =IFERROR((W21*(1+AB22)),"na") -> -2664.8421 | AC21: =IFERROR((X21*(1+AC22)),"na") -> -2610.1112 | AD21: =IFERROR((Y21*(1+AD22)),"na") -> -2680.3173 | AE21: =IFERROR((Z21*(1+AE22)),"na") -> -2506.9252 | AF21: =AB21+AC21+AD21+AE21 -> -10462.196 | AG21: =IFERROR((AB21*(1+AG22)),"na") -> -3018.6601 | AH21: =IFERROR((AC21*(1+AH22)),"na") -> -2956.6168 | AI21: =IFERROR((AD21*(1+AI22)),"na") -> -3036.1666 | AJ21: =IFERROR((AE21*(1+AJ22)),"na") -> -2839.7433 | AK21: =AG21+AH21+AI21+AJ21 -> -11851.187 | AL21: =IFERROR((AG21*(1+AL22)),"na") -> -3419.4225 | AM21: =IFERROR((AH21*(1+AM22)),"na") -> -3349.139 | AN21: =IFERROR((AI21*(1+AN22)),"na") -> -3439.2515 | AO21: =IFERROR((AJ21*(1+AO22)),"na") -> -3216.75 | AP21: =AL21+AM21+AN21+AO21 -> -13424.563 | AQ21: =IFERROR((AL21*(1+AQ22)),"na") -> -3873.3885 | AR21: =IFERROR((AM21*(1+AR22)),"na") -> -3793.7738 | AS21: =IFERROR((AN21*(1+AS22)),"na") -> -3895.8498 | AT21: =IFERROR((AO21*(1+AT22)),"na") -> -3643.8088 | AU21: =AQ21+AR21+AS21+AT21 -> -15206.821
A22: y-o-y growth | B22: % | C22: na | D22: na | E22: na | F22: na | G22: na | H22: =IFERROR(H21/C21-1,"na") -> 0.14209417 | I22: =IFERROR(I21/D21-1,"na") -> 0.12136654 | J22: =IFERROR(J21/E21-1,"na") -> 0.14628564 | K22: =IFERROR(K21/F21-1,"na") -> 0.085566177 | L22: =IFERROR(L21/G21-1,"na") -> 0.12349828 | M22: =IFERROR(M21/H21-1,"na") -> 0.11321683 | N22: =IFERROR(N21/I21-1,"na") -> 0.17575525 | O22: =IFERROR(O21/J21-1,"na") -> 0.054883214 | ... T22: =IFERROR(T21/O21-1,"na") -> 0.19738427 | U22: =MEDIAN(P22,R22:T22) -> 0.126789 | V22: =IFERROR(V21/Q21-1,"na") -> 0.14399432 | W22: =MEDIAN(R22:U22) -> 0.13574692 | X22: =MEDIAN(S22:U22,W22) -> 0.13126796 | Y22: =MEDIAN(T22:U22,W22:X22) -> 0.13350744 | Z22: =MEDIAN(U22,W22:Y22) -> 0.1323877 | AA22: =IFERROR(AA21/V21-1,"na") -> 0.13324826 | AB22: =MEDIAN(W22:Z22) -> 0.13294757 | AC22: =MEDIAN(X22:Z22,AB22) -> 0.13266764 | AD22: =MEDIAN(Y22:Z22,AB22:AC22) -> 0.1328076 | AE22: =MEDIAN(Z22,AB22:AD22) -> 0.13273762 | AF22: =IFERROR(AF21/AA21-1,"na") -> 0.13279156 | AG22: =MEDIAN(AB22:AE22) -> 0.13277261 | AH22: =MEDIAN(AC22:AE22,AG22) -> 0.13275512 | AI22: =MEDIAN(AD22:AE22,AG22:AH22) -> 0.13276386 | AJ22: =MEDIAN(AE22,AG22:AI22) -> 0.13275949 | AK22: =IFERROR(AK21/AF21-1,"na") -> 0.13276286 | AL22: =MEDIAN(AG22:AJ22) -> 0.13276168 | AM22: =MEDIAN(AH22:AJ22,AL22) -> 0.13276058 | AN22: =MEDIAN(AI22:AJ22,AL22:AM22) -> 0.13276113 | AO22: =MEDIAN(AJ22,AL22:AN22) -> 0.13276086 | AP22: =IFERROR(AP21/AK21-1,"na") -> 0.13276107 | AQ22: =MEDIAN(AL22:AO22) -> 0.13276099 | AR22: =MEDIAN(AM22:AO22,AQ22) -> 0.13276093 | AS22: =MEDIAN(AN22:AO22,AQ22:AR22) -> 0.13276096 | AT22: =MEDIAN(AO22,AQ22:AS22) -> 0.13276094 | AU22: =IFERROR(AU21/AP21-1,"na") -> 0.13276096
A23: Other operating expense | B23: INR Mn | C23: -2348.3 | D23: -2438.9 | E23: -2522 | F23: -2991.8 | G23: =C23+D23+E23+F23 -> -10301 | H23: -2646.1 | I23: -2791.1 | J23: -2536.3 | K23: -2690.1 | L23: =H23+I23+J23+K23 -> -10663.6 | M23: -2889.1 | N23: -2511.3 | O23: -2796.8 | P23: -3260.1 | Q23: =M23+N23+O23+P23 -> -11457.3 | R23: -3379.3 | S23: -2997.4 | T23: -3276.1 | U23: =U24-U19-U21 -> -3418.3253 | V23: =R23+S23+T23+U23 -> -13071.125 | W23: =W24-W19-W21 -> -3667.7974 | X23: =X24-X19-X21 -> -3522.5833 | Y23: =Y24-Y19-Y21 -> -3792.7991 | Z23: =Z24-Z19-Z21 -> -3686.7973 | AA23: =W23+X23+Y23+Z23 -> -14669.977 | AB23: =AB24-AB19-AB21 -> -3992.0872 | AC23: =AC24-AC19-AC21 -> -3772.7624 | AD23: =AD24-AD19-AD21 -> -4034.5504 | AE23: =AE24-AE19-AE21 -> -3944.9246 | AF23: =AB23+AC23+AD23+AE23 -> -15744.325 | AG23: =AG24-AG19-AG21 -> -4334.34 | AH23: =AH24-AH19-AH21 -> -4089.5154 | AI23: =AI24-AI19-AI21 -> -4374.2891 | AJ23: =AJ24-AJ19-AJ21 -> -4283.3715 | AK23: =AG23+AH23+AI23+AJ23 -> -17081.516 | AL23: =AL24-AL19-AL21 -> -4445.302 | AM23: =AM24-AM19-AM21 -> -4187.0878 | AN23: =AN24-AN19-AN21 -> -4486.5057 | AO23: =AO24-AO19-AO21 -> -4403.7467 | AP23: =AL23+AM23+AN23+AO23 -> -17522.642 | AQ23: =AQ24-AQ19-AQ21 -> -4539.7761 | AR23: =AR24-AR19-AR21 -> -4267.9618 | AS23: =AS24-AS19-AS21 -> -4582.5763 | AT23: =AT24-AT19-AT21 -> -4510.1908 | AU23: =AQ23+AR23+AS23+AT23 -> -17900.505
A24: EBITDA | B24: INR Mn | C24: =C19+C21+C23 -> 3436.9 | D24: =D19+D21+D23 -> 3013.9 | E24: =E19+E21+E23 -> 2952.6 | F24: =F19+F21+F23 -> 2383.7 | G24: =G19+G21+G23 -> 11787.1 | H24: =H19+H21+H23 -> 3943.3 | I24: =I19+I21+I23 -> 3225.4 | J24: =J19+J21+J23 -> 2908.8 | ... T24: =T19+T21+T23 -> 3367.5 | U24: ='Operational Drivers'!U43 -> 3491.4796 | V24: =R24+S24+T24+U24 -> 14323.98 | W24: ='Operational Drivers'!W43 -> 3982.0431 | X24: ='Operational Drivers'!X43 -> 3757.0999 | Y24: ='Operational Drivers'!Y43 -> 3920.6921 | Z24: ='Operational Drivers'!Z43 -> 3779.8981 | AA24: =W24+X24+Y24+Z24 -> 15439.733 | AB24: ='Operational Drivers'!AB43 -> 4278.9783 | AC24: ='Operational Drivers'!AC43 -> 4096.1165 | AD24: ='Operational Drivers'!AD43 -> 4305.8883 | AE24: ='Operational Drivers'!AE43 -> 4138.7581 | AF24: =AB24+AC24+AD24+AE24 -> 16819.741 | AG24: ='Operational Drivers'!AG43 -> 4570.9919 | AH24: ='Operational Drivers'!AH43 -> 4379.6588 | AI24: ='Operational Drivers'!AI43 -> 4606.051 | AJ24: ='Operational Drivers'!AJ43 -> 4427.4348 | AK24: =AG24+AH24+AI24+AJ24 -> 17984.137 | AL24: ='Operational Drivers'!AL43 -> 4888.7871 | AM24: ='Operational Drivers'!AM43 -> 4684.4253 | AN24: ='Operational Drivers'!AN43 -> 4926.7051 | AO24: ='Operational Drivers'!AO43 -> 4736.8354 | AP24: =AL24+AM24+AN24+AO24 -> 19236.753 | AQ24: ='Operational Drivers'!AQ43 -> 5229.8924 | AR24: ='Operational Drivers'!AR43 -> 5011.2955 | AS24: ='Operational Drivers'!AS43 -> 5270.4832 | AT24: ='Operational Drivers'!AT43 -> 5068.6848 | AU24: =AQ24+AR24+AS24+AT24 -> 20580.356
A25: y-o-y growth | B25: % | C25: na | D25: na | E25: na | F25: na | G25: na | H25: =IFERROR(H24/C24-1,"na") -> 0.14734208 | I25: =IFERROR(I24/D24-1,"na") -> 0.070174856 | J25: =IFERROR(J24/E24-1,"na") -> -0.014834383 | K25: =IFERROR(K24/F24-1,"na") -> 0.081721693 | L25: =IFERROR(L24/G24-1,"na") -> 0.073716181 | M25: =IFERROR(M24/H24-1,"na") -> -0.18601172 | N25: =IFERROR(N24/I24-1,"na") -> 0.16593291 | O25: =IFERROR(O24/J24-1,"na") -> 0.27286166 | ... AU25: =IFERROR(AU24/AP24-1,"na") -> 0.069845626
A26: EBITDA margin | B26: % | C26: =IFERROR(C24/C9,"na") -> 0.23388864 | D26: =IFERROR(D24/D9,"na") -> 0.22831538 | E26: =IFERROR(E24/E9,"na") -> 0.22049467 | F26: =IFERROR(F24/F9,"na") -> 0.19210219 | G26: =IFERROR(G24/G9,"na") -> 0.21952155 | H26: =IFERROR(H24/H9,"na") -> 0.25126643 | I26: =IFERROR(I24/I9,"na") -> 0.22751256 | J26: =IFERROR(J24/J9,"na") -> 0.21799378 | ... AU26: =IFERROR(AU24/AU9,"na") -> 0.19933409
A27: Depreciation & Amortization | B27: INR Mn | C27: -321.4 | D27: -328.9 | E27: -330.1 | F27: -350.9 | G27: =C27+D27+E27+F27 -> -1331.3 | H27: -257.5 | I27: -302.9 | J27: -295.1 | K27: -295.9 | L27: =H27+I27+J27+K27 -> -1151.4 | M27: -312.6 | N27: -296.1 | O27: -292.4 | P27: -297.7 | Q27: =M27+N27+O27+P27 -> -1198.8 | R27: -301.1 | S27: -315.8 | T27: -320.9 | U27: =IFERROR((S82+S91)*U28*0.25,"na") -> -324.08872 | V27: =R27+S27+T27+U27 -> -1261.8887 | W27: =IFERROR((V82+V91)*W28*0.25,"na") -> -323.8546 | X27: =IFERROR((V82+V91)*X28*0.25,"na") -> -326.09379 | Y27: =IFERROR((V82+V91)*Y28*0.25,"na") -> -325.04936 | Z27: =IFERROR((V82+V91)*Z28*0.25,"na") -> -325.43241 | AA27: =W27+X27+Y27+Z27 -> -1300.4302 | AB27: =IFERROR((AA82+AA91)*AB28*0.25,"na") -> -342.95717 | AC27: =IFERROR((AA82+AA91)*AC28*0.25,"na") -> -343.2876 | AD27: =IFERROR((AA82+AA91)*AD28*0.25,"na") -> -343.11011 | AE27: =IFERROR((AA82+AA91)*AE28*0.25,"na") -> -343.16369 | AF27: =AB27+AC27+AD27+AE27 -> -1372.5186 | AG27: =IFERROR((AF82+AF91)*AG28*0.25,"na") -> -359.37814 | AH27: =IFERROR((AF82+AF91)*AH28*0.25,"na") -> -359.4233 | AI27: =IFERROR((AF82+AF91)*AI28*0.25,"na") -> -359.39323 | AJ27: =IFERROR((AF82+AF91)*AJ28*0.25,"na") -> -359.40212 | AK27: =AG27+AH27+AI27+AJ27 -> -1437.5968 | AL27: =IFERROR((AK82+AK91)*AL28*0.25,"na") -> -374.19502 | AM27: =IFERROR((AK82+AK91)*AM28*0.25,"na") -> -374.2005 | AN27: =IFERROR((AK82+AK91)*AN28*0.25,"na") -> -374.1956 | AO27: =IFERROR((AK82+AK91)*AO28*0.25,"na") -> -374.19729 | AP27: =AL27+AM27+AN27+AO27 -> -1496.7884 | AQ27: =IFERROR((AP82+AP91)*AQ28*0.25,"na") -> -389.90453 | AR27: =IFERROR((AP82+AP91)*AR28*0.25,"na") -> -389.90507 | AS27: =IFERROR((AP82+AP91)*AS28*0.25,"na") -> -389.90432 | AT27: =IFERROR((AP82+AP91)*AT28*0.25,"na") -> -389.90466 | AU27: =AQ27+AR27+AS27+AT27 -> -1559.6186
A28: as a % of fixed and intangible assets | B28: % | C28: na | D28: na | E28: =IFERROR(E27*4/(D82+D91),"na") -> -0.089292235 | F28: =IFERROR(F27*4/(D82+D91),"na") -> -0.094918647 | G28: na | H28: =IFERROR(H27*4/(F82+F91),"na") -> -0.068325948 | I28: =IFERROR(I27*4/(F82+F91),"na") -> -0.080372542 | J28: =IFERROR(J27*4/(I82+I91),"na") -> -0.084914143 | K28: =IFERROR(K27*4/(I82+I91),"na") -> -0.085144341 | L28: =IFERROR(L27/(G82+G91),"na") -> -0.076379123 | M28: =IFERROR(M27*4/(K82+K91),"na") -> -0.096995648 | N28: =IFERROR(N27*4/(K82+K91),"na") -> -0.091875916 | O28: =IFERROR(O27*4/(N82+N91),"na") -> -0.091249532 | P28: =IFERROR(P27*4/(N82+N91),"na") -> -0.092903508 | Q28: =IFERROR(Q27/(L82+L91),"na") -> -0.092992949 | R28: =IFERROR(R27*4/(P82+P91),"na") -> -0.086491921 | S28: =IFERROR(S27*4/(P82+P91),"na") -> -0.090714542 | T28: =IFERROR(T27*4/(S82+S91),"na") -> -0.088859352 | U28: =AVERAGE(P28,R28,S28,T28) -> -0.089742331 | V28: =IFERROR(V27/(Q82+Q91),"na") -> -0.090620375 | W28: =AVERAGE(R28,T28,U28,S28) -> -0.088952037 | X28: =AVERAGE(S28,U28,W28,T28) -> -0.089567065 | Y28: =AVERAGE(T28,W28,X28,U28) -> -0.089280196 | Z28: =AVERAGE(U28,X28,Y28,W28) -> -0.089385407 | AA28: =IFERROR(AA27/(V82+V91),"na") -> -0.089296176 | AB28: =AVERAGE(W28,Y28,Z28,X28) -> -0.089296176 | AC28: =AVERAGE(X28,Z28,AB28,Y28) -> -0.089382211 | AD28: =AVERAGE(Y28,AB28,AC28,Z28) -> -0.089335998 | AE28: =AVERAGE(Z28,AC28,AD28,AB28) -> -0.089349948 | AF28: =IFERROR(AF27/(AA82+AA91),"na") -> -0.089341083 | AG28: =AVERAGE(AB28,AD28,AE28,AC28) -> -0.089341083 | AH28: =AVERAGE(AC28,AE28,AG28,AD28) -> -0.08935231 | AI28: =AVERAGE(AD28,AG28,AH28,AE28) -> -0.089344835 | AJ28: =AVERAGE(AE28,AH28,AI28,AG28) -> -0.089347044 | AK28: =IFERROR(AK27/(AF82+AF91),"na") -> -0.089346318 | AL28: =AVERAGE(AG28,AI28,AJ28,AH28) -> -0.089346318 | AM28: =AVERAGE(AH28,AJ28,AL28,AI28) -> -0.089347627 | AN28: =AVERAGE(AI28,AL28,AM28,AJ28) -> -0.089346456 | AO28: =AVERAGE(AJ28,AM28,AN28,AL28) -> -0.089346861 | AP28: =IFERROR(AP27/(AK82+AK91),"na") -> -0.089346816 | AQ28: =AVERAGE(AL28,AN28,AO28,AM28) -> -0.089346816 | AR28: =AVERAGE(AM28,AO28,AQ28,AN28) -> -0.08934694 | AS28: =AVERAGE(AN28,AQ28,AR28,AO28) -> -0.089346768 | AT28: =AVERAGE(AO28,AR28,AS28,AQ28) -> -0.089346846 | AU28: =IFERROR(AU27/(AP82+AP91),"na") -> -0.089346842
A29: EBIT | B29: INR Mn | C29: =C24+C27 -> 3115.5 | D29: =D24+D27 -> 2685 | E29: =E24+E27 -> 2622.5 | F29: =F24+F27 -> 2032.8 | G29: =G24+G27 -> 10455.8 | H29: =H24+H27 -> 3685.8 | I29: =I24+I27 -> 2922.5 | J29: =J24+J27 -> 2613.7 | ... AU29: =AU24+AU27 -> 19020.737
A30: EBIT margin | B30: % | C30: =IFERROR(C29/C9,"na") -> 0.21201666 | D30: =IFERROR(D29/D9,"na") -> 0.20339985 | E30: =IFERROR(E29/E9,"na") -> 0.19584341 | F30: =IFERROR(F29/F9,"na") -> 0.16382319 | G30: =IFERROR(G29/G9,"na") -> 0.19472758 | H30: =IFERROR(H29/H9,"na") -> 0.23485857 | I30: =IFERROR(I29/I9,"na") -> 0.20614666 | J30: =IFERROR(J29/J9,"na") -> 0.19587814 | ... AU30: =IFERROR(AU29/AU9,"na") -> 0.18422817
A31: Finance expense | B31: INR Mn | C31: -39 | D31: -30.7 | E31: -31.3 | F31: -31.7 | G31: =C31+D31+E31+F31 -> -132.7 | H31: -35.3 | I31: -26.2 | J31: -29.7 | K31: -48.1 | L31: =H31+I31+J31+K31 -> -139.3 | M31: -37.3 | N31: -38.7 | O31: -41.1 | P31: -38.3 | Q31: =M31+N31+O31+P31 -> -155.4 | R31: -72.7 | S31: -60.2 | T31: -62.1 | U31: =IFERROR((S100+S113)*U32*0.25,"na") -> -55.486478 | V31: =R31+S31+T31+U31 -> -250.48648 | W31: =IFERROR((V100+V113)*W32*0.25,"na") -> -67.048638 | X31: =IFERROR((V100+V113)*X32*0.25,"na") -> -65.635798 | Y31: =IFERROR((V100+V113)*Y32*0.25,"na") -> -66.994747 | Z31: =IFERROR((V100+V113)*Z32*0.25,"na") -> -65.880429 | AA31: =W31+X31+Y31+Z31 -> -265.55961 | AB31: =IFERROR((AA100+AA113)*AB32*0.25,"na") -> -66.389903 | AC31: =IFERROR((AA100+AA113)*AC32*0.25,"na") -> -66.225219 | AD31: =IFERROR((AA100+AA113)*AD32*0.25,"na") -> -66.372575 | AE31: =IFERROR((AA100+AA113)*AE32*0.25,"na") -> -66.217031 | AF31: =AB31+AC31+AD31+AE31 -> -265.20473 | AG31: =IFERROR((AF100+AF113)*AG32*0.25,"na") -> -66.301182 | AH31: =IFERROR((AF100+AF113)*AH32*0.25,"na") -> -66.279002 | AI31: =IFERROR((AF100+AF113)*AI32*0.25,"na") -> -66.292447 | AJ31: =IFERROR((AF100+AF113)*AJ32*0.25,"na") -> -66.272416 | AK31: =AG31+AH31+AI31+AJ31 -> -265.14505 | AL31: =IFERROR((AK100+AK113)*AL32*0.25,"na") -> -66.286262 | AM31: =IFERROR((AK100+AK113)*AM32*0.25,"na") -> -66.282532 | AN31: =IFERROR((AK100+AK113)*AN32*0.25,"na") -> -66.283414 | AO31: =IFERROR((AK100+AK113)*AO32*0.25,"na") -> -66.281156 | AP31: =AL31+AM31+AN31+AO31 -> -265.13336 | AQ31: =IFERROR((AP100+AP113)*AQ32*0.25,"na") -> -66.283341 | AR31: =IFERROR((AP100+AP113)*AR32*0.25,"na") -> -66.282611 | AS31: =IFERROR((AP100+AP113)*AS32*0.25,"na") -> -66.28263 | AT31: =IFERROR((AP100+AP113)*AT32*0.25,"na") -> -66.282434 | AU31: =AQ31+AR31+AS31+AT31 -> -265.13102
A32: as a % of total debt | B32: % | C32: na | D32: na | E32: =IFERROR(E31*4/(D100+D113),"na") -> -0.22281545 | F32: =IFERROR(F31*4/(D100+D113),"na") -> -0.22566293 | G32: na | H32: =IFERROR(H31*4/(F100+F113),"na") -> -0.16753678 | I32: =IFERROR(I31*4/(F100+F113),"na") -> -0.12434741 | J32: =IFERROR(J31*4/(I100+I113),"na") -> -0.11870504 | K32: =IFERROR(K31*4/(I100+I113),"na") -> -0.1922462 | L32: =IFERROR(L31/(G100+G113),"na") -> -0.16528239 | M32: =IFERROR(M31*4/(K100+K113),"na") -> -0.15300995 | N32: =IFERROR(N31*4/(K100+K113),"na") -> -0.15875295 | O32: =IFERROR(O31*4/(N100+N113),"na") -> -0.17869565 | P32: =IFERROR(P31*4/(N100+N113),"na") -> -0.16652174 | Q32: =IFERROR(Q31/(L100+L113),"na") -> -0.15936827 | R32: =IFERROR(R31*4/(P100+P113),"na") -> -0.2372909 | S32: =IFERROR(S31*4/(P100+P113),"na") -> -0.19649123 | T32: =IFERROR(T31*4/(S100+S113),"na") -> -0.23321754 | U32: =AVERAGE(P32,R32,S32,T32) -> -0.20838035 | V32: =IFERROR(V31/(Q100+Q113),"na") -> -0.20439533 | W32: =AVERAGE(R32,T32,U32,S32) -> -0.218845 | X32: =AVERAGE(S32,U32,W32,T32) -> -0.21423353 | Y32: =AVERAGE(T32,W32,X32,U32) -> -0.21866911 | Z32: =AVERAGE(U32,X32,Y32,W32) -> -0.215032 | AA32: =IFERROR(AA31/(V100+V113),"na") -> -0.21669491 | AB32: =AVERAGE(W32,Y32,Z32,X32) -> -0.21669491 | AC32: =AVERAGE(X32,Z32,AB32,Y32) -> -0.21615739 | AD32: =AVERAGE(Y32,AB32,AC32,Z32) -> -0.21663835 | AE32: =AVERAGE(Z32,AC32,AD32,AB32) -> -0.21613066 | AF32: =IFERROR(AF31/(AA100+AA113),"na") -> -0.21640533 | AG32: =AVERAGE(AB32,AD32,AE32,AC32) -> -0.21640533 | AH32: =AVERAGE(AC32,AE32,AG32,AD32) -> -0.21633293 | AI32: =AVERAGE(AD32,AG32,AH32,AE32) -> -0.21637682 | AJ32: =AVERAGE(AE32,AH32,AI32,AG32) -> -0.21631143 | AK32: =IFERROR(AK31/(AF100+AF113),"na") -> -0.21635663 | AL32: =AVERAGE(AG32,AI32,AJ32,AH32) -> -0.21635663 | AM32: =AVERAGE(AH32,AJ32,AL32,AI32) -> -0.21634445 | AN32: =AVERAGE(AI32,AL32,AM32,AJ32) -> -0.21634733 | AO32: =AVERAGE(AJ32,AM32,AN32,AL32) -> -0.21633996 | AP32: =IFERROR(AP31/(AK100+AK113),"na") -> -0.21634709 | AQ32: =AVERAGE(AL32,AN32,AO32,AM32) -> -0.21634709 | AR32: =AVERAGE(AM32,AO32,AQ32,AN32) -> -0.21634471 | AS32: =AVERAGE(AN32,AQ32,AR32,AO32) -> -0.21634477 | AT32: =AVERAGE(AO32,AR32,AS32,AQ32) -> -0.21634414 | AU32: =IFERROR(AU31/(AP100+AP113),"na") -> -0.21634518
A33: Finance income | B33: INR Mn | C33: 104.5 | D33: 122.5 | E33: 96.7 | F33: 186.2 | G33: =C33+D33+E33+F33 -> 509.9 | H33: 240.7 | I33: 323.9 | J33: 272.3 | K33: 285.6 | L33: =H33+I33+J33+K33 -> 1122.5 | M33: 432.2 | N33: 336.7 | O33: 194.5 | P33: 520.7 | Q33: =M33+N33+O33+P33 -> 1484.1 | R33: 321.3 | S33: 276.3 | T33: 306.7 | U33: =IFERROR((S68+S86)*U34*0.25,"na") -> 352.96721 | V33: =R33+S33+T33+U33 -> 1257.2672 | W33: =IFERROR((V68+V86)*W34*0.25,"na") -> 301.26308 | X33: =IFERROR((V68+V86)*X34*0.25,"na") -> 296.25385 | Y33: =IFERROR((V68+V86)*Y34*0.25,"na") -> 301.24231 | Z33: =IFERROR((V68+V86)*Z34*0.25,"na") -> 305.94698 | AA33: =W33+X33+Y33+Z33 -> 1204.7062 | AB33: =IFERROR((AA68+AA86)*AB34*0.25,"na") -> 301.17655 | AC33: =IFERROR((AA68+AA86)*AC34*0.25,"na") -> 301.15492 | AD33: =IFERROR((AA68+AA86)*AD34*0.25,"na") -> 302.38019 | AE33: =IFERROR((AA68+AA86)*AE34*0.25,"na") -> 302.66466 | AF33: =AB33+AC33+AD33+AE33 -> 1207.3763 | AG33: =IFERROR((AF68+AF86)*AG34*0.25,"na") -> 301.84408 | AH33: =IFERROR((AF68+AF86)*AH34*0.25,"na") -> 302.01096 | AI33: =IFERROR((AF68+AF86)*AI34*0.25,"na") -> 302.22497 | AJ33: =IFERROR((AF68+AF86)*AJ34*0.25,"na") -> 302.18617 | AK33: =AG33+AH33+AI33+AJ33 -> 1208.2662 | AL33: =IFERROR((AK68+AK86)*AL34*0.25,"na") -> 302.06655 | AM33: =IFERROR((AK68+AK86)*AM34*0.25,"na") -> 302.12216 | AN33: =IFERROR((AK68+AK86)*AN34*0.25,"na") -> 302.14996 | AO33: =IFERROR((AK68+AK86)*AO34*0.25,"na") -> 302.13121 | AP33: =AL33+AM33+AN33+AO33 -> 1208.4699 | AQ33: =IFERROR((AP68+AP86)*AQ34*0.25,"na") -> 302.11747 | AR33: =IFERROR((AP68+AP86)*AR34*0.25,"na") -> 302.1302 | AS33: =IFERROR((AP68+AP86)*AS34*0.25,"na") -> 302.13221 | AT33: =IFERROR((AP68+AP86)*AT34*0.25,"na") -> 302.12777 | AU33: =AQ33+AR33+AS33+AT33 -> 1208.5077
A34: as a % of investments | B34: % | C34: na | D34: na | E34: =IFERROR(E33*4/(D68+D86),"na") -> 0.061758554 | F34: =IFERROR(F33*4/(D68+D86),"na") -> 0.11891875 | G34: na | H34: =IFERROR(H33*4/(F68+F86),"na") -> 0.12892513 | I34: =IFERROR(I33*4/(F68+F86),"na") -> 0.1734892 | J34: =IFERROR(J33*4/(I68+I86),"na") -> 0.094365941 | K34: =IFERROR(K33*4/(I68+I86),"na") -> 0.098975074 | L34: =IFERROR(L33/(G68+G86),"na") -> 0.15030999 | M34: =IFERROR(M33*4/(K68+K86),"na") -> 0.11635248 | N34: =IFERROR(N33*4/(K68+K86),"na") -> 0.09064294 | O34: =IFERROR(O33*4/(N68+N86),"na") -> 0.049593942 | P34: =IFERROR(P33*4/(N68+N86),"na") -> 0.13276897 | Q34: =IFERROR(Q33/(L68+L86),"na") -> 0.099883567 | R34: =IFERROR(R33*4/(P68+P86),"na") -> 0.10154627 | S34: =IFERROR(S33*4/(P68+P86),"na") -> 0.087324099 | T34: =IFERROR(T33*4/(S68+S86),"na") -> 0.089259469 | U34: =AVERAGE(P34,R34,S34,T34) -> 0.1027247 | V34: =IFERROR(V33/(Q68+Q86),"na") -> 0.099339239 | W34: =AVERAGE(R34,T34,U34,S34) -> 0.095213634 | X34: =AVERAGE(S34,U34,W34,T34) -> 0.093630476 | Y34: =AVERAGE(T34,W34,X34,U34) -> 0.09520707 | Z34: =AVERAGE(U34,X34,Y34,W34) -> 0.096693971 | AA34: =IFERROR(AA33/(V68+V86),"na") -> 0.095186288 | AB34: =AVERAGE(W34,Y34,Z34,X34) -> 0.095186288 | AC34: =AVERAGE(X34,Z34,AB34,Y34) -> 0.095179451 | AD34: =AVERAGE(Y34,AB34,AC34,Z34) -> 0.095566695 | AE34: =AVERAGE(Z34,AC34,AD34,AB34) -> 0.095656601 | AF34: =IFERROR(AF33/(AA68+AA86),"na") -> 0.095397259 | AG34: =AVERAGE(AB34,AD34,AE34,AC34) -> 0.095397259 | AH34: =AVERAGE(AC34,AE34,AG34,AD34) -> 0.095450002 | AI34: =AVERAGE(AD34,AG34,AH34,AE34) -> 0.095517639 | AJ34: =AVERAGE(AE34,AH34,AI34,AG34) -> 0.095505375 | AK34: =IFERROR(AK33/(AF68+AF86),"na") -> 0.095467569 | AL34: =AVERAGE(AG34,AI34,AJ34,AH34) -> 0.095467569 | AM34: =AVERAGE(AH34,AJ34,AL34,AI34) -> 0.095485146 | AN34: =AVERAGE(AI34,AL34,AM34,AJ34) -> 0.095493932 | AO34: =AVERAGE(AJ34,AM34,AN34,AL34) -> 0.095488006 | AP34: =IFERROR(AP33/(AK68+AK86),"na") -> 0.095483663 | AQ34: =AVERAGE(AL34,AN34,AO34,AM34) -> 0.095483663 | AR34: =AVERAGE(AM34,AO34,AQ34,AN34) -> 0.095487687 | AS34: =AVERAGE(AN34,AQ34,AR34,AO34) -> 0.095488322 | AT34: =AVERAGE(AO34,AR34,AS34,AQ34) -> 0.095486919 | AU34: =IFERROR(AU33/(AP68+AP86),"na") -> 0.095486648
A35: Share of profit of JV and Associate | B35: INR Mn | C35: =C36+C37 -> 3.6 | D35: =D36+D37 -> 4.6 | E35: =E36+E37 -> 7.6 | F35: =F36+F37 -> 13.5 | G35: =G36+G37 -> 29.3 | H35: =H36+H37 -> 8.6 | I35: =I36+I37 -> 15.2 | J35: =J36+J37 -> 5.7 | ... AU35: =AU36+AU37 -> 40
A36: Share of profit of associate | B36: INR Mn | C36: 3.6 | D36: 4.6 | E36: 7.6 | F36: 13.5 | G36: =C36+D36+E36+F36 -> 29.3 | H36: 8.6 | I36: 15.2 | J36: 5.7 | K36: 14.1 | L36: =H36+I36+J36+K36 -> 43.6 | M36: 4.3 | N36: 10.8 | O36: 18.5 | P36: 13.9 | Q36: =M36+N36+O36+P36 -> 47.5 | R36: 4.6 | S36: -1.1 | T36: 17.8 | U36: 8 | V36: =R36+S36+T36+U36 -> 29.3 | W36: 8 | X36: =W36 -> 8 | Y36: =X36 -> 8 | Z36: =Y36 -> 8 | AA36: =W36+X36+Y36+Z36 -> 32 | AB36: =Z36 -> 8 | AC36: =AB36 -> 8 | AD36: =AC36 -> 8 | AE36: =AD36 -> 8 | AF36: =AB36+AC36+AD36+AE36 -> 32 | AG36: =AE36 -> 8 | AH36: =AG36 -> 8 | AI36: =AH36 -> 8 | AJ36: =AI36 -> 8 | AK36: =AG36+AH36+AI36+AJ36 -> 32 | AL36: =AJ36 -> 8 | AM36: =AL36 -> 8 | AN36: =AM36 -> 8 | AO36: =AN36 -> 8 | AP36: =AL36+AM36+AN36+AO36 -> 32 | AQ36: =AO36 -> 8 | AR36: =AQ36 -> 8 | AS36: =AR36 -> 8 | AT36: =AS36 -> 8 | AU36: =AQ36+AR36+AS36+AT36 -> 32
A37: Share of profit of JV | B37: INR Mn | C37: 0 | D37: 0 | E37: 0 | F37: 0 | G37: =C37+D37+E37+F37 -> 0 | H37: 0 | I37: 0 | J37: 0 | K37: 9.4 | L37: =H37+I37+J37+K37 -> 9.4 | M37: 1.2 | N37: 0.4 | O37: 2.5 | P37: -5.7 | Q37: =M37+N37+O37+P37 -> -1.6 | R37: -0.4 | S37: -5.4 | T37: -3.1 | U37: 2 | V37: =R37+S37+T37+U37 -> -6.9 | W37: 2 | X37: =W37 -> 2 | Y37: =X37 -> 2 | Z37: =Y37 -> 2 | AA37: =W37+X37+Y37+Z37 -> 8 | AB37: =Z37 -> 2 | AC37: =AB37 -> 2 | AD37: =AC37 -> 2 | AE37: =AD37 -> 2 | AF37: =AB37+AC37+AD37+AE37 -> 8 | AG37: =AE37 -> 2 | AH37: =AG37 -> 2 | AI37: =AH37 -> 2 | AJ37: =AI37 -> 2 | AK37: =AG37+AH37+AI37+AJ37 -> 8 | AL37: =AJ37 -> 2 | AM37: =AL37 -> 2 | AN37: =AM37 -> 2 | AO37: =AN37 -> 2 | AP37: =AL37+AM37+AN37+AO37 -> 8 | AQ37: =AO37 -> 2 | AR37: =AQ37 -> 2 | AS37: =AR37 -> 2 | AT37: =AS37 -> 2 | AU37: =AQ37+AR37+AS37+AT37 -> 8
A38: Exceptional items | B38: INR Mn | C38: 5.5 | D38: -12.3 | E38: -6.7 | F38: -34.6 | G38: =C38+D38+E38+F38 -> -48.1 | H38: -4 | I38: -11.4 | J38: -42.7 | K38: 0 | L38: =H38+I38+J38+K38 -> -58.1 | M38: 0 | N38: 0 | O38: 0 | P38: 0 | Q38: =M38+N38+O38+P38 -> 0 | R38: 0 | S38: 0 | T38: 0 | U38: 0 | V38: =R38+S38+T38+U38 -> 0 | W38: 0 | X38: 0 | Y38: 0 | Z38: 0 | AA38: =W38+X38+Y38+Z38 -> 0 | AB38: 0 | AC38: 0 | AD38: 0 | AE38: 0 | AF38: =AB38+AC38+AD38+AE38 -> 0 | AG38: 0 | AH38: 0 | AI38: 0 | AJ38: 0 | AK38: =AG38+AH38+AI38+AJ38 -> 0 | AL38: 0 | AM38: 0 | AN38: 0 | AO38: 0 | AP38: =AL38+AM38+AN38+AO38 -> 0 | AQ38: 0 | AR38: 0 | AS38: 0 | AT38: 0 | AU38: =AQ38+AR38+AS38+AT38 -> 0
A39: PBT | B39: INR Mn | C39: =C29+C31+C33+C35+C38 -> 3190.1 | D39: =D29+D31+D33+D35+D38 -> 2769.1 | E39: =E29+E31+E33+E35+E38 -> 2688.8 | F39: =F29+F31+F33+F35+F38 -> 2166.2 | G39: =G29+G31+G33+G35+G38 -> 10814.2 | H39: =H29+H31+H33+H35+H38 -> 3895.8 | I39: =I29+I31+I33+I35+I38 -> 3224 | J39: =J29+J31+J33+J35+J38 -> 2819.3 | ... AU39: =AU29+AU31+AU33+AU35+AU38 -> 20004.114
A40: Tax | B40: INR Mn | C40: =C41+C43 -> -925.9 | D40: =D41+D43 -> -835.7 | E40: =E41+E43 -> -822.1 | F40: =F41+F43 -> -637.4 | G40: =G41+G43 -> -3221.1 | H40: =H41+H43 -> -1174.3 | I40: =I41+I43 -> -911.7 | J40: =J41+J43 -> -793.2 | ... AU40: =AU41+AU43 -> -6181.2712
A41: Current tax | B41: INR Mn | C41: -925.9 | D41: -835.7 | E41: -822.1 | F41: -637.4 | G41: =C41+D41+E41+F41 -> -3221.1 | H41: -1174.3 | I41: -911.7 | J41: -793.2 | K41: -951.2 | L41: =H41+I41+J41+K41 -> -3830.4 | M41: -980.3 | N41: -1211.4 | O41: -1144.6 | P41: -404.5 | Q41: =M41+N41+O41+P41 -> -3740.8 | R41: -1342.8 | S41: -1131.8 | T41: -1183.8 | U41: =-IFERROR(U39*U42,"na") -> -1042.4615 | V41: =R41+S41+T41+U41 -> -4700.8615 | W41: =-IFERROR(W39*W42,"na") -> -1170.7209 | X41: =-IFERROR(X39*X42,"na") -> -1101.4873 | Y41: =-IFERROR(Y39*Y42,"na") -> -1151.9671 | Z41: =-IFERROR(Z39*Z42,"na") -> -1111.3597 | AA41: =W41+X41+Y41+Z41 -> -4535.5349 | AB41: =-IFERROR(AB39*AB42,"na") -> -1254.2423 | AC41: =-IFERROR(AC39*AC42,"na") -> -1199.3276 | AD41: =-IFERROR(AD39*AD42,"na") -> -1262.6358 | AE41: =-IFERROR(AE39*AE42,"na") -> -1212.6126 | AF41: =AB41+AC41+AD41+AE41 -> -4928.8183 | AG41: =-IFERROR(AG39*AG42,"na") -> -1337.147 | AH41: =-IFERROR(AH39*AH42,"na") -> -1279.7903 | AI41: =-IFERROR(AI39*AI42,"na") -> -1347.7771 | AJ41: =-IFERROR(AJ39*AJ42,"na") -> -1294.1839 | AK41: =AG41+AH41+AI41+AJ41 -> -5258.8983 | AL41: =-IFERROR(AL39*AL42,"na") -> -1428.1117 | AM41: =-IFERROR(AM39*AM42,"na") -> -1366.8193 | AN41: =-IFERROR(AN39*AN42,"na") -> -1439.5128 | AO41: =-IFERROR(AO39*AO42,"na") -> -1382.5465 | AP41: =AL41+AM41+AN41+AO41 -> -5616.9903 | AQ41: =-IFERROR(AQ39*AQ42,"na") -> -1525.7466 | AR41: =-IFERROR(AR39*AR42,"na") -> -1460.1714 | AS41: =-IFERROR(AS39*AS42,"na") -> -1537.9285 | AT41: =-IFERROR(AT39*AT42,"na") -> -1477.3876 | AU41: =AQ41+AR41+AS41+AT41 -> -6001.2342
A42: corporate tax | B42: % | C42: =-IFERROR(C41/C39,"na") -> 0.29024169 | D42: =-IFERROR(D41/D39,"na") -> 0.30179481 | E42: =-IFERROR(E41/E39,"na") -> 0.30574978 | F42: =-IFERROR(F41/F39,"na") -> 0.29424799 | G42: =-IFERROR(G41/G39,"na") -> 0.29785837 | H42: =-IFERROR(H41/H39,"na") -> 0.30142718 | I42: =-IFERROR(I41/I39,"na") -> 0.28278536 | J42: =-IFERROR(J41/J39,"na") -> 0.28134643 | ... T42: =-IFERROR(T41/T39,"na") -> 0.35808706 | U42: 0.3 | V42: =-IFERROR(V41/V39,"na") -> 0.33360094 | W42: 0.3 | X42: =W42 -> 0.3 | Y42: =X42 -> 0.3 | Z42: =Y42 -> 0.3 | AA42: =-IFERROR(AA41/AA39,"na") -> 0.3 | AB42: =Z42 -> 0.3 | AC42: =AB42 -> 0.3 | AD42: =AC42 -> 0.3 | AE42: =AD42 -> 0.3 | AF42: =-IFERROR(AF41/AF39,"na") -> 0.3 | AG42: =AE42 -> 0.3 | AH42: =AG42 -> 0.3 | AI42: =AH42 -> 0.3 | AJ42: =AI42 -> 0.3 | AK42: =-IFERROR(AK41/AK39,"na") -> 0.3 | AL42: =AJ42 -> 0.3 | AM42: =AL42 -> 0.3 | AN42: =AM42 -> 0.3 | AO42: =AN42 -> 0.3 | AP42: =-IFERROR(AP41/AP39,"na") -> 0.3 | AQ42: =AO42 -> 0.3 | AR42: =AQ42 -> 0.3 | AS42: =AR42 -> 0.3 | AT42: =AS42 -> 0.3 | AU42: =-IFERROR(AU41/AU39,"na") -> 0.3
A43: Deferred tax | B43: INR Mn | C43: 0 | D43: 0 | E43: 0 | F43: 0 | G43: =C43+D43+E43+F43 -> 0 | H43: 0 | I43: 0 | J43: 0 | K43: -20.1 | L43: =H43+I43+J43+K43 -> -20.1 | M43: -52.2 | N43: -33.1 | O43: -48.5 | P43: -52.5 | Q43: =M43+N43+O43+P43 -> -186.3 | R43: -17.7 | S43: -98.6 | T43: 73.5 | U43: =IFERROR(U41*U44,"na") -> -31.273845 | V43: =R43+S43+T43+U43 -> -74.073845 | W43: =IFERROR(W41*W44,"na") -> -35.121627 | X43: =IFERROR(X41*X44,"na") -> -33.044618 | Y43: =IFERROR(Y41*Y44,"na") -> -34.559013 | Z43: =IFERROR(Z41*Z44,"na") -> -33.34079 | AA43: =W43+X43+Y43+Z43 -> -136.06605 | AB43: =IFERROR(AB41*AB44,"na") -> -37.62727 | AC43: =IFERROR(AC41*AC44,"na") -> -35.979827 | AD43: =IFERROR(AD41*AD44,"na") -> -37.879073 | AE43: =IFERROR(AE41*AE44,"na") -> -36.378379 | AF43: =AB43+AC43+AD43+AE43 -> -147.86455 | AG43: =IFERROR(AG41*AG44,"na") -> -40.11441 | AH43: =IFERROR(AH41*AH44,"na") -> -38.393708 | AI43: =IFERROR(AI41*AI44,"na") -> -40.433313 | AJ43: =IFERROR(AJ41*AJ44,"na") -> -38.825518 | AK43: =AG43+AH43+AI43+AJ43 -> -157.76695 | AL43: =IFERROR(AL41*AL44,"na") -> -42.843351 | AM43: =IFERROR(AM41*AM44,"na") -> -41.00458 | AN43: =IFERROR(AN41*AN44,"na") -> -43.185384 | AO43: =IFERROR(AO41*AO44,"na") -> -41.476394 | AP43: =AL43+AM43+AN43+AO43 -> -168.50971 | AQ43: =IFERROR(AQ41*AQ44,"na") -> -45.772398 | AR43: =IFERROR(AR41*AR44,"na") -> -43.805142 | AS43: =IFERROR(AS41*AS44,"na") -> -46.137856 | AT43: =IFERROR(AT41*AT44,"na") -> -44.321629 | AU43: =AQ43+AR43+AS43+AT43 -> -180.03703
A44: as a % of tax | B44: % | C44: =IFERROR(C43/C41,"na") -> 0 | D44: =IFERROR(D43/D41,"na") -> 0 | E44: =IFERROR(E43/E41,"na") -> 0 | F44: =IFERROR(F43/F41,"na") -> 0 | G44: =IFERROR(G43/G41,"na") -> 0 | H44: =IFERROR(H43/H41,"na") -> 0 | I44: =IFERROR(I43/I41,"na") -> 0 | J44: =IFERROR(J43/J41,"na") -> 0 | ... T44: =IFERROR(T43/T41,"na") -> -0.062088191 | U44: 0.03 | V44: =IFERROR(V43/V41,"na") -> 0.015757504 | W44: 0.03 | X44: =W44 -> 0.03 | Y44: =X44 -> 0.03 | Z44: =Y44 -> 0.03 | AA44: =IFERROR(AA43/AA41,"na") -> 0.03 | AB44: =Z44 -> 0.03 | AC44: =AB44 -> 0.03 | AD44: =AC44 -> 0.03 | AE44: =AD44 -> 0.03 | AF44: =IFERROR(AF43/AF41,"na") -> 0.03 | AG44: =AE44 -> 0.03 | AH44: =AG44 -> 0.03 | AI44: =AH44 -> 0.03 | AJ44: =AI44 -> 0.03 | AK44: =IFERROR(AK43/AK41,"na") -> 0.03 | AL44: =AJ44 -> 0.03 | AM44: =AL44 -> 0.03 | AN44: =AM44 -> 0.03 | AO44: =AN44 -> 0.03 | AP44: =IFERROR(AP43/AP41,"na") -> 0.03 | AQ44: =AO44 -> 0.03 | AR44: =AQ44 -> 0.03 | AS44: =AR44 -> 0.03 | AT44: =AS44 -> 0.03 | AU44: =IFERROR(AU43/AU41,"na") -> 0.03
A45: PAT | B45: INR Mn | C45: =C39+C40 -> 2264.2 | D45: =D39+D40 -> 1933.4 | E45: =E39+E40 -> 1866.7 | F45: =F39+F40 -> 1528.8 | G45: =G39+G40 -> 7593.1 | H45: =H39+H40 -> 2721.5 | I45: =I39+I40 -> 2312.3 | J45: =J39+J40 -> 2026.1 | ... AU45: =AU39+AU40 -> 13822.843
A46: PAT margin | B46: % | C46: =IFERROR(C45/C9,"na") -> 0.15408381 | D46: =IFERROR(D45/D9,"na") -> 0.14646304 | E46: =IFERROR(E45/E9,"na") -> 0.13940168 | F46: =IFERROR(F45/F9,"na") -> 0.12320587 | G46: =IFERROR(G45/G9,"na") -> 0.14141299 | H46: =IFERROR(H45/H9,"na") -> 0.17341354 | I46: =IFERROR(I45/I9,"na") -> 0.16310451 | J46: =IFERROR(J45/J9,"na") -> 0.15184172 | ... AU46: =IFERROR(AU45/AU9,"na") -> 0.13388319
A47: Minority interest (NCI) | B47: INR Mn | C47: -8.9 | D47: -16.4 | E47: -9.5 | F47: -2.8 | G47: =C47+D47+E47+F47 -> -37.6 | H47: -21.6 | I47: -5.6 | J47: -1.8 | K47: -3.3 | L47: =H47+I47+J47+K47 -> -32.3 | M47: -0.2 | N47: -10.1 | O47: 7 | P47: -34.1 | Q47: =M47+N47+O47+P47 -> -37.4 | R47: -21.1 | S47: 4.5 | T47: -0.9 | U47: =-IFERROR(U45*U48,"na") -> -9.14002 | V47: =R47+S47+T47+U47 -> -26.64002 | W47: =-IFERROR(W45*W48,"na") -> -10.786242 | X47: =-IFERROR(X45*X48,"na") -> -10.148369 | Y47: =-IFERROR(Y45*Y48,"na") -> -10.613457 | Z47: =-IFERROR(Z45*Z48,"na") -> -10.239327 | AA47: =W47+X47+Y47+Z47 -> -41.787395 | AB47: =-IFERROR(AB45*AB48,"na") -> -11.555753 | AC47: =-IFERROR(AC45*AC48,"na") -> -11.049805 | AD47: =-IFERROR(AD45*AD48,"na") -> -11.633084 | AE47: =-IFERROR(AE45*AE48,"na") -> -11.172204 | AF47: =AB47+AC47+AD47+AE47 -> -45.410846 | AG47: =-IFERROR(AG45*AG48,"na") -> -12.319581 | AH47: =-IFERROR(AH45*AH48,"na") -> -11.791134 | AI47: =-IFERROR(AI45*AI48,"na") -> -12.41752 | AJ47: =-IFERROR(AJ45*AJ48,"na") -> -11.923748 | AK47: =AG47+AH47+AI47+AJ47 -> -48.451983 | AL47: =-IFERROR(AL45*AL48,"na") -> -13.157669 | AM47: =-IFERROR(AM45*AM48,"na") -> -12.592962 | AN47: =-IFERROR(AN45*AN48,"na") -> -13.262711 | AO47: =-IFERROR(AO45*AO48,"na") -> -12.737861 | AP47: =AL47+AM47+AN47+AO47 -> -51.751204 | AQ47: =-IFERROR(AQ45*AQ48,"na") -> -14.057212 | AR47: =-IFERROR(AR45*AR48,"na") -> -13.453046 | AS47: =-IFERROR(AS45*AS48,"na") -> -14.169448 | AT47: =-IFERROR(AT45*AT48,"na") -> -13.611665 | AU47: =AQ47+AR47+AS47+AT47 -> -55.291371
A48: as a % of PAT | B48: % | C48: =-IFERROR(C47/C45,"na") -> 0.0039307482 | D48: =-IFERROR(D47/D45,"na") -> 0.0084824661 | E48: =-IFERROR(E47/E45,"na") -> 0.0050891948 | F48: =-IFERROR(F47/F45,"na") -> 0.0018315018 | G48: =-IFERROR(G47/G45,"na") -> 0.0049518642 | H48: =-IFERROR(H47/H45,"na") -> 0.0079367996 | I48: =-IFERROR(I47/I45,"na") -> 0.0024218311 | J48: =-IFERROR(J47/J45,"na") -> 0.0008884063 | ... T48: =-IFERROR(T47/T45,"na") -> 0.00040991073 | U48: =AVERAGE(L48,Q48) -> 0.0038065394 | V48: =-IFERROR(V47/V45,"na") -> 0.0028594953 | W48: 0.004 | X48: =W48 -> 0.004 | Y48: =X48 -> 0.004 | Z48: =Y48 -> 0.004 | AA48: =-IFERROR(AA47/AA45,"na") -> 0.004 | AB48: =Z48 -> 0.004 | AC48: =AB48 -> 0.004 | AD48: =AC48 -> 0.004 | AE48: =AD48 -> 0.004 | AF48: =-IFERROR(AF47/AF45,"na") -> 0.004 | AG48: =AE48 -> 0.004 | AH48: =AG48 -> 0.004 | AI48: =AH48 -> 0.004 | AJ48: =AI48 -> 0.004 | AK48: =-IFERROR(AK47/AK45,"na") -> 0.004 | AL48: =AJ48 -> 0.004 | AM48: =AL48 -> 0.004 | AN48: =AM48 -> 0.004 | AO48: =AN48 -> 0.004 | AP48: =-IFERROR(AP47/AP45,"na") -> 0.004 | AQ48: =AO48 -> 0.004 | AR48: =AQ48 -> 0.004 | AS48: =AR48 -> 0.004 | AT48: =AS48 -> 0.004 | AU48: =-IFERROR(AU47/AU45,"na") -> 0.004
A49: PAT to equity shareholders | B49: INR Mn | C49: =C45+C47 -> 2255.3 | D49: =D45+D47 -> 1917 | E49: =E45+E47 -> 1857.2 | F49: =F45+F47 -> 1526 | G49: =G45+G47 -> 7555.5 | H49: =H45+H47 -> 2699.9 | I49: =I45+I47 -> 2306.7 | J49: =J45+J47 -> 2024.3 | ... AU49: =AU45+AU47 -> 13767.551
A50: y-o-y growth | B50: % | C50: na | D50: na | E50: na | F50: na | G50: na | H50: =IFERROR(H49/C49-1,"na") -> 0.19713564 | I50: =IFERROR(I49/D49-1,"na") -> 0.20328638 | J50: =IFERROR(J49/E49-1,"na") -> 0.089974155 | K50: =IFERROR(K49/F49-1,"na") -> 0.028178244 | L50: =IFERROR(L49/G49-1,"na") -> 0.13823043 | M50: =IFERROR(M49/H49-1,"na") -> -0.16111708 | N50: =IFERROR(N49/I49-1,"na") -> 0.092079594 | O50: =IFERROR(O49/J49-1,"na") -> 0.18480462 | ... AU50: =IFERROR(AU49/AP49-1,"na") -> 0.068407434
A52: Total shares outstanding | B52: Mn | C52: 512.7 | D52: 512.7 | E52: 512.7 | F52: 512.7 | G52: =F52 -> 512.7 | H52: 512.7 | I52: 512.7 | J52: 512.7 | K52: 512.7 | L52: =K52 -> 512.7 | M52: 512.7 | N52: 512.8 | O52: 512.8 | P52: 507.8 | Q52: =P52 -> 507.8 | R52: 507.8 | S52: 507.9 | T52: 508 | U52: =T52+V183 -> 508 | V52: =U52 -> 508 | W52: =U52+AA183 -> 508 | X52: =W52+AA183 -> 508 | Y52: =X52+AA183 -> 508 | Z52: =Y52+AA183 -> 508 | AA52: =Z52 -> 508 | AB52: =Z52+AF183 -> 508 | AC52: =AB52+AF183 -> 508 | AD52: =AC52+AF183 -> 508 | AE52: =AD52+AF183 -> 508 | AF52: =AE52 -> 508 | AG52: =AE52+AK183 -> 508 | AH52: =AG52+AK183 -> 508 | AI52: =AH52+AK183 -> 508 | AJ52: =AI52+AK183 -> 508 | AK52: =AJ52 -> 508 | AL52: =AJ52+AP183 -> 508 | AM52: =AL52+AP183 -> 508 | AN52: =AM52+AP183 -> 508 | AO52: =AN52+AP183 -> 508 | AP52: =AO52 -> 508 | AQ52: =AO52+AU183 -> 508 | AR52: =AQ52+AU183 -> 508 | AS52: =AR52+AU183 -> 508 | AT52: =AS52+AU183 -> 508 | AU52: =AT52 -> 508
A53: Total diluted shares outstanding | B53: Mn | C53: =C52+C55-C54 -> 512.7 | D53: =D52+D55-D54 -> 512.7 | E53: =E52+E55-E54 -> 512.7 | F53: =F52+F55-F54 -> 512.7 | G53: =G52+G55-G54 -> 512.7 | H53: =H52+H55-H54 -> 513.28897 | I53: =I52+I55-I54 -> 512.7 | J53: =J52+J55-J54 -> 512.7 | ... T53: =T52+T55-T54 -> 508 | U53: =T53+V183 -> 508 | V53: =V52+V55-V54 -> 508 | W53: =U53+AA183 -> 508 | X53: =W53+AA183 -> 508 | Y53: =X53+AA183 -> 508 | Z53: =Y53+AA183 -> 508 | AA53: =AA52+AA55-AA54 -> 508 | AB53: =Z53+AF183 -> 508 | AC53: =AB53+AF183 -> 508 | AD53: =AC53+AF183 -> 508 | AE53: =AD53+AF183 -> 508 | AF53: =AF52+AF55-AF54 -> 508 | AG53: =AE53+AK183 -> 508 | AH53: =AG53+AK183 -> 508 | AI53: =AH53+AK183 -> 508 | AJ53: =AI53+AK183 -> 508 | AK53: =AK52+AK55-AK54 -> 508 | AL53: =AJ53+AP183 -> 508 | AM53: =AL53+AP183 -> 508 | AN53: =AM53+AP183 -> 508 | AO53: =AN53+AP183 -> 508 | AP53: =AP52+AP55-AP54 -> 508 | AQ53: =AO53+AU183 -> 508 | AR53: =AQ53+AU183 -> 508 | AS53: =AR53+AU183 -> 508 | AT53: =AS53+AU183 -> 508 | AU53: =AU52+AU55-AU54 -> 508
A54: Weighted average number of basic share | B54: Mn | C54: 512.7 | D54: 512.7 | E54: 512.7 | F54: 512.7 | G54: =AVERAGE(C54:F54) -> 512.7 | H54: 512.7 | I54: 512.8 | J54: 512.7 | K54: 512.7 | L54: =AVERAGE(H54:K54) -> 512.725 | M54: 512.7 | N54: 512.8 | O54: 512.8 | P54: 507.8 | Q54: =AVERAGE(M54:P54) -> 511.525 | R54: 507.8 | S54: 507.9 | T54: 508 | U54: =AVERAGE(T52:U52) -> 508 | V54: =AVERAGE(R54:U54) -> 507.925 | W54: =AVERAGE(U52,W52) -> 508 | X54: =AVERAGE(W52,X52) -> 508 | Y54: =AVERAGE(X52,Y52) -> 508 | Z54: =AVERAGE(Y52:Z52) -> 508 | AA54: =AVERAGE(W54:Z54) -> 508 | AB54: =AVERAGE(Z52,AB52) -> 508 | AC54: =AVERAGE(AB52,AC52) -> 508 | AD54: =AVERAGE(AC52,AD52) -> 508 | AE54: =AVERAGE(AD52:AE52) -> 508 | AF54: =AVERAGE(AB54:AE54) -> 508 | AG54: =AVERAGE(AE52,AG52) -> 508 | AH54: =AVERAGE(AG52,AH52) -> 508 | AI54: =AVERAGE(AH52,AI52) -> 508 | AJ54: =AVERAGE(AI52:AJ52) -> 508 | AK54: =AVERAGE(AG54:AJ54) -> 508 | AL54: =AVERAGE(AJ52,AL52) -> 508 | AM54: =AVERAGE(AL52,AM52) -> 508 | AN54: =AVERAGE(AM52,AN52) -> 508 | AO54: =AVERAGE(AN52:AO52) -> 508 | AP54: =AVERAGE(AL54:AO54) -> 508 | AQ54: =AVERAGE(AO52,AQ52) -> 508 | AR54: =AVERAGE(AQ52,AR52) -> 508 | AS54: =AVERAGE(AR52,AS52) -> 508 | AT54: =AVERAGE(AS52:AT52) -> 508 | AU54: =AVERAGE(AQ54:AT54) -> 508
A55: Weighted average number of diluted shares | B55: Mn | C55: 512.7 | D55: 512.7 | E55: 512.7 | F55: 512.7 | G55: =AVERAGE(C55:F55) -> 512.7 | H55: =IFERROR(H49/H58,"na") -> 513.28897 | I55: 512.8 | J55: 512.7 | K55: 512.7 | L55: =AVERAGE(H55:K55) -> 512.87224 | M55: 512.7 | N55: 512.8 | O55: 512.8 | P55: 507.8 | Q55: =AVERAGE(M55:P55) -> 511.525 | R55: 507.8 | S55: 507.9 | T55: 508 | U55: =AVERAGE(T53:U53) -> 508 | V55: =AVERAGE(R55:U55) -> 507.925 | W55: =AVERAGE(U53,W53) -> 508 | X55: =AVERAGE(W53,X53) -> 508 | Y55: =AVERAGE(X53,Y53) -> 508 | Z55: =AVERAGE(Y53:Z53) -> 508 | AA55: =AVERAGE(W55:Z55) -> 508 | AB55: =AVERAGE(Z53,AB53) -> 508 | AC55: =AVERAGE(AB53,AC53) -> 508 | AD55: =AVERAGE(AC53,AD53) -> 508 | AE55: =AVERAGE(AD53:AE53) -> 508 | AF55: =AVERAGE(AB55:AE55) -> 508 | AG55: =AVERAGE(AE53,AG53) -> 508 | AH55: =AVERAGE(AG53,AH53) -> 508 | AI55: =AVERAGE(AH53,AI53) -> 508 | AJ55: =AVERAGE(AI53:AJ53) -> 508 | AK55: =AVERAGE(AG55:AJ55) -> 508 | AL55: =AVERAGE(AJ53,AL53) -> 508 | AM55: =AVERAGE(AL53,AM53) -> 508 | AN55: =AVERAGE(AM53,AN53) -> 508 | AO55: =AVERAGE(AN53:AO53) -> 508 | AP55: =AVERAGE(AL55:AO55) -> 508 | AQ55: =AVERAGE(AO53,AQ53) -> 508 | AR55: =AVERAGE(AQ53,AR53) -> 508 | AS55: =AVERAGE(AR53,AS53) -> 508 | AT55: =AVERAGE(AS53:AT53) -> 508 | AU55: =AVERAGE(AQ55:AT55) -> 508
A57: Basic EPS | B57: INR/share | C57: =IFERROR(C49/C54,"na") -> 4.3988687 | D57: =IFERROR(D49/D54,"na") -> 3.7390287 | E57: =IFERROR(E49/E54,"na") -> 3.6223913 | F57: =IFERROR(F49/F54,"na") -> 2.9763995 | G57: =IFERROR(G49/G54,"na") -> 14.736688 | H57: =IFERROR(H49/H54,"na") -> 5.2660425 | I57: =IFERROR(I49/I54,"na") -> 4.4982449 | J57: =IFERROR(J49/J54,"na") -> 3.9483129 | ... AU57: =IFERROR(AU49/AU54,"na") -> 27.101479
A58: Diluted EPS | B58: INR/share | C58: =IFERROR(C49/C55,"na") -> 4.3988687 | D58: =IFERROR(D49/D55,"na") -> 3.7390287 | E58: =IFERROR(E49/E55,"na") -> 3.6223913 | F58: =IFERROR(F49/F55,"na") -> 2.9763995 | G58: =IFERROR(G49/G55,"na") -> 14.736688 | H58: 5.26 | I58: =IFERROR(I49/I55,"na") -> 4.4982449 | J58: =IFERROR(J49/J55,"na") -> 3.9483129 | K58: =IFERROR(K49/K55,"na") -> 3.0602692 | L58: =IFERROR(L49/L55,"na") -> 16.768114 | M58: =IFERROR(M49/M55,"na") -> 4.4175931 | N58: =IFERROR(N49/N55,"na") -> 4.9124415 | O58: =IFERROR(O49/O55,"na") -> 4.6770671 | P58: =IFERROR(P49/P55,"na") -> 4.8072076 | ... AU58: =IFERROR(AU49/AU55,"na") -> 27.101479
A60: DPS | B60: INR/share | C60: 0 | D60: 0 | E60: 0 | F60: =3.65+0.5 -> 4.15 | G60: =C60+D60+E60+F60 -> 4.15 | H60: 0 | I60: 0 | J60: 0 | K60: 4.75 | L60: =H60+I60+J60+K60 -> 4.75 | M60: 0 | N60: 0 | O60: 0 | P60: 6 | Q60: =M60+N60+O60+P60 -> 6 | R60: 0 | S60: 0 | T60: 0 | U60: =V60-(R60+S60+T60) -> 6.1269838 | V60: =IFERROR(V58*V61,"na") -> 6.1269838 | W60: =R60 -> 0 | X60: =S60 -> 0 | Y60: =T60 -> 0 | Z60: =AA60-(W60+X60+Y60) -> 6.8616054 | AA60: =IFERROR(AA58*AA61,"na") -> 6.8616054 | AB60: =W60 -> 0 | AC60: =X60 -> 0 | AD60: =Y60 -> 0 | AE60: =AF60-(AB60+AC60+AD60) -> 7.4565861 | AF60: =IFERROR(AF58*AF61,"na") -> 7.4565861 | AG60: =AB60 -> 0 | AH60: =AC60 -> 0 | AI60: =AD60 -> 0 | AJ60: =AK60-(AG60+AH60+AI60) -> 7.9559491 | AK60: =IFERROR(AK58*AK61,"na") -> 7.9559491 | AL60: =AG60 -> 0 | AM60: =AH60 -> 0 | AN60: =AI60 -> 0 | AO60: =AP60-(AL60+AM60+AN60) -> 8.4976903 | AP60: =IFERROR(AP58*AP61,"na") -> 8.4976903 | AQ60: =AL60 -> 0 | AR60: =AM60 -> 0 | AS60: =AN60 -> 0 | AT60: =AU60-(AQ60+AR60+AS60) -> 9.0789955 | AU60: =IFERROR(AU58*AU61,"na") -> 9.0789955
A61: payout ratio | B61: % | G61: =IFERROR(G60/G58,"na") -> 0.28161009 | L61: =IFERROR(L60/L58,"na") -> 0.28327575 | Q61: =IFERROR(Q60/Q58,"na") -> 0.31892243 | V61: 0.335 | AA61: =V61 -> 0.335 | AF61: =AA61 -> 0.335 | AK61: =AF61 -> 0.335 | AP61: =AK61 -> 0.335 | AU61: =AP61 -> 0.335
A63: Balance Sheet
A65: Cash and cash equivalents | B65: INR Mn | D65: =D66+D67 -> 1180.1 | F65: =F66+F67 -> 1319.4 | G65: =G66+G67 -> 1319.4 | I65: =I66+I67 -> 1536.8 | K65: =K66+K67 -> 999.4 | L65: =L66+L67 -> 999.4 | N65: =N66+N67 -> 1522.7 | P65: =P66+P67 -> 1635.8 | Q65: =Q66+Q67 -> 1635.8 | S65: =S66+S67 -> 1543.9 | V65: =Q65+V196 -> 7413.7113 | AA65: =V65+AA196 -> 13113.522 | AF65: =AA65+AF196 -> 18935.507 | AK65: =AF65+AK196 -> 26211.863 | AP65: =AK65+AP196 -> 33424.517 | AU65: =AP65+AU196 -> 41388.039
A66: Cash and cash equivalents | B66: INR Mn | D66: 1180.1 | F66: 1319.4 | G66: =F66 -> 1319.4 | I66: 333.2 | K66: 903.7 | L66: =K66 -> 903.7 | N66: 1407.1 | P66: 1493.4 | Q66: =P66 -> 1493.4 | S66: 1396
A67: Bank balances | B67: INR Mn | D67: 0 | F67: 0 | G67: =F67 -> 0 | I67: 1203.6 | K67: 95.7 | L67: =K67 -> 95.7 | N67: 115.6 | P67: 142.4 | Q67: =P67 -> 142.4 | S67: 147.9
A68: Investments | B68: INR Mn | D68: 3993.7 | F68: 5311.7 | G68: =F68 -> 5311.7 | I68: 10733.6 | K68: 13898.1 | L68: =K68 -> 13898.1 | N68: 14866.5 | P68: 11149.2 | Q68: =P68 -> 11149.2 | S68: 11448.6 | V68: =Q68 -> 11149.2 | AA68: =V68 -> 11149.2 | AF68: =AA68 -> 11149.2 | AK68: =AF68 -> 11149.2 | AP68: =AK68 -> 11149.2 | AU68: =AP68 -> 11149.2
A69: Inventories | B69: INR Mn | D69: 6180.4 | F69: 6290 | G69: =F69 -> 6290 | I69: 6294.2 | K69: 7208.6 | L69: =K69 -> 7208.6 | N69: 6387.7 | P69: 8043.3 | Q69: =P69 -> 8043.3 | S69: 8647.8 | V69: =-IFERROR((V14*V70)/V5,"na") -> 9424.1095 | AA69: =-IFERROR((AA14*AA70)/AA5,"na") -> 9708.8426 | AF69: =-IFERROR((AF14*AF70)/AF5,"na") -> 10646.197 | AK69: =-IFERROR((AK14*AK70)/AK5,"na") -> 11153.255 | AP69: =-IFERROR((AP14*AP70)/AP5,"na") -> 11929.927 | AU69: =-IFERROR((AU14*AU70)/AU5,"na") -> 12727.975
A70: Inventories days | B70: days | G70: =-IFERROR((AVERAGE(G69)/G14)*G5,"na") -> 89.012876 | L70: =-IFERROR((AVERAGE(L69,G69)/L14)*L5,"na") -> 93.329741 | Q70: =-IFERROR((AVERAGE(Q69,L69)/Q14)*Q5,"na") -> 96.392283 | V70: 94 | AA70: =V70 -> 94 | AF70: =AA70 -> 94 | AK70: =AF70 -> 94 | AP70: =AVERAGE(AA70,AF70,AK70) -> 94 | AU70: =AP70 -> 94
A71: Accounts receivables | B71: INR Mn | D71: 8182.1 | F71: 7294 | G71: =F71 -> 7294 | I71: 8834.1 | K71: 7685.4 | L71: =K71 -> 7685.4 | N71: 9276.3 | P71: 9381.3 | Q71: =P71 -> 9381.3 | S71: 11061.7 | V71: =IFERROR((V9*V72)/V5,"na") -> 9881.9914 | AA71: =IFERROR((AA9*AA72)/AA5,"na") -> 10539.343 | AF71: =IFERROR((AF9*AF72)/AF5,"na") -> 11556.879 | AK71: =IFERROR((AK9*AK72)/AK5,"na") -> 12359.547 | AP71: =IFERROR((AP9*AP72)/AP5,"na") -> 13220.221 | AU71: =IFERROR((AU9*AU72)/AU5,"na") -> 14104.582
A72: Receivable days | B72: days | G72: =IFERROR((AVERAGE(G71)/G9)*G5,"na") -> 49.718388 | L72: =IFERROR((AVERAGE(L71,G71)/L9)*L5,"na") -> 48.670869 | Q72: =IFERROR((AVERAGE(Q71,L71)/Q9)*Q5,"na") -> 51.169258 | V72: 50 | AA72: =V72 -> 50 | AF72: =AA72 -> 50 | AK72: =AF72 -> 50 | AP72: =AVERAGE(AA72,AF72,AK72) -> 50 | AU72: =AP72 -> 50
A73: Other current assets | B73: INR Mn | D73: =D75+D76+D77+D78+D79 -> 1006.5 | F73: =F75+F76+F77+F78+F79 -> 1267.3 | G73: =G75+G76+G77+G78+G79 -> 1267.3 | I73: =I75+I76+I77+I78+I79 -> 1628.4 | K73: =K75+K76+K77+K78+K79 -> 1548.4 | L73: =L75+L76+L77+L78+L79 -> 1548.4 | N73: =N75+N76+N77+N78+N79 -> 2606.3 | P73: =P75+P76+P77+P78+P79 -> 2878.2 | Q73: =Q75+Q76+Q77+Q78+Q79 -> 2878.2 | S73: =S75+S76+S77+S78+S79 -> 2662.2 | V73: =IFERROR(V9*V74,"na") -> 2367.4369 | AA73: =IFERROR(AA9*AA74,"na") -> 2768.8323 | AF73: =IFERROR(AF9*AF74,"na") -> 3261.9019 | AK73: =IFERROR(AK9*AK74,"na") -> 3229.1978 | AP73: =IFERROR(AP9*AP74,"na") -> 3549.6968 | AU73: =IFERROR(AU9*AU74,"na") -> 3828.2141
A74: as a % of sales | B74: % | G74: =IFERROR(G73/G9,"na") -> 0.023602045 | L74: =IFERROR(L73/L9,"na") -> 0.027567347 | Q74: =IFERROR(Q73/Q9,"na") -> 0.047284377 | V74: =AVERAGE(G74,L74,Q74) -> 0.032817923 | AA74: =AVERAGE(L74,Q74,V74) -> 0.035889882 | AF74: =AVERAGE(Q74,V74,AA74) -> 0.038664061 | AK74: =AVERAGE(V74,AA74,AF74) -> 0.035790622 | AP74: =AVERAGE(AA74,AF74,AK74) -> 0.036781522 | AU74: =AVERAGE(AF74,AK74,AP74) -> 0.037078735
A75: Loans | B75: INR Mn | D75: 818.9 | F75: 798.6 | G75: =F75 -> 798.6 | I75: 158.6 | K75: 130.3 | L75: =K75 -> 130.3 | N75: 132.8 | P75: 118.5 | Q75: =P75 -> 118.5 | S75: 128.5
A76: Other financial assets | B76: INR Mn | D76: 0 | F76: 0 | G76: =F76 -> 0 | I76: 405.2 | K76: 489.9 | L76: =K76 -> 489.9 | N76: 740.5 | P76: 654.9 | Q76: =P76 -> 654.9 | S76: 817.1
A77: Current tax assets | B77: INR Mn | D77: 0 | F77: 0 | G77: =F77 -> 0 | I77: 0 | K77: 2.8 | L77: =K77 -> 2.8 | N77: 23.1 | P77: 286.4 | Q77: =P77 -> 286.4 | S77: 91.1
A78: Other current assets | B78: INR Mn | D78: 187.6 | F78: 468.7 | G78: =F78 -> 468.7 | I78: 1064.6 | K78: 925.4 | L78: =K78 -> 925.4 | N78: 1709.9 | P78: 1754.9 | Q78: =P78 -> 1754.9 | S78: 1625.5
A79: Assets held for sale | B79: INR Mn | D79: 0 | F79: 0 | G79: =F79 -> 0 | I79: 0 | K79: 0 | L79: =K79 -> 0 | N79: 0 | P79: 63.5 | Q79: =P79 -> 63.5 | S79: 0
A80: Total current assets | B80: INR Mn | D80: =D65+D68+D69+D71+D73 -> 20542.8 | F80: =F65+F68+F69+F71+F73 -> 21482.4 | G80: =G65+G68+G69+G71+G73 -> 21482.4 | I80: =I65+I68+I69+I71+I73 -> 29027.1 | K80: =K65+K68+K69+K71+K73 -> 31339.9 | L80: =L65+L68+L69+L71+L73 -> 31339.9 | N80: =N65+N68+N69+N71+N73 -> 34659.5 | P80: =P65+P68+P69+P71+P73 -> 33087.8 | Q80: =Q65+Q68+Q69+Q71+Q73 -> 33087.8 | S80: =S65+S68+S69+S71+S73 -> 35364.2 | V80: =V65+V68+V69+V71+V73 -> 40236.449 | AA80: =AA65+AA68+AA69+AA71+AA73 -> 47279.74 | AF80: =AF65+AF68+AF69+AF71+AF73 -> 55549.686 | AK80: =AK65+AK68+AK69+AK71+AK73 -> 64103.063 | AP80: =AP65+AP68+AP69+AP71+AP73 -> 73273.562 | AU80: =AU65+AU68+AU69+AU71+AU73 -> 83198.01
A82: Fixed Assets | B82: INR Mn | D82: =D83+D84 -> 14787.4 | F82: =F83+F84 -> 15074.8 | G82: =G83+G84 -> 15074.8 | I82: =I83+I84 -> 10204.4 | K82: =K83+K84 -> 9368.3 | L82: =L83+L84 -> 9368.3 | N82: =N83+N84 -> 9486.8 | P82: =P83+P84 -> 10303.2 | Q82: =Q83+Q84 -> 10303.2 | S82: =S83+S84 -> 10881.1 | V82: =Q82+V27-V167-V169 -> 10941.311 | AA82: =V82+AA27-AA167-AA169 -> 11740.881 | AF82: =AA82+AF27-AF167-AF169 -> 12468.363 | AK82: =AF82+AK27-AK167-AK169 -> 13130.766 | AP82: =AK82+AP27-AP167-AP169 -> 13833.977 | AU82: =AP82+AU27-AU167-AU169 -> 14474.359
A83: Property, plant and equipment | B83: INR Mn | D83: 14787.4 | F83: 15074.8 | G83: =F83 -> 15074.8 | I83: 7553.9 | K83: 7891.2 | L83: =K83 -> 7891.2 | N83: 7686.8 | P83: 8025.9 | Q83: =P83 -> 8025.9 | S83: 8895.7
A84: Capital WIP | B84: INR Mn | D84: 0 | F84: 0 | G84: =F84 -> 0 | I84: 2650.5 | K84: 1477.1 | L84: =K84 -> 1477.1 | N84: 1800 | P84: 2277.3 | Q84: =P84 -> 2277.3 | S84: 1985.4
A85: Associates | B85: INR Mn | D85: 0 | F85: 0 | G85: =F85 -> 0 | I85: 0 | K85: 0 | L85: =K85 -> 0 | N85: 0 | P85: 250.3 | Q85: =P85 -> 250.3 | S85: 227.6 | V85: =Q85-V138-V170-V171 -> 272.7 | AA85: =V85-AA138-AA170-AA171 -> 312.7 | AF85: =AA85-AF138-AF170-AF171 -> 352.7 | AK85: =AF85-AK138-AK170-AK171 -> 392.7 | AP85: =AK85-AP138-AP170-AP171 -> 432.7 | AU85: =AP85-AU138-AU170-AU171 -> 472.7
A86: Long-term financial assets | B86: INR Mn | D86: =D87+D88+D89 -> 2269.4 | F86: =F87+F88+F89 -> 2156.2 | G86: =G87+G88+G89 -> 2156.2 | I86: =I87+I88+I89 -> 808.7 | K86: =K87+K88+K89 -> 960.2 | L86: =L87+L88+L89 -> 960.2 | N86: =N87+N88+N89 -> 820.9 | P86: =P87+P88+P89 -> 1507.1 | Q86: =Q87+Q88+Q89 -> 1507.1 | S86: =S87+S88+S89 -> 2295.6 | V86: =Q86 -> 1507.1 | AA86: =V86 -> 1507.1 | AF86: =AA86 -> 1507.1 | AK86: =AF86 -> 1507.1 | AP86: =AK86 -> 1507.1 | AU86: =AP86 -> 1507.1
A87: Investments | B87: INR Mn | D87: 1241.5 | F87: 1178 | G87: =F87 -> 1178 | I87: 473 | K87: 532.9 | L87: =K87 -> 532.9 | N87: 407.9 | P87: 1059.9 | Q87: =P87 -> 1059.9 | S87: 1818.6
A88: Loans | B88: INR Mn | D88: 1027.9 | F88: 978.2 | G88: =F88 -> 978.2 | I88: 209.8 | K88: 84.3 | L88: =K88 -> 84.3 | N88: 76.5 | P88: 59.1 | Q88: =P88 -> 59.1 | S88: 76.4
A89: Other financial assets | B89: INR Mn | D89: 0 | F89: 0 | G89: =F89 -> 0 | I89: 125.9 | K89: 343 | L89: =K89 -> 343 | N89: 336.5 | P89: 388.1 | Q89: =P89 -> 388.1 | S89: 400.6
A90: Goodwill | B90: INR Mn | D90: 223.4 | F90: 239.3 | G90: =F90 -> 239.3 | I90: 1097.5 | K90: 1338.3 | L90: =K90 -> 1338.3 | N90: 1290.3 | P90: 1774.2 | Q90: =P90 -> 1774.2 | S90: 1862.4 | V90: =Q90 -> 1774.2 | AA90: =V90 -> 1774.2 | AF90: =AA90 -> 1774.2 | AK90: =AF90 -> 1774.2 | AP90: =AK90 -> 1774.2 | AU90: =AP90 -> 1774.2
A91: Intangibles | B91: INR Mn | D91: 0 | F91: 0 | G91: =F91 -> 0 | I91: 3696.7 | K91: 3523 | L91: =K91 -> 3523 | N91: 3330.8 | P91: 3621.8 | Q91: =P91 -> 3621.8 | S91: 3564.2 | V91: =Q91+V168 -> 3621.8 | AA91: =V91+AA168 -> 3621.8 | AF91: =AA91+AF168 -> 3621.8 | AK91: =AF91+AK168 -> 3621.8 | AP91: =AK91+AP168 -> 3621.8 | AU91: =AP91+AU168 -> 3621.8
A92: Other non-current assets | B92: INR Mn | D92: =D93+D94+D95 -> 19.3 | F92: =F93+F94+F95 -> 129.2 | G92: =G93+G94+G95 -> 129.2 | I92: =I93+I94+I95 -> 1138.4 | K92: =K93+K94+K95 -> 1212.2 | L92: =L93+L94+L95 -> 1212.2 | N92: =N93+N94+N95 -> 1365.3 | P92: =P93+P94+P95 -> 1500.2 | Q92: =Q93+Q94+Q95 -> 1500.2 | S92: =S93+S94+S95 -> 1525.8 | V92: =Q92 -> 1500.2 | AA92: =V92 -> 1500.2 | AF92: =AA92 -> 1500.2 | AK92: =AF92 -> 1500.2 | AP92: =AK92 -> 1500.2 | AU92: =AP92 -> 1500.2
A93: Income tax assets | B93: INR Mn | D93: 0 | F93: 0 | G93: =F93 -> 0 | I93: 0 | K93: 421 | L93: =K93 -> 421 | N93: 402 | P93: 648.2 | Q93: =P93 -> 648.2 | S93: 563.2
A94: Deferred tax assets | B94: INR Mn | D94: 0 | F94: 32.2 | G94: =F94 -> 32.2 | I94: 0 | K94: 37.6 | L94: =K94 -> 37.6 | N94: 50.5 | P94: 58.6 | Q94: =P94 -> 58.6 | S94: 71.4
A95: Other non-current assets | B95: INR Mn | D95: 19.3 | F95: 97 | G95: =F95 -> 97 | I95: 1138.4 | K95: 753.6 | L95: =K95 -> 753.6 | N95: 912.8 | P95: 793.4 | Q95: =P95 -> 793.4 | S95: 891.2
A96: Total non-current assets | B96: INR Mn | D96: =D82+D85+D86+D90+D91+D92 -> 17299.5 | F96: =F82+F85+F86+F90+F91+F92 -> 17599.5 | G96: =G82+G85+G86+G90+G91+G92 -> 17599.5 | I96: =I82+I85+I86+I90+I91+I92 -> 16945.7 | K96: =K82+K85+K86+K90+K91+K92 -> 16402 | L96: =L82+L85+L86+L90+L91+L92 -> 16402 | N96: =N82+N85+N86+N90+N91+N92 -> 16294.1 | P96: =P82+P85+P86+P90+P91+P92 -> 18956.8 | Q96: =Q82+Q85+Q86+Q90+Q91+Q92 -> 18956.8 | S96: =S82+S85+S86+S90+S91+S92 -> 20356.7 | V96: =V82+V85+V86+V90+V91+V92 -> 19617.311 | AA96: =AA82+AA85+AA86+AA90+AA91+AA92 -> 20456.881 | AF96: =AF82+AF85+AF86+AF90+AF91+AF92 -> 21224.363 | AK96: =AK82+AK85+AK86+AK90+AK91+AK92 -> 21926.766 | AP96: =AP82+AP85+AP86+AP90+AP91+AP92 -> 22669.977 | AU96: =AU82+AU85+AU86+AU90+AU91+AU92 -> 23350.359
A98: Total Assets | B98: INR Mn | D98: =D80+D96 -> 37842.3 | F98: =F80+F96 -> 39081.9 | G98: =G80+G96 -> 39081.9 | I98: =I80+I96 -> 45972.8 | K98: =K80+K96 -> 47741.9 | L98: =L80+L96 -> 47741.9 | N98: =N80+N96 -> 50953.6 | P98: =P80+P96 -> 52044.6 | Q98: =Q80+Q96 -> 52044.6 | S98: =S80+S96 -> 55720.9 | V98: =V80+V96 -> 59853.76 | AA98: =AA80+AA96 -> 67736.621 | AF98: =AF80+AF96 -> 76774.048 | AK98: =AK80+AK96 -> 86029.828 | AP98: =AP80+AP96 -> 95943.539 | AU98: =AU80+AU96 -> 106548.37
A100: Short term borrowings | B100: INR Mn | D100: 540.4 | F100: 749.2 | G100: =F100 -> 749.2 | I100: 922.5 | K100: 926.6 | L100: =K100 -> 926.6 | N100: 861.1 | P100: 1154.4 | Q100: =P100 -> 1154.4 | S100: 956.6 | V100: =Q100 -> 1154.4 | AA100: =V100 -> 1154.4 | AF100: =AA100 -> 1154.4 | AK100: =AF100 -> 1154.4 | AP100: =AK100 -> 1154.4 | AU100: =AP100 -> 1154.4
A101: Accounts payable | B101: INR Mn | D101: =D103+D104 -> 3748.7 | F101: =F103+F104 -> 3791.6 | G101: =G103+G104 -> 3791.6 | I101: =I103+I104 -> 4200.1 | K101: =K103+K104 -> 3903.2 | L101: =L103+L104 -> 3903.2 | N101: =N103+N104 -> 4610.5 | P101: =P103+P104 -> 5438.1 | Q101: =Q103+Q104 -> 5438.1 | S101: =S103+S104 -> 6397.5 | V101: =-IFERROR((V14*V102)/V5,"na") -> 5614.3631 | AA101: =-IFERROR((AA14*AA102)/AA5,"na") -> 5783.9913 | AF101: =-IFERROR((AF14*AF102)/AF5,"na") -> 6342.4154 | AK101: =-IFERROR((AK14*AK102)/AK5,"na") -> 6644.4923 | AP101: =-IFERROR((AP14*AP102)/AP5,"na") -> 7107.1907 | AU101: =-IFERROR((AU14*AU102)/AU5,"na") -> 7582.6234
A102: Payable days | B102: days | G102: =-IFERROR((AVERAGE(G101)/G14)*G5,"na") -> 53.656792 | L102: =-IFERROR((AVERAGE(L101,G101)/L14)*L5,"na") -> 53.202087 | Q102: =-IFERROR((AVERAGE(Q101,L101)/Q14)*Q5,"na") -> 59.037184 | V102: 56 | AA102: =V102 -> 56 | AF102: =AA102 -> 56 | AK102: =AF102 -> 56 | AP102: =AVERAGE(AA102,AF102,AK102) -> 56 | AU102: =AP102 -> 56
A103: Due to micro and small enterprises | B103: INR Mn | D103: 0 | F103: 0 | G103: =F103 -> 0 | I103: 0 | K103: 0 | L103: =K103 -> 0 | N103: 0 | P103: 0 | Q103: =P103 -> 0 | S103: 259.2
A104: Due to others | B104: INR Mn | D104: 3748.7 | F104: 3791.6 | G104: =F104 -> 3791.6 | I104: 4200.1 | K104: 3903.2 | L104: =K104 -> 3903.2 | N104: 4610.5 | P104: 5438.1 | Q104: =P104 -> 5438.1 | S104: 6138.3
A105: Other current liabilities | B105: INR Mn | D105: =D107+D108+D109+D110 -> 5379.5 | F105: =F107+F108+F109+F110 -> 5073.5 | G105: =G107+G108+G109+G110 -> 5073.5 | I105: =I107+I108+I109+I110 -> 6361.6 | K105: =K107+K108+K109+K110 -> 5394.3 | L105: =L107+L108+L109+L110 -> 5394.3 | N105: =N107+N108+N109+N110 -> 6000.6 | P105: =P107+P108+P109+P110 -> 5489.8 | Q105: =Q107+Q108+Q109+Q110 -> 5489.8 | S105: =S107+S108+S109+S110 -> 6713.9 | V105: =IFERROR(V9*V106,"na") -> 6853.161 | AA105: =IFERROR(AA9*AA106,"na") -> 7232.0523 | AF105: =IFERROR(AF9*AF106,"na") -> 7844.0395 | AK105: =IFERROR(AK9*AK106,"na") -> 8472.6928 | AP105: =IFERROR(AP9*AP106,"na") -> 9027.5263 | AU105: =IFERROR(AU9*AU106,"na") -> 9650.9072
A106: as a % of sales | B106: % | G106: =IFERROR(G105/G9,"na") -> 0.094488262 | L106: =IFERROR(L105/L9,"na") -> 0.096038841 | Q106: =IFERROR(Q105/Q9,"na") -> 0.090188927 | V106: 0.095 | AA106: =AVERAGE(L106,Q106,V106) -> 0.093742589 | AF106: =AVERAGE(Q106,V106,AA106) -> 0.092977172 | AK106: =AVERAGE(V106,AA106,AF106) -> 0.093906587 | AP106: =AVERAGE(AA106,AF106,AK106) -> 0.093542116 | AU106: =AVERAGE(AF106,AK106,AP106) -> 0.093475292
A107: Other financial liabilities | B107: INR Mn | D107: 0 | F107: 0 | G107: =F107 -> 0 | I107: 3856.4 | K107: 4182.9 | L107: =K107 -> 4182.9 | N107: 4004.2 | P107: 4431.2 | Q107: =P107 -> 4431.2 | S107: 4605.5
A108: Other current liabilities | B108: INR Mn | D108: 4241.4 | F108: 4508.7 | G108: =F108 -> 4508.7 | I108: 1318.2 | K108: 900.4 | L108: =K108 -> 900.4 | N108: 1083.1 | P108: 790.9 | Q108: =P108 -> 790.9 | S108: 1012.5
A109: Provisions | B109: INR Mn | D109: 1138.1 | F109: 564.8 | G109: =F109 -> 564.8 | I109: 321.6 | K109: 141.4 | L109: =K109 -> 141.4 | N109: 212.5 | P109: 130.7 | Q109: =P109 -> 130.7 | S109: 197.6
A110: Current tax liabilities | B110: INR Mn | D110: 0 | F110: 0 | G110: =F110 -> 0 | I110: 865.4 | K110: 169.6 | L110: =K110 -> 169.6 | N110: 700.8 | P110: 137 | Q110: =P110 -> 137 | S110: 898.3
A111: Total current liabilities | B111: INR Mn | D111: =D100+D101+D105 -> 9668.6 | F111: =F100+F101+F105 -> 9614.3 | G111: =G100+G101+G105 -> 9614.3 | I111: =I100+I101+I105 -> 11484.2 | K111: =K100+K101+K105 -> 10224.1 | L111: =L100+L101+L105 -> 10224.1 | N111: =N100+N101+N105 -> 11472.2 | P111: =P100+P101+P105 -> 12082.3 | Q111: =Q100+Q101+Q105 -> 12082.3 | S111: =S100+S101+S105 -> 14068 | V111: =V100+V101+V105 -> 13621.924 | AA111: =AA100+AA101+AA105 -> 14170.444 | AF111: =AF100+AF101+AF105 -> 15340.855 | AK111: =AK100+AK101+AK105 -> 16271.585 | AP111: =AP100+AP101+AP105 -> 17289.117 | AU111: =AU100+AU101+AU105 -> 18387.931
...

Sheet Operational Drivers
A1: Operational drivers | C1: 1Q2016 | D1: 2Q2016 | E1: 3Q2016 | F1: 4Q2016 | G1: FY2016 | H1: 1Q2017 | I1: 2Q2017 | J1: 3Q2017 | K1: 4Q2017 | L1: FY2017 | M1: 1Q2018 | N1: 2Q2018 | O1: 3Q2018 | P1: 4Q2018 | Q1: FY2018 | R1: 1Q2019 | S1: 2Q2019 | T1: 3Q2019 | U1: 4Q2019 | V1: FY2019 | W1: 1Q2020 | X1: 2Q2020 | Y1: 3Q2020 | Z1: 4Q2020 | AA1: FY2020 | AB1: 1Q2021 | AC1: 2Q2021 | AD1: 3Q2021 | AE1: 4Q2021 | AF1: FY2021 | AG1: 1Q2022 | AH1: 2Q2022 | AI1: 3Q2022 | AJ1: 4Q2022 | AK1: FY2022 | AL1: 1Q2023 | AM1: 2Q2023 | AN1: 3Q2023 | AO1: 4Q2023 | AP1: FY2023 | AQ1: 1Q2024 | AR1: 2Q2024 | AS1: 3Q2024 | AT1: 4Q2024 | AU1: FY2024
C2: 42185 | D2: 42277 | E2: 42369 | F2: 42460 | G2: 42460 | H2: 42551 | I2: 42643 | J2: 42735 | K2: 42825 | L2: 42825 | M2: 42916 | N2: 43008 | O2: 43100 | P2: 43190 | Q2: 43190 | R2: 43281 | S2: 43373 | T2: 43465 | U2: 43555 | V2: 43555 | W2: 43646 | X2: 43738 | Y2: 43830 | Z2: 43921 | AA2: 43921 | AB2: 44012 | AC2: 44104 | AD2: 44196 | AE2: 44286 | AF2: 44286 | AG2: 44377 | AH2: 44469 | AI2: 44561 | AJ2: 44651 | AK2: 44651 | AL2: 44742 | AM2: 44834 | AN2: 44926 | AO2: 45016 | AP2: 45016 | AQ2: 45107 | AR2: 45199 | AS2: 45291 | AT2: 45382 | AU2: 45382
C3: A | D3: A | E3: A | F3: A | G3: A | H3: A | I3: A | J3: A | K3: A | L3: A | M3: A | N3: A | O3: A | P3: A | Q3: A | R3: A | S3: A | T3: A | U3: F | V3: F | W3: F | X3: F | Y3: F | Z3: F | AA3: F | AB3: F | AC3: F | AD3: F | AE3: F | AF3: F | AG3: F | AH3: F | AI3: F | AJ3: F | AK3: F | AL3: F | AM3: F | AN3: F | AO3: F | AP3: F | AQ3: F | AR3: F | AS3: F | AT3: F | AU3: F
A6: Total Revenue | B6: INR Mn | C6: =Financials!C9 -> 14694.6 | D6: =Financials!D9 -> 13200.6 | E6: =Financials!E9 -> 13390.8 | F6: =Financials!F9 -> 12408.5 | G6: =C6+D6+E6+F6 -> 53694.5 | H6: =Financials!H9 -> 15693.7 | I6: =Financials!I9 -> 14176.8 | J6: =Financials!J9 -> 13343.5 | K6: =Financials!K9 -> 12953.9 | L6: =H6+I6+J6+K6 -> 56167.9 | M6: =Financials!M9 -> 15289.2 | N6: =Financials!N9 -> 15298.7 | O6: =Financials!O9 -> 15429 | P6: =Financials!P9 -> 14853.1 | Q6: =M6+N6+O6+P6 -> 60870 | R6: =Financials!R9 -> 18340.7 | S6: =Financials!S9 -> 17574.4 | T6: =Financials!T9 -> 18483 | U6: =U23+U31+U39 -> 17740.437 | V6: =R6+S6+T6+U6 -> 72138.537 | W6: =W23+W31+W39 -> 19611.711 | X6: =X23+X31+X39 -> 18792.306 | Y6: =Y23+Y31+Y39 -> 19763.872 | Z6: =Z23+Z31+Z39 -> 18980.101 | AA6: =AA23+AA31+AA39 -> 77147.989 | AB6: =AB23+AB31+AB39 -> 21442.956 | AC6: =AC23+AC31+AC39 -> 20547.039 | AD6: =AD23+AD31+AD39 -> 21609.326 | ... AU6: =AU23+AU31+AU39 -> 103245.54
A7: y-o-y growth | B7: % | C7: na | D7: na | E7: na | F7: na | G7: na | H7: =IFERROR(H6/C6-1,"na") -> 0.067990963 | I7: =IFERROR(I6/D6-1,"na") -> 0.073951184 | J7: =IFERROR(J6/E6-1,"na") -> -0.0035322759 | K7: =IFERROR(K6/F6-1,"na") -> 0.043953741 | L7: =IFERROR(L6/G6-1,"na") -> 0.046064308 | M7: =IFERROR(M6/H6-1,"na") -> -0.025774674 | N7: =IFERROR(N6/I6-1,"na") -> 0.079136335 | O7: =IFERROR(O6/J6-1,"na") -> 0.15629333 | ... AU7: =IFERROR(AU6/AP6-1,"na") -> 0.069817602
A9: Total revenue mix | B9: % | C9: =C11+C16+C21 -> 1 | D9: =D11+D16+D21 -> 1 | E9: =E11+E16+E21 -> 1 | F9: =F11+F16+F21 -> 1 | G9: =G11+G16+G21 -> 1 | H9: =H11+H16+H21 -> 1 | I9: =I11+I16+I21 -> 1 | J9: =J11+J16+J21 -> 1 | ... AU9: =AU11+AU16+AU21 -> 1
A11: Consumer & Bazaar mix | B11: % | C11: =SUM(C12:C14) -> 0.82 | D11: =SUM(D12:D14) -> 0.82 | E11: =SUM(E12:E14) -> 0.82 | F11: =SUM(F12:F14) -> 0.84 | G11: =SUM(G12:G14) -> 0.82462189 | H11: =SUM(H12:H14) -> 0.83 | I11: =SUM(I12:I14) -> 0.83 | J11: =SUM(J12:J14) -> 0.83 | ... AU11: =SUM(AU12:AU14) -> 0.84246375
A12: Adhesives & Sealants | B12: % | C12: 0.5 | D12: 0.5 | E12: 0.5 | F12: 0.53 | G12: =IFERROR(G24/G$6,"na") -> 0.50693283 | H12: 0.53 | I12: 0.53 | J12: 0.53 | K12: 0.53 | L12: =IFERROR(L24/L$6,"na") -> 0.53 | M12: 0.55 | N12: 0.55 | O12: 0.55 | P12: 0.55 | Q12: =IFERROR(Q24/Q$6,"na") -> 0.55 | R12: 0.55 | S12: 0.55 | T12: 0.55 | U12: =IFERROR(U24/U$6,"na") -> 0.54977753 | V12: =IFERROR(V24/V$6,"na") -> 0.54994529 | W12: =IFERROR(W24/W$6,"na") -> 0.5555036 | X12: =IFERROR(X24/X$6,"na") -> 0.5555036 | Y12: =IFERROR(Y24/Y$6,"na") -> 0.5555036 | Z12: =IFERROR(Z24/Z$6,"na") -> 0.55497898 | AA12: =IFERROR(AA24/AA$6,"na") -> 0.55537453 | AB12: =IFERROR(AB24/AB$6,"na") -> 0.55886947 | ... AU12: =IFERROR(AU24/AU$6,"na") -> 0.57504683
A13: Construction/ Paints Chemicals | B13: % | C13: 0.2 | D13: 0.2 | E13: 0.2 | F13: 0.19 | G13: =IFERROR(G26/G$6,"na") -> 0.19768906 | H13: 0.19 | I13: 0.19 | J13: 0.19 | K13: 0.19 | L13: =IFERROR(L26/L$6,"na") -> 0.19 | M13: 0.19 | N13: 0.19 | O13: 0.19 | P13: 0.2 | Q13: =IFERROR(Q26/Q$6,"na") -> 0.19244013 | R13: 0.2 | S13: 0.2 | T13: 0.2 | U13: =IFERROR(U26/U$6,"na") -> 0.20681638 | V13: =IFERROR(V26/V$6,"na") -> 0.2016763 | W13: =IFERROR(W26/W$6,"na") -> 0.19826054 | X13: =IFERROR(X26/X$6,"na") -> 0.19826054 | Y13: =IFERROR(Y26/Y$6,"na") -> 0.19826054 | Z13: =IFERROR(Z26/Z$6,"na") -> 0.2049069 | AA13: =IFERROR(AA26/AA$6,"na") -> 0.1998957 | AB13: =IFERROR(AB26/AB$6,"na") -> 0.19946183 | ... AU13: =IFERROR(AU26/AU$6,"na") -> 0.19020298
A14: Art/ Craft Materials & Others | B14: % | C14: 0.12 | D14: 0.12 | E14: 0.12 | F14: 0.12 | G14: =IFERROR(G28/G$6,"na") -> 0.12 | H14: 0.11 | I14: 0.11 | J14: 0.11 | K14: 0.11 | L14: =IFERROR(L28/L$6,"na") -> 0.11 | M14: 0.1 | N14: 0.1 | O14: 0.1 | P14: 0.09 | Q14: =IFERROR(Q28/Q$6,"na") -> 0.097559865 | R14: 0.09 | S14: 0.09 | T14: 0.09 | U14: =IFERROR(U28/U$6,"na") -> 0.079572603 | V14: =IFERROR(V28/V$6,"na") -> 0.087435676 | W14: =IFERROR(W28/W$6,"na") -> 0.086692229 | X14: =IFERROR(X28/X$6,"na") -> 0.086692229 | Y14: =IFERROR(Y28/Y$6,"na") -> 0.086692229 | Z14: =IFERROR(Z28/Z$6,"na") -> 0.076606669 | AA14: =IFERROR(AA28/AA$6,"na") -> 0.084210959 | AB14: =IFERROR(AB28/AB$6,"na") -> 0.084045962 | ... AU14: =IFERROR(AU28/AU$6,"na") -> 0.077213934
A16: Industrial Products mix | B16: % | C16: =SUM(C17:C19) -> 0.18 | D16: =SUM(D17:D19) -> 0.18 | E16: =SUM(E17:E19) -> 0.18 | F16: =SUM(F17:F19) -> 0.16 | G16: =SUM(G17:G19) -> 0.17537811 | H16: =SUM(H17:H19) -> 0.16 | I16: =SUM(I17:I19) -> 0.16 | J16: =SUM(J17:J19) -> 0.16 | ... AU16: =SUM(AU17:AU19) -> 0.14731442
A17: Pigment & Preparation | B17: % | C17: 0.06 | D17: 0.06 | E17: 0.06 | F17: 0.06 | G17: =IFERROR(G32/G$6,"na") -> 0.06 | H17: 0.06 | I17: 0.06 | J17: 0.06 | K17: 0.06 | L17: =IFERROR(L32/L$6,"na") -> 0.06 | M17: 0.05 | N17: 0.05 | O17: 0.05 | P17: 0.06 | Q17: =IFERROR(Q32/Q$6,"na") -> 0.052440135 | R17: 0.06 | S17: 0.06 | T17: 0.06 | U17: =IFERROR(U32/U$6,"na") -> 0.070731202 | V17: =IFERROR(V32/V$6,"na") -> 0.062639036 | W17: =IFERROR(W32/W$6,"na") -> 0.060600393 | X17: =IFERROR(X32/X$6,"na") -> 0.060600393 | Y17: =IFERROR(Y32/Y$6,"na") -> 0.060600393 | Z17: =IFERROR(Z32/Z$6,"na") -> 0.071400391 | AA17: =IFERROR(AA32/AA$6,"na") -> 0.06325743 | AB17: =IFERROR(AB32/AB$6,"na") -> 0.060967578 | ... AU17: =IFERROR(AU32/AU$6,"na") -> 0.065498114
A18: Industrial Resins | B18: % | C18: 0.06 | D18: 0.06 | E18: 0.06 | F18: 0.05 | G18: =IFERROR(G34/G$6,"na") -> 0.057689056 | H18: =11%-H19-H21 -> 0.05 | I18: =11%-I19-I21 -> 0.05 | J18: =11%-J19-J21 -> 0.05 | K18: =11%-K19-K21 -> 0.05 | L18: =IFERROR(L34/L$6,"na") -> 0.05 | M18: 0.05 | N18: 0.05 | O18: 0.05 | P18: 0.05 | Q18: =IFERROR(Q34/Q$6,"na") -> 0.05 | R18: 0.05 | S18: 0.05 | T18: 0.05 | U18: =IFERROR(U34/U$6,"na") -> 0.04911889 | V18: =IFERROR(V34/V$6,"na") -> 0.049783316 | W18: =IFERROR(W34/W$6,"na") -> 0.049565136 | X18: =IFERROR(X34/X$6,"na") -> 0.049565136 | Y18: =IFERROR(Y34/Y$6,"na") -> 0.049565136 | Z18: =IFERROR(Z34/Z$6,"na") -> 0.04866539 | AA18: =IFERROR(AA34/AA$6,"na") -> 0.049343779 | AB18: =IFERROR(AB34/AB$6,"na") -> 0.048958813 | ... AU18: =IFERROR(AU34/AU$6,"na") -> 0.047427153
A19: Industrial Adhesives | B19: % | C19: 0.06 | D19: 0.06 | E19: 0.06 | F19: 0.05 | G19: =IFERROR(G36/G$6,"na") -> 0.057689056 | H19: 0.05 | I19: 0.05 | J19: 0.05 | K19: 0.05 | L19: =IFERROR(L36/L$6,"na") -> 0.05 | M19: 0.05 | N19: 0.05 | O19: 0.05 | P19: 0.04 | Q19: =IFERROR(Q36/Q$6,"na") -> 0.047559865 | R19: 0.04 | S19: 0.04 | T19: 0.04 | U19: =IFERROR(U36/U$6,"na") -> 0.034159614 | V19: =IFERROR(V36/V$6,"na") -> 0.038563722 | W19: =IFERROR(W36/W$6,"na") -> 0.039278032 | X19: =IFERROR(X36/X$6,"na") -> 0.039278032 | Y19: =IFERROR(Y36/Y$6,"na") -> 0.039278032 | Z19: =IFERROR(Z36/Z$6,"na") -> 0.033524943 | AA19: =IFERROR(AA36/AA$6,"na") -> 0.037862646 | AB19: =IFERROR(AB36/AB$6,"na") -> 0.03771984 | ... AU19: =IFERROR(AU36/AU$6,"na") -> 0.034389151
A21: Others | B21: % | C21: 0 | D21: 0 | E21: 0 | F21: 0 | G21: =IFERROR(G39/G$6,"na") -> 0 | H21: 0.01 | I21: 0.01 | J21: 0.01 | K21: 0.01 | L21: =IFERROR(L39/L$6,"na") -> 0.01 | M21: 0.01 | N21: 0.01 | O21: 0.01 | P21: 0.01 | Q21: =IFERROR(Q39/Q$6,"na") -> 0.01 | R21: 0.01 | S21: 0.01 | T21: 0.01 | U21: =IFERROR(U39/U$6,"na") -> 0.0098237781 | V21: =IFERROR(V39/V$6,"na") -> 0.0099566632 | W21: =IFERROR(W39/W$6,"na") -> 0.010100065 | X21: =IFERROR(X39/X$6,"na") -> 0.010100065 | Y21: =IFERROR(Y39/Y$6,"na") -> 0.010100065 | Z21: =IFERROR(Z39/Z$6,"na") -> 0.009916721 | AA21: =IFERROR(AA39/AA$6,"na") -> 0.010054959 | AB21: =IFERROR(AB39/AB$6,"na") -> 0.0099765128 | ... AU21: =IFERROR(AU39/AU$6,"na") -> 0.010221829
A23: Consumer & Bazaar Revenue | B23: INR Mn | C23: =C24+C26+C28 -> 12049.572 | D23: =D24+D26+D28 -> 10824.492 | E23: =E24+E26+E28 -> 10980.456 | F23: =F24+F26+F28 -> 10423.14 | G23: =G24+G26+G28 -> 44277.66 | H23: =H24+H26+H28 -> 13025.771 | I23: =I24+I26+I28 -> 11766.744 | J23: =J24+J26+J28 -> 11075.105 | ... AU23: =AU24+AU26+AU28 -> 86980.627
A24: Adhesives & Sealants | B24: INR Mn | C24: =C$6*C12 -> 7347.3 | D24: =D$6*D12 -> 6600.3 | E24: =E$6*E12 -> 6695.4 | F24: =F$6*F12 -> 6576.505 | G24: =C24+D24+E24+F24 -> 27219.505 | H24: =H$6*H12 -> 8317.661 | I24: =I$6*I12 -> 7513.704 | J24: =J$6*J12 -> 7072.055 | K24: =K$6*K12 -> 6865.567 | L24: =H24+I24+J24+K24 -> 29768.987 | M24: =M$6*M12 -> 8409.06 | N24: =N$6*N12 -> 8414.285 | O24: =O$6*O12 -> 8485.95 | P24: =P$6*P12 -> 8169.205 | Q24: =M24+N24+O24+P24 -> 33478.5 | R24: =R$6*R12 -> 10087.385 | S24: =S$6*S12 -> 9665.92 | T24: =T$6*T12 -> 10165.65 | U24: =IFERROR((P24*(1+U25)),"na") -> 9753.2937 | V24: =R24+S24+T24+U24 -> 39672.249 | W24: =IFERROR((R24*(1+W25)),"na") -> 10894.376 | X24: =IFERROR((S24*(1+X25)),"na") -> 10439.194 | Y24: =IFERROR((T24*(1+Y25)),"na") -> 10978.902 | Z24: =IFERROR((U24*(1+Z25)),"na") -> 10533.557 | AA24: =W24+X24+Y24+Z24 -> 42846.029 | AB24: =IFERROR((W24*(1+AB25)),"na") -> 11983.813 | AC24: =IFERROR((X24*(1+AC25)),"na") -> 11483.113 | AD24: =IFERROR((Y24*(1+AD25)),"na") -> 12076.792 | AE24: =IFERROR((Z24*(1+AE25)),"na") -> 11586.913 | AF24: =AB24+AC24+AD24+AE24 -> 47130.631 | AG24: =IFERROR((AB24*(1+AG25)),"na") -> 12942.518 | AH24: =IFERROR((AC24*(1+AH25)),"na") -> 12401.762 | AI24: =IFERROR((AD24*(1+AI25)),"na") -> 13042.936 | AJ24: =IFERROR((AE24*(1+AJ25)),"na") -> 12513.866 | AK24: =AG24+AH24+AI24+AJ24 -> 50901.082 | AL24: =IFERROR((AG24*(1+AL25)),"na") -> 13977.92 | AM24: =IFERROR((AH24*(1+AM25)),"na") -> 13393.903 | AN24: =IFERROR((AI24*(1+AN25)),"na") -> 14086.37 | AO24: =IFERROR((AJ24*(1+AO25)),"na") -> 13514.975 | AP24: =AL24+AM24+AN24+AO24 -> 54973.169 | AQ24: =IFERROR((AL24*(1+AQ25)),"na") -> 15096.154 | AR24: =IFERROR((AM24*(1+AR25)),"na") -> 14465.415 | AS24: =IFERROR((AN24*(1+AS25)),"na") -> 15213.28 | AT24: =IFERROR((AO24*(1+AT25)),"na") -> 14596.173 | AU24: =AQ24+AR24+AS24+AT24 -> 59371.022
A25: y-o-y growth | B25: % | C25: na | D25: na | E25: na | F25: na | G25: na | H25: =IFERROR(H24/C24-1,"na") -> 0.13207042 | I25: =IFERROR(I24/D24-1,"na") -> 0.13838826 | J25: =IFERROR(J24/E24-1,"na") -> 0.056255788 | K25: =IFERROR(K24/F24-1,"na") -> 0.043953741 | L25: =IFERROR(L24/G24-1,"na") -> 0.09366379 | M25: =IFERROR(M24/H24-1,"na") -> 0.010988546 | N25: =IFERROR(N24/I24-1,"na") -> 0.11985846 | O25: =IFERROR(O24/J24-1,"na") -> 0.19992704 | ... T25: =IFERROR(T24/O24-1,"na") -> 0.19793895 | U25: =MEDIAN(P25,R25:T25) -> 0.19390977 | V25: =IFERROR(V24/Q24-1,"na") -> 0.18500676 | W25: 0.08 | X25: =W25 -> 0.08 | Y25: =X25 -> 0.08 | Z25: =Y25 -> 0.08 | AA25: =IFERROR(AA24/V24-1,"na") -> 0.08 | AB25: 0.1 | AC25: =AB25 -> 0.1 | AD25: =AC25 -> 0.1 | AE25: =AD25 -> 0.1 | AF25: =IFERROR(AF24/AA24-1,"na") -> 0.1 | AG25: 0.08 | AH25: =AG25 -> 0.08 | AI25: =AH25 -> 0.08 | AJ25: =AI25 -> 0.08 | AK25: =IFERROR(AK24/AF24-1,"na") -> 0.08 | AL25: 0.08 | AM25: =AL25 -> 0.08 | AN25: =AM25 -> 0.08 | AO25: =AN25 -> 0.08 | AP25: =IFERROR(AP24/AK24-1,"na") -> 0.08 | AQ25: 0.08 | AR25: =AQ25 -> 0.08 | AS25: =AR25 -> 0.08 | AT25: =AS25 -> 0.08 | AU25: =IFERROR(AU24/AP24-1,"na") -> 0.08
A26: Construction/ Paints Chemicals | B26: INR Mn | C26: =C$6*C13 -> 2938.92 | D26: =D$6*D13 -> 2640.12 | E26: =E$6*E13 -> 2678.16 | F26: =F$6*F13 -> 2357.615 | G26: =C26+D26+E26+F26 -> 10614.815 | H26: =H$6*H13 -> 2981.803 | I26: =I$6*I13 -> 2693.592 | J26: =J$6*J13 -> 2535.265 | K26: =K$6*K13 -> 2461.241 | L26: =H26+I26+J26+K26 -> 10671.901 | M26: =M$6*M13 -> 2904.948 | N26: =N$6*N13 -> 2906.753 | O26: =O$6*O13 -> 2931.51 | P26: =P$6*P13 -> 2970.62 | Q26: =M26+N26+O26+P26 -> 11713.831 | R26: =R$6*R13 -> 3668.14 | S26: =S$6*S13 -> 3514.88 | T26: =T$6*T13 -> 3696.6 | U26: =IFERROR((P26*(1+U27)),"na") -> 3669.013 | V26: =R26+S26+T26+U26 -> 14548.633 | W26: =IFERROR((R26*(1+W27)),"na") -> 3888.2284 | X26: =IFERROR((S26*(1+X27)),"na") -> 3725.7728 | Y26: =IFERROR((T26*(1+Y27)),"na") -> 3918.396 | Z26: =IFERROR((U26*(1+Z27)),"na") -> 3889.1538 | AA26: =W26+X26+Y26+Z26 -> 15421.551 | AB26: =IFERROR((W26*(1+AB27)),"na") -> 4277.0512 | AC26: =IFERROR((X26*(1+AC27)),"na") -> 4098.3501 | AD26: =IFERROR((Y26*(1+AD27)),"na") -> 4310.2356 | AE26: =IFERROR((Z26*(1+AE27)),"na") -> 4278.0691 | AF26: =AB26+AC26+AD26+AE26 -> 16963.706 | AG26: =IFERROR((AB26*(1+AG27)),"na") -> 4490.9038 | AH26: =IFERROR((AC26*(1+AH27)),"na") -> 4303.2676 | AI26: =IFERROR((AD26*(1+AI27)),"na") -> 4525.7474 | AJ26: =IFERROR((AE26*(1+AJ27)),"na") -> 4491.9726 | AK26: =AG26+AH26+AI26+AJ26 -> 17811.891 | AL26: =IFERROR((AG26*(1+AL27)),"na") -> 4715.449 | AM26: =IFERROR((AH26*(1+AM27)),"na") -> 4518.431 | AN26: =IFERROR((AI26*(1+AN27)),"na") -> 4752.0347 | AO26: =IFERROR((AJ26*(1+AO27)),"na") -> 4716.5712 | AP26: =AL26+AM26+AN26+AO26 -> 18702.486 | AQ26: =IFERROR((AL26*(1+AQ27)),"na") -> 4951.2214 | AR26: =IFERROR((AM26*(1+AR27)),"na") -> 4744.3525 | AS26: =IFERROR((AN26*(1+AS27)),"na") -> 4989.6365 | AT26: =IFERROR((AO26*(1+AT27)),"na") -> 4952.3998 | AU26: =AQ26+AR26+AS26+AT26 -> 19637.61
A27: y-o-y growth | B27: % | C27: na | D27: na | E27: na | F27: na | G27: na | H27: =IFERROR(H26/C26-1,"na") -> 0.014591415 | I27: =IFERROR(I26/D26-1,"na") -> 0.020253625 | J27: =IFERROR(J26/E26-1,"na") -> -0.053355662 | K27: =IFERROR(K26/F26-1,"na") -> 0.043953741 | L27: =IFERROR(L26/G26-1,"na") -> 0.0053779552 | M27: =IFERROR(M26/H26-1,"na") -> -0.025774674 | N27: =IFERROR(N26/I26-1,"na") -> 0.079136335 | O27: =IFERROR(O26/J26-1,"na") -> 0.15629333 | ... T27: =IFERROR(T26/O26-1,"na") -> 0.26098836 | U27: =MEDIAN(P27,R27:T27) -> 0.23510008 | V27: =IFERROR(V26/Q26-1,"na") -> 0.24200469 | W27: 0.06 | X27: =W27 -> 0.06 | Y27: =X27 -> 0.06 | Z27: =Y27 -> 0.06 | AA27: =IFERROR(AA26/V26-1,"na") -> 0.06 | AB27: 0.1 | AC27: =AB27 -> 0.1 | AD27: =AC27 -> 0.1 | AE27: =AD27 -> 0.1 | AF27: =IFERROR(AF26/AA26-1,"na") -> 0.1 | AG27: 0.05 | AH27: =AG27 -> 0.05 | AI27: =AH27 -> 0.05 | AJ27: =AI27 -> 0.05 | AK27: =IFERROR(AK26/AF26-1,"na") -> 0.05 | AL27: 0.05 | AM27: =AL27 -> 0.05 | AN27: =AM27 -> 0.05 | AO27: =AN27 -> 0.05 | AP27: =IFERROR(AP26/AK26-1,"na") -> 0.05 | AQ27: 0.05 | AR27: =AQ27 -> 0.05 | AS27: =AR27 -> 0.05 | AT27: =AS27 -> 0.05 | AU27: =IFERROR(AU26/AP26-1,"na") -> 0.05
A28: Art/ Craft Materials & Others | B28: INR Mn | C28: =C$6*C14 -> 1763.352 | D28: =D$6*D14 -> 1584.072 | E28: =E$6*E14 -> 1606.896 | F28: =F$6*F14 -> 1489.02 | G28: =C28+D28+E28+F28 -> 6443.34 | H28: =H$6*H14 -> 1726.307 | I28: =I$6*I14 -> 1559.448 | J28: =J$6*J14 -> 1467.785 | K28: =K$6*K14 -> 1424.929 | L28: =H28+I28+J28+K28 -> 6178.469 | M28: =M$6*M14 -> 1528.92 | N28: =N$6*N14 -> 1529.87 | O28: =O$6*O14 -> 1542.9 | P28: =P$6*P14 -> 1336.779 | Q28: =M28+N28+O28+P28 -> 5938.469 | R28: =R$6*R14 -> 1650.663 | S28: =S$6*S14 -> 1581.696 | T28: =T$6*T14 -> 1663.47 | U28: =IFERROR((P28*(1+U29)),"na") -> 1411.6527 | V28: =R28+S28+T28+U28 -> 6307.4817 | W28: =IFERROR((R28*(1+W29)),"na") -> 1700.1829 | X28: =IFERROR((S28*(1+X29)),"na") -> 1629.1469 | Y28: =IFERROR((T28*(1+Y29)),"na") -> 1713.3741 | Z28: =IFERROR((U28*(1+Z29)),"na") -> 1454.0023 | AA28: =W28+X28+Y28+Z28 -> 6496.7062 | AB28: =IFERROR((W28*(1+AB29)),"na") -> 1802.1939 | AC28: =IFERROR((X28*(1+AC29)),"na") -> 1726.8957 | AD28: =IFERROR((Y28*(1+AD29)),"na") -> 1816.1765 | AE28: =IFERROR((Z28*(1+AE29)),"na") -> 1541.2425 | AF28: =AB28+AC28+AD28+AE28 -> 6886.5086 | AG28: =IFERROR((AB28*(1+AG29)),"na") -> 1892.3036 | AH28: =IFERROR((AC28*(1+AH29)),"na") -> 1813.2405 | AI28: =IFERROR((AD28*(1+AI29)),"na") -> 1906.9854 | AJ28: =IFERROR((AE28*(1+AJ29)),"na") -> 1618.3046 | AK28: =AG28+AH28+AI28+AJ28 -> 7230.834 | AL28: =IFERROR((AG28*(1+AL29)),"na") -> 1986.9187 | AM28: =IFERROR((AH28*(1+AM29)),"na") -> 1903.9025 | AN28: =IFERROR((AI28*(1+AN29)),"na") -> 2002.3346 | AO28: =IFERROR((AJ28*(1+AO29)),"na") -> 1699.2198 | AP28: =AL28+AM28+AN28+AO28 -> 7592.3757 | AQ28: =IFERROR((AL28*(1+AQ29)),"na") -> 2086.2647 | AR28: =IFERROR((AM28*(1+AR29)),"na") -> 1999.0976 | AS28: =IFERROR((AN28*(1+AS29)),"na") -> 2102.4514 | AT28: =IFERROR((AO28*(1+AT29)),"na") -> 1784.1808 | AU28: =AQ28+AR28+AS28+AT28 -> 7971.9945
A29: y-o-y growth | B29: % | C29: na | D29: na | E29: na | F29: na | G29: na | H29: =IFERROR(H28/C28-1,"na") -> -0.021008284 | I29: =IFERROR(I28/D28-1,"na") -> -0.015544748 | J29: =IFERROR(J28/E28-1,"na") -> -0.086571253 | K29: =IFERROR(K28/F28-1,"na") -> -0.043042404 | L29: =IFERROR(L28/G28-1,"na") -> -0.041107717 | M29: =IFERROR(M28/H28-1,"na") -> -0.11434061 | N29: =IFERROR(N28/I28-1,"na") -> -0.018966968 | O29: =IFERROR(O28/J28-1,"na") -> 0.051175751 | ... T29: =IFERROR(T28/O28-1,"na") -> 0.078145052 | U29: =MEDIAN(P29,R29:T29) -> 0.056010566 | V29: =IFERROR(V28/Q28-1,"na") -> 0.062139374 | W29: 0.03 | X29: =W29 -> 0.03 | Y29: =X29 -> 0.03 | Z29: =Y29 -> 0.03 | AA29: =IFERROR(AA28/V28-1,"na") -> 0.03 | AB29: 0.06 | AC29: =AB29 -> 0.06 | AD29: =AC29 -> 0.06 | AE29: =AD29 -> 0.06 | AF29: =IFERROR(AF28/AA28-1,"na") -> 0.06 | AG29: 0.05 | AH29: =AG29 -> 0.05 | AI29: =AH29 -> 0.05 | AJ29: =AI29 -> 0.05 | AK29: =IFERROR(AK28/AF28-1,"na") -> 0.05 | AL29: 0.05 | AM29: =AL29 -> 0.05 | AN29: =AM29 -> 0.05 | AO29: =AN29 -> 0.05 | AP29: =IFERROR(AP28/AK28-1,"na") -> 0.05 | AQ29: =MEDIAN(AL29:AO29) -> 0.05 | AR29: =AQ29 -> 0.05 | AS29: =AR29 -> 0.05 | AT29: =AS29 -> 0.05 | AU29: =IFERROR(AU28/AP28-1,"na") -> 0.05
A31: Industrial Products Revenue | B31: INR Mn | C31: =C32+C34+C36 -> 2645.028 | D31: =D32+D34+D36 -> 2376.108 | E31: =E32+E34+E36 -> 2410.344 | F31: =F32+F34+F36 -> 1985.36 | G31: =G32+G34+G36 -> 9416.84 | H31: =H32+H34+H36 -> 2510.992 | I31: =I32+I34+I36 -> 2268.288 | J31: =J32+J34+J36 -> 2134.96 | ... AU31: =AU32+AU34+AU36 -> 15209.557
A32: Pigment & Preparation | B32: INR Mn | C32: =C$6*C17 -> 881.676 | D32: =D$6*D17 -> 792.036 | E32: =E$6*E17 -> 803.448 | F32: =F$6*F17 -> 744.51 | G32: =C32+D32+E32+F32 -> 3221.67 | H32: =H$6*H17 -> 941.622 | I32: =I$6*I17 -> 850.608 | J32: =J$6*J17 -> 800.61 | K32: =K$6*K17 -> 777.234 | L32: =H32+I32+J32+K32 -> 3370.074 | M32: =M$6*M17 -> 764.46 | N32: =N$6*N17 -> 764.935 | O32: =O$6*O17 -> 771.45 | P32: =P$6*P17 -> 891.186 | Q32: =M32+N32+O32+P32 -> 3192.031 | R32: =R$6*R17 -> 1100.442 | S32: =S$6*S17 -> 1054.464 | T32: =T$6*T17 -> 1108.98 | U32: =IFERROR((P32*(1+U33)),"na") -> 1254.8024 | V32: =R32+S32+T32+U32 -> 4518.6884 | W32: =IFERROR((R32*(1+W33)),"na") -> 1188.4774 | X32: =IFERROR((S32*(1+X33)),"na") -> 1138.8211 | Y32: =IFERROR((T32*(1+Y33)),"na") -> 1197.6984 | Z32: =IFERROR((U32*(1+Z33)),"na") -> 1355.1866 | AA32: =W32+X32+Y32+Z32 -> 4880.1835 | AB32: =IFERROR((W32*(1+AB33)),"na") -> 1307.3251 | AC32: =IFERROR((X32*(1+AC33)),"na") -> 1252.7032 | AD32: =IFERROR((Y32*(1+AD33)),"na") -> 1317.4682 | AE32: =IFERROR((Z32*(1+AE33)),"na") -> 1490.7053 | AF32: =AB32+AC32+AD32+AE32 -> 5368.2019 | AG32: =IFERROR((AB32*(1+AG33)),"na") -> 1411.9111 | AH32: =IFERROR((AC32*(1+AH33)),"na") -> 1352.9195 | AI32: =IFERROR((AD32*(1+AI33)),"na") -> 1422.8657 | AJ32: =IFERROR((AE32*(1+AJ33)),"na") -> 1609.9617 | AK32: =AG32+AH32+AI32+AJ32 -> 5797.658 | AL32: =IFERROR((AG32*(1+AL33)),"na") -> 1524.864 | AM32: =IFERROR((AH32*(1+AM33)),"na") -> 1461.153 | AN32: =IFERROR((AI32*(1+AN33)),"na") -> 1536.695 | AO32: =IFERROR((AJ32*(1+AO33)),"na") -> 1738.7587 | AP32: =AL32+AM32+AN32+AO32 -> 6261.4707 | AQ32: =IFERROR((AL32*(1+AQ33)),"na") -> 1646.8531 | AR32: =IFERROR((AM32*(1+AR33)),"na") -> 1578.0453 | AS32: =IFERROR((AN32*(1+AS33)),"na") -> 1659.6306 | AT32: =IFERROR((AO32*(1+AT33)),"na") -> 1877.8594 | AU32: =AQ32+AR32+AS32+AT32 -> 6762.3883
A33: y-o-y growth | B33: % | C33: na | D33: na | E33: na | F33: na | G33: na | H33: =IFERROR(H32/C32-1,"na") -> 0.067990963 | I33: =IFERROR(I32/D32-1,"na") -> 0.073951184 | J33: =IFERROR(J32/E32-1,"na") -> -0.0035322759 | K33: =IFERROR(K32/F32-1,"na") -> 0.043953741 | L33: =IFERROR(L32/G32-1,"na") -> 0.046064308 | M33: =IFERROR(M32/H32-1,"na") -> -0.18814556 | N33: =IFERROR(N32/I32-1,"na") -> -0.10071972 | O33: =IFERROR(O32/J32-1,"na") -> -0.036422228 | ... T33: =IFERROR(T32/O32-1,"na") -> 0.43752674 | U33: =MEDIAN(P33,R33:T33) -> 0.40801409 | V33: =IFERROR(V32/Q32-1,"na") -> 0.41561546 | W33: 0.08 | X33: =W33 -> 0.08 | Y33: =X33 -> 0.08 | Z33: =Y33 -> 0.08 | AA33: =IFERROR(AA32/V32-1,"na") -> 0.08 | AB33: 0.1 | AC33: =AB33 -> 0.1 | AD33: =AC33 -> 0.1 | AE33: =AD33 -> 0.1 | AF33: =IFERROR(AF32/AA32-1,"na") -> 0.1 | AG33: 0.08 | AH33: =AG33 -> 0.08 | AI33: =AH33 -> 0.08 | AJ33: =AI33 -> 0.08 | AK33: =IFERROR(AK32/AF32-1,"na") -> 0.08 | AL33: 0.08 | AM33: =AL33 -> 0.08 | AN33: =AM33 -> 0.08 | AO33: =AN33 -> 0.08 | AP33: =IFERROR(AP32/AK32-1,"na") -> 0.08 | AQ33: =MEDIAN(AL33:AO33) -> 0.08 | AR33: =AQ33 -> 0.08 | AS33: =AR33 -> 0.08 | AT33: =AS33 -> 0.08 | AU33: =IFERROR(AU32/AP32-1,"na") -> 0.08
A34: Industrial Resins | B34: INR Mn | C34: =C$6*C18 -> 881.676 | D34: =D$6*D18 -> 792.036 | E34: =E$6*E18 -> 803.448 | F34: =F$6*F18 -> 620.425 | G34: =C34+D34+E34+F34 -> 3097.585 | H34: =H$6*H18 -> 784.685 | I34: =I$6*I18 -> 708.84 | J34: =J$6*J18 -> 667.175 | K34: =K$6*K18 -> 647.695 | L34: =H34+I34+J34+K34 -> 2808.395 | M34: =M$6*M18 -> 764.46 | N34: =N$6*N18 -> 764.935 | O34: =O$6*O18 -> 771.45 | P34: =P$6*P18 -> 742.655 | Q34: =M34+N34+O34+P34 -> 3043.5 | R34: =R$6*R18 -> 917.035 | S34: =S$6*S18 -> 878.72 | T34: =T$6*T18 -> 924.15 | U34: =IFERROR((P34*(1+U35)),"na") -> 871.39059 | V34: =R34+S34+T34+U34 -> 3591.2956 | W34: =IFERROR((R34*(1+W35)),"na") -> 972.0571 | X34: =IFERROR((S34*(1+X35)),"na") -> 931.4432 | Y34: =IFERROR((T34*(1+Y35)),"na") -> 979.599 | Z34: =IFERROR((U34*(1+Z35)),"na") -> 923.67402 | AA34: =W34+X34+Y34+Z34 -> 3806.7733 | AB34: =IFERROR((W34*(1+AB35)),"na") -> 1049.8217 | AC34: =IFERROR((X34*(1+AC35)),"na") -> 1005.9587 | AD34: =IFERROR((Y34*(1+AD35)),"na") -> 1057.9669 | AE34: =IFERROR((Z34*(1+AE35)),"na") -> 997.56794 | AF34: =AB34+AC34+AD34+AE34 -> 4111.3152 | AG34: =IFERROR((AB34*(1+AG35)),"na") -> 1112.811 | AH34: =IFERROR((AC34*(1+AH35)),"na") -> 1066.3162 | AI34: =IFERROR((AD34*(1+AI35)),"na") -> 1121.4449 | AJ34: =IFERROR((AE34*(1+AJ35)),"na") -> 1057.422 | AK34: =AG34+AH34+AI34+AJ34 -> 4357.9941 | AL34: =IFERROR((AG34*(1+AL35)),"na") -> 1179.5796 | AM34: =IFERROR((AH34*(1+AM35)),"na") -> 1130.2951 | AN34: =IFERROR((AI34*(1+AN35)),"na") -> 1188.7316 | AO34: =IFERROR((AJ34*(1+AO35)),"na") -> 1120.8673 | AP34: =AL34+AM34+AN34+AO34 -> 4619.4737 | AQ34: =IFERROR((AL34*(1+AQ35)),"na") -> 1250.3544 | AR34: =IFERROR((AM34*(1+AR35)),"na") -> 1198.1129 | AS34: =IFERROR((AN34*(1+AS35)),"na") -> 1260.0555 | AT34: =IFERROR((AO34*(1+AT35)),"na") -> 1188.1194 | AU34: =AQ34+AR34+AS34+AT34 -> 4896.6422
A35: y-o-y growth | B35: % | C35: na | D35: na | E35: na | F35: na | G35: na | H35: =IFERROR(H34/C34-1,"na") -> -0.11000753 | I35: =IFERROR(I34/D34-1,"na") -> -0.10504068 | J35: =IFERROR(J34/E34-1,"na") -> -0.16961023 | K35: =IFERROR(K34/F34-1,"na") -> 0.043953741 | L35: =IFERROR(L34/G34-1,"na") -> -0.093359827 | M35: =IFERROR(M34/H34-1,"na") -> -0.025774674 | N35: =IFERROR(N34/I34-1,"na") -> 0.079136335 | O35: =IFERROR(O34/J34-1,"na") -> 0.15629333 | ... T35: =IFERROR(T34/O34-1,"na") -> 0.19793895 | U35: =MEDIAN(P35,R35:T35) -> 0.17334507 | V35: =IFERROR(V34/Q34-1,"na") -> 0.17998869 | W35: 0.06 | X35: =W35 -> 0.06 | Y35: =X35 -> 0.06 | Z35: =Y35 -> 0.06 | AA35: =IFERROR(AA34/V34-1,"na") -> 0.06 | AB35: 0.08 | AC35: =AB35 -> 0.08 | AD35: =AC35 -> 0.08 | AE35: =AD35 -> 0.08 | AF35: =IFERROR(AF34/AA34-1,"na") -> 0.08 | AG35: 0.06 | AH35: =AG35 -> 0.06 | AI35: =AH35 -> 0.06 | AJ35: =AI35 -> 0.06 | AK35: =IFERROR(AK34/AF34-1,"na") -> 0.06 | AL35: 0.06 | AM35: =AL35 -> 0.06 | AN35: =AM35 -> 0.06 | AO35: =AN35 -> 0.06 | AP35: =IFERROR(AP34/AK34-1,"na") -> 0.06 | AQ35: 0.06 | AR35: =AQ35 -> 0.06 | AS35: =AR35 -> 0.06 | AT35: =AS35 -> 0.06 | AU35: =IFERROR(AU34/AP34-1,"na") -> 0.06
A36: Industrial Adhesives | B36: INR Mn | C36: =C$6*C19 -> 881.676 | D36: =D$6*D19 -> 792.036 | E36: =E$6*E19 -> 803.448 | F36: =F$6*F19 -> 620.425 | G36: =C36+D36+E36+F36 -> 3097.585 | H36: =H$6*H19 -> 784.685 | I36: =I$6*I19 -> 708.84 | J36: =J$6*J19 -> 667.175 | K36: =K$6*K19 -> 647.695 | L36: =H36+I36+J36+K36 -> 2808.395 | M36: =M$6*M19 -> 764.46 | N36: =N$6*N19 -> 764.935 | O36: =O$6*O19 -> 771.45 | P36: =P$6*P19 -> 594.124 | Q36: =M36+N36+O36+P36 -> 2894.969 | R36: =R$6*R19 -> 733.628 | S36: =S$6*S19 -> 702.976 | T36: =T$6*T19 -> 739.32 | U36: =IFERROR((P36*(1+U37)),"na") -> 606.00648 | V36: =R36+S36+T36+U36 -> 2781.9305 | W36: =IFERROR((R36*(1+W37)),"na") -> 770.3094 | X36: =IFERROR((S36*(1+X37)),"na") -> 738.1248 | Y36: =IFERROR((T36*(1+Y37)),"na") -> 776.286 | Z36: =IFERROR((U36*(1+Z37)),"na") -> 636.3068 | AA36: =W36+X36+Y36+Z36 -> 2921.027 | AB36: =IFERROR((W36*(1+AB37)),"na") -> 808.82487 | AC36: =IFERROR((X36*(1+AC37)),"na") -> 775.03104 | AD36: =IFERROR((Y36*(1+AD37)),"na") -> 815.1003 | AE36: =IFERROR((Z36*(1+AE37)),"na") -> 668.12214 | AF36: =AB36+AC36+AD36+AE36 -> 3067.0784 | AG36: =IFERROR((AB36*(1+AG37)),"na") -> 849.26611 | AH36: =IFERROR((AC36*(1+AH37)),"na") -> 813.78259 | AI36: =IFERROR((AD36*(1+AI37)),"na") -> 855.85532 | AJ36: =IFERROR((AE36*(1+AJ37)),"na") -> 701.52825 | AK36: =AG36+AH36+AI36+AJ36 -> 3220.4323 | AL36: =IFERROR((AG36*(1+AL37)),"na") -> 891.72942 | AM36: =IFERROR((AH36*(1+AM37)),"na") -> 854.47172 | AN36: =IFERROR((AI36*(1+AN37)),"na") -> 898.64808 | AO36: =IFERROR((AJ36*(1+AO37)),"na") -> 736.60466 | AP36: =AL36+AM36+AN36+AO36 -> 3381.4539 | AQ36: =IFERROR((AL36*(1+AQ37)),"na") -> 936.31589 | AR36: =IFERROR((AM36*(1+AR37)),"na") -> 897.19531 | AS36: =IFERROR((AN36*(1+AS37)),"na") -> 943.58048 | AT36: =IFERROR((AO36*(1+AT37)),"na") -> 773.4349 | AU36: =AQ36+AR36+AS36+AT36 -> 3550.5266
A37: y-o-y growth | B37: % | C37: na | D37: na | E37: na | F37: na | G37: na | H37: =IFERROR(H36/C36-1,"na") -> -0.11000753 | I37: =IFERROR(I36/D36-1,"na") -> -0.10504068 | J37: =IFERROR(J36/E36-1,"na") -> -0.16961023 | K37: =IFERROR(K36/F36-1,"na") -> 0.043953741 | L37: =IFERROR(L36/G36-1,"na") -> -0.093359827 | M37: =IFERROR(M36/H36-1,"na") -> -0.025774674 | N37: =IFERROR(N36/I36-1,"na") -> 0.079136335 | O37: =IFERROR(O36/J36-1,"na") -> 0.15629333 | ... T37: =IFERROR(T36/O36-1,"na") -> -0.041648843 | U37: 0.02 | V37: =IFERROR(V36/Q36-1,"na") -> -0.039046539 | W37: 0.05 | X37: =W37 -> 0.05 | Y37: =X37 -> 0.05 | Z37: =Y37 -> 0.05 | AA37: =IFERROR(AA36/V36-1,"na") -> 0.05 | AB37: 0.05 | AC37: =AB37 -> 0.05 | AD37: =AC37 -> 0.05 | AE37: =AD37 -> 0.05 | AF37: =IFERROR(AF36/AA36-1,"na") -> 0.05 | AG37: =AE37 -> 0.05 | AH37: =AG37 -> 0.05 | AI37: =AH37 -> 0.05 | AJ37: =AI37 -> 0.05 | AK37: =IFERROR(AK36/AF36-1,"na") -> 0.05 | AL37: =AJ37 -> 0.05 | AM37: =AL37 -> 0.05 | AN37: =AM37 -> 0.05 | AO37: =AN37 -> 0.05 | AP37: =IFERROR(AP36/AK36-1,"na") -> 0.05 | AQ37: =AO37 -> 0.05 | AR37: =AQ37 -> 0.05 | AS37: =AR37 -> 0.05 | AT37: =AS37 -> 0.05 | AU37: =IFERROR(AU36/AP36-1,"na") -> 0.05
A39: Others Revenue | B39: INR Mn | C39: =C$6*C21 -> 0 | D39: =D$6*D21 -> 0 | E39: =E$6*E21 -> 0 | F39: =F$6*F21 -> 0 | G39: =C39+D39+E39+F39 -> 0 | H39: =H$6*H21 -> 156.937 | I39: =I$6*I21 -> 141.768 | J39: =J$6*J21 -> 133.435 | K39: =K$6*K21 -> 129.539 | L39: =H39+I39+J39+K39 -> 561.679 | M39: =M$6*M21 -> 152.892 | N39: =N$6*N21 -> 152.987 | O39: =O$6*O21 -> 154.29 | P39: =P$6*P21 -> 148.531 | Q39: =M39+N39+O39+P39 -> 608.7 | R39: =R$6*R21 -> 183.407 | S39: =S$6*S21 -> 175.744 | T39: =T$6*T21 -> 184.83 | U39: =IFERROR((P39*(1+U40)),"na") -> 174.27812 | V39: =R39+S39+T39+U39 -> 718.25912 | W39: =IFERROR((R39*(1+W40)),"na") -> 198.07956 | X39: =IFERROR((S39*(1+X40)),"na") -> 189.80352 | Y39: =IFERROR((T39*(1+Y40)),"na") -> 199.6164 | Z39: =IFERROR((U39*(1+Z40)),"na") -> 188.22037 | AA39: =W39+X39+Y39+Z39 -> 775.71985 | AB39: =IFERROR((W39*(1+AB40)),"na") -> 213.92592 | AC39: =IFERROR((X39*(1+AC40)),"na") -> 204.9878 | AD39: =IFERROR((Y39*(1+AD40)),"na") -> 215.58571 | AE39: =IFERROR((Z39*(1+AE40)),"na") -> 203.278 | AF39: =AB39+AC39+AD39+AE39 -> 837.77743 | AG39: =IFERROR((AB39*(1+AG40)),"na") -> 231.04 | AH39: =IFERROR((AC39*(1+AH40)),"na") -> 221.38683 | AI39: =IFERROR((AD39*(1+AI40)),"na") -> 232.83257 | AJ39: =IFERROR((AE39*(1+AJ40)),"na") -> 219.54024 | AK39: =AG39+AH39+AI39+AJ39 -> 904.79963 | AL39: =IFERROR((AG39*(1+AL40)),"na") -> 249.5232 | AM39: =IFERROR((AH39*(1+AM40)),"na") -> 239.09777 | AN39: =IFERROR((AI39*(1+AN40)),"na") -> 251.45917 | AO39: =IFERROR((AJ39*(1+AO40)),"na") -> 237.10345 | AP39: =AL39+AM39+AN39+AO39 -> 977.1836 | AQ39: =IFERROR((AL39*(1+AQ40)),"na") -> 269.48505 | AR39: =IFERROR((AM39*(1+AR40)),"na") -> 258.22559 | AS39: =IFERROR((AN39*(1+AS40)),"na") -> 271.57591 | AT39: =IFERROR((AO39*(1+AT40)),"na") -> 256.07173 | AU39: =AQ39+AR39+AS39+AT39 -> 1055.3583
A40: y-o-y growth | B40: % | C40: na | D40: na | E40: na | F40: na | G40: na | H40: =IFERROR(H39/C39-1,"na") -> na | I40: =IFERROR(I39/D39-1,"na") -> na | J40: =IFERROR(J39/E39-1,"na") -> na | K40: =IFERROR(K39/F39-1,"na") -> na | L40: =IFERROR(L39/G39-1,"na") -> na | M40: =IFERROR(M39/H39-1,"na") -> -0.025774674 | N40: =IFERROR(N39/I39-1,"na") -> 0.079136335 | O40: =IFERROR(O39/J39-1,"na") -> 0.15629333 | ... T40: =IFERROR(T39/O39-1,"na") -> 0.19793895 | U40: =MEDIAN(P40,R40:T40) -> 0.17334507 | V40: =IFERROR(V39/Q39-1,"na") -> 0.17998869 | W40: 0.08 | X40: =W40 -> 0.08 | Y40: =X40 -> 0.08 | Z40: =Y40 -> 0.08 | AA40: =IFERROR(AA39/V39-1,"na") -> 0.08 | AB40: =MEDIAN(W40:Z40) -> 0.08 | AC40: =AB40 -> 0.08 | AD40: =AC40 -> 0.08 | AE40: =AD40 -> 0.08 | AF40: =IFERROR(AF39/AA39-1,"na") -> 0.08 | AG40: =MEDIAN(AB40:AE40) -> 0.08 | AH40: =AG40 -> 0.08 | AI40: =AH40 -> 0.08 | AJ40: =AI40 -> 0.08 | AK40: =IFERROR(AK39/AF39-1,"na") -> 0.08 | AL40: =MEDIAN(AG40:AJ40) -> 0.08 | AM40: =AL40 -> 0.08 | AN40: =AM40 -> 0.08 | AO40: =AN40 -> 0.08 | AP40: =IFERROR(AP39/AK39-1,"na") -> 0.08 | AQ40: =MEDIAN(AL40:AO40) -> 0.08 | AR40: =AQ40 -> 0.08 | AS40: =AR40 -> 0.08 | AT40: =AS40 -> 0.08 | AU40: =IFERROR(AU39/AP39-1,"na") -> 0.08
A42: EBITDA
A43: EBITDA calculated | B43: INR Mn | C43: =Financials!C24 -> 3436.9 | D43: =Financials!D24 -> 3013.9 | E43: =Financials!E24 -> 2952.6 | F43: =Financials!F24 -> 2383.7 | G43: =C43+D43+E43+F43 -> 11787.1 | H43: =Financials!H24 -> 3943.3 | I43: =Financials!I24 -> 3225.4 | J43: =Financials!J24 -> 2908.8 | K43: =Financials!K24 -> 2578.5 | L43: =H43+I43+J43+K43 -> 12656 | M43: =Financials!M24 -> 3209.8 | N43: =Financials!N24 -> 3760.6 | O43: =Financials!O24 -> 3702.5 | P43: =Financials!P24 -> 2739.3 | Q43: =M43+N43+O43+P43 -> 13412.2 | R43: =Financials!R24 -> 3816.6 | S43: =Financials!S24 -> 3648.4 | T43: =Financials!T24 -> 3367.5 | U43: =U44+U46 -> 3491.4796 | V43: =R43+S43+T43+U43 -> 14323.98 | W43: =W44+W46 -> 3982.0431 | X43: =X44+X46 -> 3757.0999 | Y43: =Y44+Y46 -> 3920.6921 | Z43: =Z44+Z46 -> 3779.8981 | AA43: =W43+X43+Y43+Z43 -> 15439.733 | AB43: =AB44+AB46 -> 4278.9783 | AC43: =AC44+AC46 -> 4096.1165 | AD43: =AD44+AD46 -> 4305.8883 | AE43: =AE44+AE46 -> 4138.7581 | AF43: =AB43+AC43+AD43+AE43 -> 16819.741 | AG43: =AG44+AG46 -> 4570.9919 | AH43: =AH44+AH46 -> 4379.6588 | AI43: =AI44+AI46 -> 4606.051 | AJ43: =AJ44+AJ46 -> 4427.4348 | AK43: =AG43+AH43+AI43+AJ43 -> 17984.137 | AL43: =AL44+AL46 -> 4888.7871 | AM43: =AM44+AM46 -> 4684.4253 | AN43: =AN44+AN46 -> 4926.7051 | AO43: =AO44+AO46 -> 4736.8354 | AP43: =AL43+AM43+AN43+AO43 -> 19236.753 | AQ43: =AQ44+AQ46 -> 5229.8924 | AR43: =AR44+AR46 -> 5011.2955 | AS43: =AS44+AS46 -> 5270.4832 | AT43: =AT44+AT46 -> 5068.6848 | AU43: =AQ43+AR43+AS43+AT43 -> 20580.356
A44: EBITDA reported | B44: INR Mn | C44: =G44-(D44+E44+F44) -> 3436 | D44: 3014 | E44: 2953 | F44: 2384 | G44: 11787 | H44: 3940 | I44: 3230 | J44: 2910 | K44: 2600 | L44: =H44+I44+J44+K44 -> 12680 | M44: 3210 | N44: 3770 | O44: 3720 | P44: 2740 | Q44: =M44+N44+O44+P44 -> 13440 | R44: 3840 | S44: 3700 | T44: 3370 | U44: =IFERROR(U6*U45,"na") -> 3493.4796 | V44: =R44+S44+T44+U44 -> 14403.48 | W44: =IFERROR(W6*W45,"na") -> 3984.0431 | X44: =IFERROR(X6*X45,"na") -> 3759.0999 | Y44: =IFERROR(Y6*Y45,"na") -> 3922.6921 | Z44: =IFERROR(Z6*Z45,"na") -> 3781.8981 | AA44: =W44+X44+Y44+Z44 -> 15447.733 | AB44: =IFERROR(AB6*AB45,"na") -> 4280.9783 | AC44: =IFERROR(AC6*AC45,"na") -> 4098.1165 | AD44: =IFERROR(AD6*AD45,"na") -> 4307.8883 | AE44: =IFERROR(AE6*AE45,"na") -> 4140.7581 | AF44: =AB44+AC44+AD44+AE44 -> 16827.741 | AG44: =IFERROR(AG6*AG45,"na") -> 4572.9919 | AH44: =IFERROR(AH6*AH45,"na") -> 4381.6588 | AI44: =IFERROR(AI6*AI45,"na") -> 4608.051 | AJ44: =IFERROR(AJ6*AJ45,"na") -> 4429.4348 | AK44: =AG44+AH44+AI44+AJ44 -> 17992.137 | AL44: =IFERROR(AL6*AL45,"na") -> 4890.7871 | AM44: =IFERROR(AM6*AM45,"na") -> 4686.4253 | AN44: =IFERROR(AN6*AN45,"na") -> 4928.7051 | AO44: =IFERROR(AO6*AO45,"na") -> 4738.8354 | AP44: =AL44+AM44+AN44+AO44 -> 19244.753 | AQ44: =IFERROR(AQ6*AQ45,"na") -> 5231.8924 | AR44: =IFERROR(AR6*AR45,"na") -> 5013.2955 | AS44: =IFERROR(AS6*AS45,"na") -> 5272.4832 | AT44: =IFERROR(AT6*AT45,"na") -> 5070.6848 | AU44: =AQ44+AR44+AS44+AT44 -> 20588.356
A45: EBITDA margin | B45: % | C45: =IFERROR(C44/C6,"na") -> 0.23382739 | D45: =IFERROR(D44/D6,"na") -> 0.22832296 | E45: =IFERROR(E44/E6,"na") -> 0.22052454 | F45: =IFERROR(F44/F6,"na") -> 0.19212636 | G45: =IFERROR(G44/G6,"na") -> 0.21951969 | H45: =IFERROR(H44/H6,"na") -> 0.25105616 | I45: =IFERROR(I44/I6,"na") -> 0.22783703 | J45: =IFERROR(J44/J6,"na") -> 0.21808371 | ... T45: =IFERROR(T44/T6,"na") -> 0.18232971 | U45: =MEDIAN(P45,R45:T45) -> 0.19692185 | V45: =IFERROR(V44/V6,"na") -> 0.19966415 | W45: =MEDIAN(R45:U45) -> 0.20314613 | X45: =MEDIAN(S45:U45,W45) -> 0.20003399 | Y45: =MEDIAN(T45:U45,W45:X45) -> 0.19847792 | Z45: =MEDIAN(U45,W45:Y45) -> 0.19925595 | AA45: =IFERROR(AA44/AA6,"na") -> 0.20023507 | AB45: =MEDIAN(W45:Z45) -> 0.19964497 | AC45: =MEDIAN(X45:Z45,AB45) -> 0.19945046 | AD45: =MEDIAN(Y45:Z45,AB45:AC45) -> 0.19935321 | AE45: =MEDIAN(Z45,AB45:AD45) -> 0.19940183 | AF45: =IFERROR(AF44/AF6,"na") -> 0.19946302 | AG45: =MEDIAN(AB45:AE45) -> 0.19942615 | AH45: =MEDIAN(AC45:AE45,AG45) -> 0.19941399 | AI45: =MEDIAN(AD45:AE45,AG45:AH45) -> 0.19940791 | AJ45: =MEDIAN(AE45,AG45:AI45) -> 0.19941095 | AK45: =IFERROR(AK44/AK6,"na") -> 0.19941478 | AL45: =MEDIAN(AG45:AJ45) -> 0.19941247 | AM45: =MEDIAN(AH45:AJ45,AL45) -> 0.19941171 | AN45: =MEDIAN(AI45:AJ45,AL45:AM45) -> 0.19941133 | AO45: =MEDIAN(AJ45,AL45:AN45) -> 0.19941152 | AP45: =IFERROR(AP44/AP6,"na") -> 0.19941176 | AQ45: =MEDIAN(AL45:AO45) -> 0.19941162 | AR45: =MEDIAN(AM45:AO45,AQ45) -> 0.19941157 | AS45: =MEDIAN(AN45:AO45,AQ45:AR45) -> 0.19941155 | AT45: =MEDIAN(AO45,AQ45:AS45) -> 0.19941156 | AU45: =IFERROR(AU44/AU6,"na") -> 0.19941157
A46: Others | B46: INR Mn | C46: =C43-C44 -> 0.9 | D46: =D43-D44 -> -0.1 | E46: =E43-E44 -> -0.4 | F46: =F43-F44 -> -0.3 | G46: =C46+D46+E46+F46 -> 0.1 | H46: =H43-H44 -> 3.3 | I46: =I43-I44 -> -4.6 | J46: =J43-J44 -> -1.2 | K46: =K43-K44 -> -21.5 | L46: =H46+I46+J46+K46 -> -24 | M46: =M43-M44 -> -0.2 | N46: =N43-N44 -> -9.4 | O46: =O43-O44 -> -17.5 | P46: =P43-P44 -> -0.7 | Q46: =M46+N46+O46+P46 -> -27.8 | R46: =R43-R44 -> -23.4 | S46: =S43-S44 -> -51.6 | T46: =T43-T44 -> -2.5 | U46: -2 | V46: =R46+S46+T46+U46 -> -79.5 | W46: -2 | X46: =W46 -> -2 | Y46: =X46 -> -2 | Z46: =Y46 -> -2 | AA46: =W46+X46+Y46+Z46 -> -8 | AB46: -2 | AC46: =AB46 -> -2 | AD46: =AC46 -> -2 | AE46: =AD46 -> -2 | AF46: =AB46+AC46+AD46+AE46 -> -8 | AG46: -2 | AH46: =AG46 -> -2 | AI46: =AH46 -> -2 | AJ46: =AI46 -> -2 | AK46: =AG46+AH46+AI46+AJ46 -> -8 | AL46: -2 | AM46: =AL46 -> -2 | AN46: =AM46 -> -2 | AO46: =AN46 -> -2 | AP46: =AL46+AM46+AN46+AO46 -> -8 | AQ46: -2 | AR46: =AQ46 -> -2 | AS46: =AR46 -> -2 | AT46: =AS46 -> -2 | AU46: =AQ46+AR46+AS46+AT46 -> -8

Sheet Valuation
A1: Free Cash Flows | C1: =Summary!C1 -> FY2016 | D1: =Summary!D1 -> FY2017 | E1: =Summary!E1 -> FY2018 | F1: =Summary!F1 -> FY2019 | G1: =Summary!G1 -> FY2020 | H1: =Summary!H1 -> FY2021 | I1: =Summary!I1 -> FY2022 | J1: =Summary!J1 -> FY2023 | K1: =Summary!K1 -> FY2024 | L1: FY2025 | M1: FY2026 | N1: FY2027 | O1: FY2028 | P1: FY2029
C2: =Summary!C2 -> A | D2: =Summary!D2 -> A | E2: =Summary!E2 -> A | F2: =Summary!F2 -> F | G2: =Summary!G2 -> F | H2: =Summary!H2 -> F | I2: =Summary!I2 -> F | J2: =Summary!J2 -> F | K2: =Summary!K2 -> F | L2: =K2 -> F | M2: =L2 -> F | N2: =M2 -> F | O2: =N2 -> F | P2: =O2 -> F
A4: Revenue | C4: =Summary!C6 -> 53694.5 | D4: =Summary!D6 -> 56167.9 | E4: =Summary!E6 -> 60870 | F4: =Summary!F6 -> 72138.537 | G4: =Summary!G6 -> 77147.989 | H4: =Summary!H6 -> 84365.219 | I4: =Summary!I6 -> 90224.691 | J4: =Summary!J6 -> 96507.612 | K4: =Summary!K6 -> 103245.54 | L4: =IFERROR((K4*(1+L5)),"na") -> 110354.42 | M4: =IFERROR((L4*(1+M5)),"na") -> 117846.44 | N4: =IFERROR((M4*(1+N5)),"na") -> 125733.56 | O4: =IFERROR((N4*(1+O5)),"na") -> 134027.38 | P4: =IFERROR((O4*(1+P5)),"na") -> 142739.16
A5: y-o-y growth | C5: na | D5: =IFERROR(D4/C4-1,"na") -> 0.046064308 | E5: =IFERROR(E4/D4-1,"na") -> 0.083715076 | F5: =IFERROR(F4/E4-1,"na") -> 0.18512464 | G5: =IFERROR(G4/F4-1,"na") -> 0.069442112 | H5: =IFERROR(H4/G4-1,"na") -> 0.093550455 | I5: =IFERROR(I4/H4-1,"na") -> 0.06945365 | J5: =IFERROR(J4/I4-1,"na") -> 0.069636378 | K5: =IFERROR(K4/J4-1,"na") -> 0.069817602 | L5: =K5+($B$32-$K$5)/5 -> 0.068854081 | M5: =L5+($B$32-$K$5)/5 -> 0.067890561 | N5: =M5+($B$32-$K$5)/5 -> 0.066927041 | O5: =N5+($B$32-$K$5)/5 -> 0.06596352 | P5: =O5+($B$32-$K$5)/5 -> 0.065
A6: EBIT | C6: =Summary!C9 -> 10455.8 | D6: =Summary!D9 -> 11504.6 | E6: =Summary!E9 -> 12213.4 | F6: =Summary!F9 -> 13062.091 | G6: =Summary!G9 -> 14139.303 | H6: =Summary!H9 -> 15447.223 | I6: =Summary!I9 -> 16546.54 | J6: =Summary!J9 -> 17739.964 | K6: =Summary!K9 -> 19020.737 | L6: =IFERROR(L4*L7,"na") -> 22070.884 | M6: =IFERROR(M4*M7,"na") -> 23569.288 | N6: =IFERROR(N4*N7,"na") -> 25146.711 | O6: =IFERROR(O4*O7,"na") -> 26805.477 | P6: =IFERROR(P4*P7,"na") -> 28547.833
A7: EBIT margin | C7: =IFERROR(C6/C4,"na") -> 0.19472758 | D7: =IFERROR(D6/D4,"na") -> 0.20482518 | E7: =IFERROR(E6/E4,"na") -> 0.20064728 | F7: =IFERROR(F6/F4,"na") -> 0.18106953 | G7: =IFERROR(G6/G4,"na") -> 0.18327507 | H7: =IFERROR(H6/H4,"na") -> 0.18309942 | I7: =IFERROR(I6/I4,"na") -> 0.18339259 | J7: =IFERROR(J6/J4,"na") -> 0.18381933 | K7: =IFERROR(K6/K4,"na") -> 0.18422817 | L7: 0.2 | M7: =L7 -> 0.2 | N7: =M7 -> 0.2 | O7: =N7 -> 0.2 | P7: =O7 -> 0.2
A8: Depreciation & Amortization | C8: =-Financials!G27 -> 1331.3 | D8: =-Financials!L27 -> 1151.4 | E8: =-Financials!Q27 -> 1198.8 | F8: =-Financials!V27 -> 1261.8887 | G8: =-Financials!AA27 -> 1300.4302 | H8: =-Financials!AF27 -> 1372.5186 | I8: =-Financials!AK27 -> 1437.5968 | J8: =-Financials!AP27 -> 1496.7884 | K8: =-Financials!AU27 -> 1559.6186 | L8: =IFERROR(L4*L9,"na") -> 1667.0047 | M8: =IFERROR(M4*M9,"na") -> 1780.1786 | N8: =IFERROR(N4*N9,"na") -> 1899.3207 | O8: =IFERROR(O4*O9,"na") -> 2024.6065 | P8: =IFERROR(P4*P9,"na") -> 2156.206
A9: as a % of sales | C9: =IFERROR(C8/C4,"na") -> 0.024793973 | D9: =IFERROR(D8/D4,"na") -> 0.020499253 | E9: =IFERROR(E8/E4,"na") -> 0.019694431 | F9: =IFERROR(F8/F4,"na") -> 0.017492574 | G9: =IFERROR(G8/G4,"na") -> 0.016856306 | H9: =IFERROR(H8/H4,"na") -> 0.016268773 | I9: =IFERROR(I8/I4,"na") -> 0.015933518 | J9: =IFERROR(J8/J4,"na") -> 0.015509537 | K9: =IFERROR(K8/K4,"na") -> 0.015105917 | L9: =K9 -> 0.015105917 | M9: =L9 -> 0.015105917 | N9: =M9 -> 0.015105917 | O9: =N9 -> 0.015105917 | P9: =O9 -> 0.015105917
A10: Tax on EBIT | C10: =-C6*C11 -> -3114.3476 | D10: =-D6*D11 -> -3530.2635 | E10: =-E6*E11 -> -3362.3702 | F10: =-F6*F11 -> -4357.5258 | G10: =-G6*G11 -> -4241.7909 | H10: =-H6*H11 -> -4634.1668 | I10: =-I6*I11 -> -4963.9619 | J10: =-J6*J11 -> -5321.9893 | ... P10: =-P6*P11 -> -8564.3498
A11: Tax rate | C11: =Financials!G42 -> 0.29785837 | D11: =Financials!L42 -> 0.30685669 | E11: =Financials!Q42 -> 0.27530174 | F11: =Financials!V42 -> 0.33360094 | G11: =Financials!AA42 -> 0.3 | H11: =Financials!AF42 -> 0.3 | I11: =Financials!AK42 -> 0.3 | J11: =Financials!AP42 -> 0.3 | K11: =Financials!AU42 -> 0.3 | L11: =K11 -> 0.3 | M11: =L11 -> 0.3 | N11: =M11 -> 0.3 | O11: =N11 -> 0.3 | P11: =O11 -> 0.3
A12: Gross cash flow | C12: =C6+C8+C10 -> 8672.7524 | D12: =D6+D8+D10 -> 9125.7365 | E12: =E6+E8+E10 -> 10049.83 | F12: =F6+F8+F10 -> 9966.4538 | G12: =G6+G8+G10 -> 11197.942 | H12: =H6+H8+H10 -> 12185.575 | I12: =I6+I8+I10 -> 13020.175 | J12: =J6+J8+J10 -> 13914.764 | ... P12: =P6+P8+P10 -> 22139.689
A14: Decrease / (increase) in working capital | D14: =D15-C15 -> 1158.7 | E14: =E15-D15 -> 2230 | F14: =F15-E15 -> -168.8863 | G14: =G15-F15 -> 794.96036 | H14: =H15-G15 -> 1277.5496 | I14: =I15-H15 -> 346.29078 | J14: =J15-I15 -> 940.31355 | K14: =K15-J15 -> 862.1128 | ... P14: =P15-O15 -> 1132.9803
A15: Net working capital | C15: =Financials!G69+Financials!G71+Financials!G73-Financials!G101-Financials!G105 -> 5986.2 | D15: =Financials!L69+Financials!L71+Financials!L73-Financials!L101-Financials!L105 -> 7144.9 | E15: =Financials!Q69+Financials!Q71+Financials!Q73-Financials!Q101-Financials!Q105 -> 9374.9 | F15: =Financials!V69+Financials!V71+Financials!V73-Financials!V101-Financials!V105 -> 9206.0137 | G15: =Financials!AA69+Financials!AA71+Financials!AA73-Financials!AA101-Financials!AA105 -> 10000.974 | H15: =Financials!AF69+Financials!AF71+Financials!AF73-Financials!AF101-Financials!AF105 -> 11278.524 | I15: =Financials!AK69+Financials!AK71+Financials!AK73-Financials!AK101-Financials!AK105 -> 11624.814 | J15: =Financials!AP69+Financials!AP71+Financials!AP73-Financials!AP101-Financials!AP105 -> 12565.128 | K15: =Financials!AU69+Financials!AU71+Financials!AU73-Financials!AU101-Financials!AU105 -> 13427.241 | L15: =IFERROR(L4*L16,"na") -> 14351.761 | M15: =IFERROR(M4*M16,"na") -> 15326.11 | N15: =IFERROR(N4*N16,"na") -> 16351.841 | O15: =IFERROR(O4*O16,"na") -> 17430.466 | P15: =IFERROR(P4*P16,"na") -> 18563.447
A16: as a % of sales | C16: =IFERROR(C15/C4,"na") -> 0.11148628 | D16: =IFERROR(D15/D4,"na") -> 0.12720611 | E16: =IFERROR(E15/E4,"na") -> 0.15401511 | F16: =IFERROR(F15/F4,"na") -> 0.12761575 | G16: =IFERROR(G15/G4,"na") -> 0.12963363 | H16: =IFERROR(H15/H4,"na") -> 0.13368689 | I16: =IFERROR(I15/I4,"na") -> 0.12884294 | J16: =IFERROR(J15/J4,"na") -> 0.13019831 | K16: =IFERROR(K15/K4,"na") -> 0.13005153 | L16: =K16 -> 0.13005153 | M16: =L16 -> 0.13005153 | N16: =M16 -> 0.13005153 | O16: =N16 -> 0.13005153 | P16: =O16 -> 0.13005153
A17: Capital Expenditure | C17: =Financials!G167+Financials!G168+Financials!G169 -> -1658.5 | D17: =Financials!L167+Financials!L168+Financials!L169 -> -1224.2 | E17: =Financials!Q167+Financials!Q168+Financials!Q169 -> -1760 | F17: =Financials!V167+Financials!V168+Financials!V169 -> -1900 | G17: =Financials!AA167+Financials!AA168+Financials!AA169 -> -2100 | H17: =Financials!AF167+Financials!AF168+Financials!AF169 -> -2100 | I17: =Financials!AK167+Financials!AK168+Financials!AK169 -> -2100 | J17: =Financials!AP167+Financials!AP168+Financials!AP169 -> -2200 | K17: =Financials!AU167+Financials!AU168+Financials!AU169 -> -2200 | L17: =-L18*L4 -> -2214.5841 | M17: =-M18*M4 -> -2218.7448 | N17: =-N18*N4 -> -2211.2661 | O17: =-O18*O4 -> -2190.8678 | P17: =-P18*P4 -> -2156.206
A18: as a % of sales | C18: =-IFERROR(C17/C4,"na") -> 0.030887707 | D18: =-IFERROR(D17/D4,"na") -> 0.021795367 | E18: =-IFERROR(E17/E4,"na") -> 0.028914079 | F18: =-IFERROR(F17/F4,"na") -> 0.026338211 | G18: =-IFERROR(G17/G4,"na") -> 0.027220411 | H18: =-IFERROR(H17/H4,"na") -> 0.024891774 | I18: =-IFERROR(I17/I4,"na") -> 0.023275225 | J18: =-IFERROR(J17/J4,"na") -> 0.022796129 | K18: =-IFERROR(K17/K4,"na") -> 0.021308426 | L18: =K18+($P$9-$K$18)/5 -> 0.020067924 | M18: =L18+($P$9-$K$18)/5 -> 0.018827422 | N18: =M18+($P$9-$K$18)/5 -> 0.017586921 | O18: =N18+($P$9-$K$18)/5 -> 0.016346419 | P18: =O18+($P$9-$K$18)/5 -> 0.015105917
A19: Free Cash Flow | C19: =C12+C14+C17 -> 7014.2524 | D19: =D12+D14+D17 -> 9060.2365 | E19: =E12+E14+E17 -> 10519.83 | F19: =F12+F14+F17 -> 7897.5675 | G19: =G12+G14+G17 -> 9892.9027 | H19: =H12+H14+H17 -> 11363.124 | I19: =I12+I14+I17 -> 11266.465 | J19: =J12+J14+J17 -> 12655.077 | ... P19: =P12+P14+P17 -> 21116.463
A22: WACC Assumptions | D22: Enterprise value | J22: Valuation
A23: Risk free rate | B23: 0.055 | D23: Share price | H23: 1104 | J23: Present value of forecast cash flows (2019-2029) | O23: =IFERROR(NPV($B$31,OFFSET($F$19,0,0,1,COUNTIF($C$2:$P$2,"F"))),"n/a") -> 94017.549
A24: Beta | B24: 0.88 | D24: Share count adjustment factor | H24: 1 | J24: Present value of forecast cash flows (2031-perpetuity) | O24: =IFERROR((OFFSET(E19,0,COUNT(F19:IC19)))*((1+B32)/($B$31-B32))/((1+$B$31)^(COUNTIFS(C2:P2,"F"))),"na") -> 496740.28
A25: Market risk premium | B25: 0.08 | D25: No. of shares used to calculate mkt cap | H25: =Financials!Q52 -> 507.8
A26: Marginal tax rate | B26: 0.3 | D26: Total market cap (INR mn) | H26: =H23*H25 -> 560611.2 | J26: net debt | O26: =H27 -> -410.3
A27: Pre-tax cost of debt | B27: 0.06 | D27: Net Debt | H27: =Financials!Q100+Financials!Q113-Financials!Q65 -> -410.3 | J27: unfunded pension liabilities | O27: =H31 -> 0
A28: Cost of equity | B28: =B23+B24*B25 -> 0.1254 | D28: Minority Interest | H28: =Financials!Q125 -> 1750.1 | J28: net investments | O28: =H29 -> 12656.3
A29: Target debt/value ratio | B29: 0.5 | D29: Investment | H29: =Financials!Q68+Financials!Q86 -> 12656.3 | J29: associates | O29: =H30 -> 250.3
A30: Target equity/value ratio | B30: =1-B29 -> 0.5 | D30: Associates | H30: =Financials!Q85 -> 250.3 | J30: minority interests | O30: =H28 -> 1750.1
A31: WACC Assumptions | B31: =(B27*B29*(1-B26))+B28*B30 -> 0.0837 | D31: Pension Liabilities | H31: =Financials!Q115 -> 0 | J31: Total Valuation | O31: =O23+O24+-O26-O27+O28+O29-O30 -> 602324.63
A32: Long-term growth rate | B32: 0.065 | D32: Other Obligations | H32: =Financials!Q114 -> 381.7
D33: Enterprise Value | H33: =H26+H27+H28-H29-H30+H31+H32 -> 549426.1 | J33: NPV/share | O33: =O31/H25*1 -> 1186.1454
J34: Current share prices | O34: =H23 -> 1104
J35: Upside (downside) to NPV/share | O35: =IFERROR(O33/O34-1,"na") -> 0.074407052
