Workbook

Sheet S
A1: Schedules and Assumptions (All numbers in INR lacs) | B1: FY 2020 | C1: FY 2021 | D1: FY 2022 | E1: FY 2023 | F1: FY 2024 | G1: FY 2025E | H1: FY 2026E | I1: FY 2027E | J1: FY 2028E | K1: FY 2029E | L1: Select Case | M1: Pessimistic | N1: Pessimistic | O1: Normal | P1: Optimistic
A2: 'Total Revenue' | B2: 3452 | C2: 749 | D2: 1656 | E2: 3830 | F2: 6264 | G2: =SUM(G3:G5) -> 7229.0156 | H2: =SUM(H3:H5) -> 7730.7944 | I2: =SUM(I3:I5) -> 8261.149 | J2: =SUM(J3:J5) -> 8821.5627 | K2: =SUM(K3:K5) -> 9413.5916
A3: Revenue from sale of tickets | B3: 1731 | C3: 102 | D3: 670 | E3: 1894 | F3: 3280 | G3: =G$7*G10 -> 3621.7846 | H3: =H$7*H10 -> 3873.1791 | I3: =I$7*I10 -> 4138.8902 | J3: =J$7*J10 -> 4419.6612 | K3: =K$7*K10 -> 4716.2716
A4: Revenue from f&b | B4: 960 | C4: 76 | D4: 412 | E4: 1193 | F4: 1958 | G4: =G$7*G11 -> 2014.9849 | H4: =H$7*H11 -> 2154.8485 | I4: =I$7*I11 -> 2302.6773 | J4: =J$7*J11 -> 2458.8846 | K4: =K$7*K11 -> 2623.9042
A5: Other revenue | B5: 761 | C5: 571 | D5: 574 | E5: 743 | F5: 1026 | G5: =G$7*G12 -> 1592.2462 | H5: =H$7*H12 -> 1702.7668 | I5: =I$7*I12 -> 1819.5814 | J5: =J$7*J12 -> 1943.0169 | K5: =K$7*K12 -> 2073.4158
X6: =FCFE!B18 -> -0.46720596 | Y6: 10 | Z6: =Y6+10 -> 20 | AA6: =Z6+10 -> 30 | AB6: =AA6+10 -> 40 | AC6: =AB6+10 -> 50 | AD6: =AC6+10 -> 60 | AE6: =AD6+10 -> 70 | AF6: =AE6+10 -> 80 | AG6: =AF6+10 -> 90 | ... AK6: =AJ6+10 -> 130
A7: No. of screens | B7: 845 | C7: 842 | D7: 871 | E7: 1680 | F7: 1718 | G7: =F7+G8 -> 1768 | H7: =G7+H8 -> 1818 | I7: =H7+I8 -> 1868 | J7: =I7+J8 -> 1918 | K7: =J7+K8 -> 1968 | X7: 0.03 | Y7: -0.53464523 | Z7: -0.53427998 | AA7: -0.53391472 | AB7: -0.53354947 | AC7: -0.53318421 | AD7: -0.53281896 | AE7: -0.5324537 | AF7: -0.53208845 | AG7: -0.53172319 | AH7: -0.53135794 | AI7: -0.53099268 | AJ7: -0.53062743 | AK7: -0.53026217
C8: =C7-B7 -> -3 | D8: =D7-C7 -> 29 | E8: =E7-D7 -> 809 | F8: =F7-E7 -> 38 | G8: =HLOOKUP(M1,$N:$P,8,0) -> 50 | H8: =G8 -> 50 | I8: =H8 -> 50 | J8: =I8 -> 50 | K8: =J8 -> 50 | N8: 50 | O8: 80 | P8: 130 | X8: =X7+0.5% -> 0.035 | Y8: -0.50518214 | Z8: -0.50399403 | AA8: -0.50280591 | AB8: -0.5016178 | AC8: -0.50042968 | AD8: -0.49924157 | AE8: -0.49805346 | AF8: -0.49686534 | AG8: -0.49567723 | AH8: -0.49448911 | AI8: -0.493301 | AJ8: -0.49211288 | AK8: -0.49092477
X9: =X8+0.5% -> 0.04 | Y9: -0.47529785 | Z9: -0.47327488 | AA9: -0.47125191 | AB9: -0.46922893 | AC9: -0.46720596 | AD9: -0.46518299 | AE9: -0.46316002 | AF9: -0.46113705 | AG9: -0.45911408 | AH9: -0.45709111 | AI9: -0.45506814 | AJ9: -0.45304516 | AK9: -0.45102219
A10: Revenue from sale of tickets / screen | B10: =B3/B$7 -> 2.0485207 | C10: =C3/C$7 -> 0.12114014 | D10: =D3/D$7 -> 0.76923077 | E10: =E3/E$7 -> 1.127381 | F10: =F3/F$7 -> 1.9091967 | G10: =MAX(B10:F10) -> 2.0485207 | H10: =G10*(1+$B$14) -> 2.1304615 | I10: =H10*(1+$B$14) -> 2.21568 | J10: =I10*(1+$B$14) -> 2.3043072 | K10: =J10*(1+$B$14) -> 2.3964795 | X10: =X9+0.5% -> 0.045 | Y10: -0.44498819 | Z10: -0.44211825 | AA10: -0.4392483 | AB10: -0.43637836 | AC10: -0.43350842 | AD10: -0.43063848 | AE10: -0.42776853 | AF10: -0.42489859 | AG10: -0.42202865 | AH10: -0.4191587 | AI10: -0.41628876 | AJ10: -0.41341882 | AK10: -0.41054887
A11: Revenue from f&b / screen | B11: =B4/B$7 -> 1.1360947 | C11: =C4/C$7 -> 0.090261283 | D11: =D4/D$7 -> 0.47301952 | E11: =E4/E$7 -> 0.71011905 | F11: =F4/F$7 -> 1.1396973 | G11: =MAX(B11:F11) -> 1.1396973 | H11: =G11*(1+$B$14) -> 1.1852852 | I11: =H11*(1+$B$14) -> 1.2326966 | J11: =I11*(1+$B$14) -> 1.2820045 | K11: =J11*(1+$B$14) -> 1.3332847 | X11: =X10+0.5% -> 0.05 | Y11: -0.414249 | Z11: -0.41051985 | AA11: -0.4067907 | AB11: -0.40306155 | AC11: -0.3993324 | AD11: -0.39560325 | AE11: -0.3918741 | AF11: -0.38814495 | AG11: -0.3844158 | AH11: -0.38068665 | AI11: -0.37695751 | AJ11: -0.37322836 | AK11: -0.36949921
A12: Other revenue / screen | B12: =B5/B$7 -> 0.90059172 | C12: =C5/C$7 -> 0.67814727 | D12: =D5/D$7 -> 0.65901263 | E12: =E5/E$7 -> 0.4422619 | F12: =F5/F$7 -> 0.59720605 | G12: =MAX(B12:F12) -> 0.90059172 | H12: =G12*(1+$B$14) -> 0.93661538 | I12: =H12*(1+$B$14) -> 0.97408 | J12: =I12*(1+$B$14) -> 1.0130432 | K12: =J12*(1+$B$14) -> 1.0535649 | X12: =X11+0.5% -> 0.055 | Y12: -0.38307607 | Z12: -0.37847536 | AA12: -0.37387465 | AB12: -0.36927394 | AC12: -0.36467324 | AD12: -0.36007253 | AE12: -0.35547182 | AF12: -0.35087111 | AG12: -0.3462704 | AH12: -0.34166969 | AI12: -0.33706898 | AJ12: -0.33246827 | AK12: -0.32786757
X13: =X12+0.5% -> 0.06 | Y13: -0.3514652 | Z13: -0.34598045 | AA13: -0.34049571 | AB13: -0.33501097 | AC13: -0.32952623 | AD13: -0.32404149 | AE13: -0.31855674 | AF13: -0.313072 | AG13: -0.30758726 | AH13: -0.30210252 | AI13: -0.29661778 | AJ13: -0.29113304 | AK13: -0.28564829
A14: Inflation | B14: 0.04 | N14: 0.04 | O14: 0.05 | P14: 0.06 | X14: =X13+0.5% -> 0.065 | Y14: -0.31941213 | Z14: -0.31303076 | AA14: -0.30664939 | AB14: -0.30026803 | AC14: -0.29388666 | AD14: -0.28750529 | AE14: -0.28112392 | AF14: -0.27474255 | AG14: -0.26836118 | AH14: -0.26197981 | AI14: -0.25559844 | AJ14: -0.24921708 | AK14: -0.24283571
X15: =X14+0.5% -> 0.07 | Y15: -0.28691262 | Z15: -0.27962191 | AA15: -0.2723312 | AB15: -0.26504049 | AC15: -0.25774978 | AD15: -0.25045907 | AE15: -0.24316836 | AF15: -0.23587765 | AG15: -0.22858694 | AH15: -0.22129623 | AI15: -0.21400551 | AJ15: -0.2067148 | AK15: -0.19942409
A16: Raw Materials as % of Total Revenue | B16: =IS!B3/IS!B$2 -> 0.076477404 | C16: =IS!C3/IS!C$2 -> 0.034712951 | D16: =IS!D3/IS!D$2 -> 0 | E16: =IS!E3/IS!E$2 -> 0 | F16: =IS!F3/IS!F$2 -> 0 | G16: 0 | H16: =G16 -> 0 | I16: =H16 -> 0 | J16: =I16 -> 0 | K16: =J16 -> 0 | X16: =X15+0.5% -> 0.075 | Y16: -0.25396239 | Z16: -0.2457495 | AA16: -0.23753661 | AB16: -0.22932372 | AC16: -0.22111083 | AD16: -0.21289794 | AE16: -0.20468505 | AF16: -0.19647216 | AG16: -0.18825927 | AH16: -0.18004638 | AI16: -0.17183349 | AJ16: -0.1636206 | AK16: -0.15540771
A17: Power & Fuel Cost as % of Total Revenue | B17: =IS!B4/IS!B$2 -> 0.05967555 | C17: =IS!C4/IS!C$2 -> 0.076101469 | D17: =IS!D4/IS!D$2 -> 0.060990338 | E17: =IS!E4/IS!E$2 -> 0.060835509 | F17: =IS!F4/IS!F$2 -> 0.061462324 | G17: 0.06 | H17: =G17 -> 0.06 | I17: =H17 -> 0.06 | J17: =I17 -> 0.06 | K17: =J17 -> 0.06
A18: Employee Cost as % of Total Revenue | B18: =IS!B5/IS!B$2 -> 0.11413673 | C18: =IS!C5/IS!C$2 -> 0.28971963 | D18: =IS!D5/IS!D$2 -> 0.16002415 | E18: =IS!E5/IS!E$2 -> 0.11462141 | F18: =IS!F5/IS!F$2 -> 0.10488506 | G18: 0.11 | H18: =G18 -> 0.11 | I18: =H18 -> 0.11 | J18: =I18 -> 0.11 | K18: =J18 -> 0.11
A19: Selling & Administrative Expenses as % of Total Revenue | B19: =IS!B6/IS!B$2 -> 0.078505214 | C19: =IS!C6/IS!C$2 -> 0.097463284 | D19: =IS!D6/IS!D$2 -> 0.065217391 | E19: =IS!E6/IS!E$2 -> 0.065274151 | F19: =IS!F6/IS!F$2 -> 0.060983397 | G19: 0.06 | H19: =G19 -> 0.06 | I19: =H19 -> 0.06 | J19: =I19 -> 0.06 | K19: =J19 -> 0.06
A20: Operating & Other expenses as % of Total Revenue | B20: =IS!B7/IS!B$2 -> 0.349073 | C20: =IS!C7/IS!C$2 -> 0.32443258 | D20: =IS!D7/IS!D$2 -> 0.45229469 | E20: =IS!E7/IS!E$2 -> 0.46788512 | F20: =IS!F7/IS!F$2 -> 0.45849298 | G20: 0.45 | H20: =G20 -> 0.45 | I20: =H20 -> 0.45 | J20: =I20 -> 0.45 | K20: =J20 -> 0.45
A23: Beginning balance of fixed assets | C23: =B26 -> 4898.4 | D23: =C26 -> 4555.53 | E23: =D26 -> 4343.43 | F23: =E26 -> 8641.4 | G23: =F26 -> 8916.9 | H23: =G26 -> 8752.0144 | I23: =H26 -> 8594.6945 | J23: =I26 -> 8444.5932 | K23: =J26 -> 8301.3792 | M23: Normal
A24: Add: Net purchases | C24: =C26-C23+C25 -> -128.87 | D24: =D26-D23+D25 -> 18.9 | E24: =E26-E23+E25 -> 4570.97 | F24: =F26-F23+F25 -> 702.5 | G24: =$B$30*G8 -> 250 | H24: =$B$30*H8 -> 250 | I24: =$B$30*I8 -> 250 | J24: =$B$30*J8 -> 250 | K24: =$B$30*K8 -> 250
A25: Less: Depreciation | C25: 214 | D25: 231 | E25: 273 | F25: 427 | G25: =(G23+G24/2)*G28 -> 414.88564 | H25: =(H23+H24/2)*H28 -> 407.3199 | I25: =(I23+I24/2)*I28 -> 400.10131 | J25: =(J23+J24/2)*J28 -> 393.21394 | K25: =(K23+K24/2)*K28 -> 386.6426
A26: Closing balance of fixed assets | B26: =BS!B8 -> 4898.4 | C26: =BS!C8 -> 4555.53 | D26: =BS!D8 -> 4343.43 | E26: =BS!E8 -> 8641.4 | F26: =BS!F8 -> 8916.9 | G26: =G23+G24-G25 -> 8752.0144 | H26: =H23+H24-H25 -> 8594.6945 | I26: =I23+I24-I25 -> 8444.5932 | J26: =J23+J24-J25 -> 8301.3792 | K26: =K23+K24-K25 -> 8164.7366
A28: Depreciation rate | C28: =C25/(C23+C24/2) -> 0.044270076 | D28: =D25/(D23+D24/2) -> 0.050602631 | E28: =E25/(E23+E24/2) -> 0.04118321 | F28: =F25/(F23+F24/2) -> 0.047483222 | G28: =AVERAGE(C28:F28) -> 0.045884785 | H28: =G28 -> 0.045884785 | I28: =H28 -> 0.045884785 | J28: =I28 -> 0.045884785 | K28: =J28 -> 0.045884785
A30: Average net purchase per screen | B30: 5 | W30: =FCFE!B14 -> 518.94139 | X30: 300 | Y30: =X30+100 -> 400 | Z30: =Y30+100 -> 500 | AA30: =Z30+100 -> 600 | AB30: =AA30+100 -> 700 | AC30: =AB30+100 -> 800 | AD30: =AC30+100 -> 900 | AE30: =AD30+100 -> 1000
W31: 0 | X31: 1208.432 | Y31: 1119.446 | Z31: 1030.4601 | AA31: 941.47418 | AB31: 852.48824 | AC31: 763.50231 | AD31: 674.51637 | AE31: 585.53044
A32: Beginning balance of intangible assets | G32: =F35 -> 5807.6 | H32: =G35 -> 5807.6 | I32: =H35 -> 5807.6 | J32: =I35 -> 5807.6 | K32: =J35 -> 5807.6 | W32: =W31+50 -> 50 | X32: 1176.972 | Y32: 1087.9861 | Z32: 999.00014 | AA32: 910.0142 | AB32: 821.02827 | AC32: 732.04233 | AD32: 643.0564 | AE32: 554.07047
A33: Add: Net purchases | G33: =HLOOKUP(M1,N:P,33,0) -> 792 | H33: =G33 -> 792 | I33: =H33 -> 792 | J33: =I33 -> 792 | K33: =J33 -> 792 | N33: 792 | O33: 600 | P33: 500 | W33: =W32+50 -> 100 | X33: 1145.512 | Y33: 1056.5261 | Z33: 967.54016 | AA33: 878.55423 | AB33: 789.56829 | AC33: 700.58236 | AD33: 611.59643 | AE33: 522.61049
A34: Less: Amortisation | G34: =G37 -> 792 | H34: =H37 -> 792 | I34: =I37 -> 792 | J34: =J37 -> 792 | K34: =K37 -> 792 | W34: =W33+50 -> 150 | X34: 1114.0521 | Y34: 1025.0661 | Z34: 936.08019 | AA34: 847.09425 | AB34: 758.10832 | AC34: 669.12239 | AD34: 580.13645 | AE34: 491.15052
A35: Closing balance of intangible assets | F35: =BS!F9 -> 5807.6 | G35: =G32+G33-G34 -> 5807.6 | H35: =H32+H33-H34 -> 5807.6 | I35: =I32+I33-I34 -> 5807.6 | J35: =J32+J33-J34 -> 5807.6 | K35: =K32+K33-K34 -> 5807.6 | W35: =W34+50 -> 200 | X35: 1082.5921 | Y35: 993.60615 | Z35: 904.62021 | AA35: 815.63428 | AB35: 726.64835 | AC35: 637.66241 | AD35: 548.67648 | AE35: 459.69054
W36: =W35+50 -> 250 | X36: 1051.1321 | Y36: 962.14617 | Z36: 873.16024 | AA36: 784.17431 | AB36: 695.18837 | AC36: 606.20244 | AD36: 517.2165 | AE36: 428.23057
A37: Amortisation | C37: =IS!C9-C25 -> 361 | D37: =IS!D9-D25 -> 383 | E37: =IS!E9-E25 -> 480 | F37: =IS!F9-F25 -> 792 | G37: =F37 -> 792 | H37: =G37 -> 792 | I37: =H37 -> 792 | J37: =I37 -> 792 | K37: =J37 -> 792 | W37: =W36+50 -> 300 | X37: 1019.6721 | Y37: 930.6862 | Z37: 841.70027 | AA37: 752.71433 | AB37: 663.7284 | AC37: 574.74247 | AD37: 485.75653 | AE37: 396.7706
W38: =W37+50 -> 350 | X38: 988.21216 | Y38: 899.22623 | Z38: 810.24029 | AA38: 721.25436 | AB38: 632.26843 | AC38: 543.28249 | AD38: 454.29656 | AE38: 365.31062
A39: Beginning balance of Debt | D39: =C42 -> 4389.41 | E39: =D42 -> 4447.17 | F39: =E42 -> 7056.3 | G39: =F42 -> 7053.9 | H39: =G42 -> 6653.9 | I39: =H42 -> 6253.9 | J39: =I42 -> 5853.9 | K39: =J42 -> 5453.9
A40: Add: Debt raised
A41: Less: Debt repaid | G41: 400 | H41: =G41 -> 400 | I41: =H41 -> 400 | J41: =I41 -> 400 | K41: =J41 -> 400 | N41: 400 | O41: 300 | P41: 200
A42: Closing balance of Debt | C42: =BS!C20 -> 4389.41 | D42: =BS!D20 -> 4447.17 | E42: =BS!E20 -> 7056.3 | F42: =BS!F20 -> 7053.9 | G42: =G39+G40-G41 -> 6653.9 | H42: =H39+H40-H41 -> 6253.9 | I42: =I39+I40-I41 -> 5853.9 | J42: =J39+J40-J41 -> 5453.9 | K42: =K39+K40-K41 -> 5053.9
A44: Interest cost | C44: =IS!C11 -> 498 | D44: =IS!D11 -> 498 | E44: =IS!E11 -> 572 | F44: =IS!F11 -> 791 | G44: =AVERAGE(G39,G42)*G45 -> 740.85865 | H44: =AVERAGE(H39,H42)*H45 -> 697.62145 | I44: =AVERAGE(I39,I42)*I45 -> 654.38425 | J44: =AVERAGE(J39,J42)*J45 -> 611.14705 | K44: =AVERAGE(K39,K42)*K45 -> 567.90984
A45: Interest rate | D45: =D44/AVERAGE(D39,D42) -> 0.11271329 | E45: =E44/AVERAGE(E39,E42) -> 0.099448253 | F45: =F44/AVERAGE(F39,F42) -> 0.11211748 | G45: =AVERAGE(D45:F45) -> 0.10809301 | H45: =G45 -> 0.10809301 | I45: =H45 -> 0.10809301 | J45: =I45 -> 0.10809301 | K45: =J45 -> 0.10809301

Sheet DAT
B1: 1 | C1: 2 | D1: 3 | E1: 4 | F1: 5
A2: Beginning balance of debt | B2: 50 | C2: =B5 -> 41.810126 | D2: =C5 -> 32.801265 | E2: =D5 -> 22.891517 | F2: =E5 -> 11.990795
A3: Add: Interest | B3: =B2*$B$9 -> 5 | C3: =C2*$B$9 -> 4.1810126 | D3: =D2*$B$9 -> 3.2801265 | E3: =E2*$B$9 -> 2.2891517 | F3: =F2*$B$9 -> 1.1990795
A4: Less: EAI | B4: =$B$10 -> 13.189874 | C4: =$B$10 -> 13.189874 | D4: =$B$10 -> 13.189874 | E4: =$B$10 -> 13.189874 | F4: =$B$10 -> 13.189874
A5: Closing balance of debt | B5: =B2+B3-B4 -> 41.810126 | C5: =C2+C3-C4 -> 32.801265 | D5: =D2+D3-D4 -> 22.891517 | E5: =E2+E3-E4 -> 11.990795 | F5: =F2+F3-F4 -> 0
A7: Principal repaid | B7: =B4-B3 -> 8.189874 | C7: =C4-C3 -> 9.0088614 | D7: =D4-D3 -> 9.9097476 | E7: =E4-E3 -> 10.900722 | F7: =F4-F3 -> 11.990795 | G7: =SUM(B7:F7) -> 50
A9: Interest rate | B9: 0.1
A10: EAI | B10: =PMT(B9,5,-B2) -> 13.189874
B13: 1 | C13: =B13+1 -> 2 | D13: =C13+1 -> 3 | E13: =D13+1 -> 4 | F13: =E13+1 -> 5 | G13: =F13+1 -> 6 | H13: =G13+1 -> 7 | I13: =H13+1 -> 8 | J13: =I13+1 -> 9 | ... BI13: =BH13+1 -> 60
A14: Beginning balance of debt | B14: 80 | C14: =B17 -> 78.966903 | D14: =C17 -> 77.925197 | E14: =D17 -> 76.87481 | F14: =E17 -> 75.81567 | G14: =F17 -> 74.747704 | H14: =G17 -> 73.670838 | I14: =H17 -> 72.584998 | J14: =I17 -> 71.490109 | ... BI14: =BH17 -> 1.6857159
A15: Add: Interest | B15: =B14*$B$19/12 -> 0.66666667 | C15: =C14*$B$19/12 -> 0.65805753 | D15: =D14*$B$19/12 -> 0.64937664 | E15: =E14*$B$19/12 -> 0.64062342 | F15: =F14*$B$19/12 -> 0.63179725 | G15: =G14*$B$19/12 -> 0.62289753 | H15: =H14*$B$19/12 -> 0.61392365 | I15: =I14*$B$19/12 -> 0.60487498 | ... BI15: =BI14*$B$19/12 -> 0.014047633
A16: Less: EAI | B16: =$B$20 -> 1.6997636 | C16: =$B$20 -> 1.6997636 | D16: =$B$20 -> 1.6997636 | E16: =$B$20 -> 1.6997636 | F16: =$B$20 -> 1.6997636 | G16: =$B$20 -> 1.6997636 | H16: =$B$20 -> 1.6997636 | I16: =$B$20 -> 1.6997636 | ... BI16: =$B$20 -> 1.6997636
A17: Closing balance of debt | B17: =B14+B15-B16 -> 78.966903 | C17: =C14+C15-C16 -> 77.925197 | D17: =D14+D15-D16 -> 76.87481 | E17: =E14+E15-E16 -> 75.81567 | F17: =F14+F15-F16 -> 74.747704 | G17: =G14+G15-G16 -> 73.670838 | H17: =H14+H15-H16 -> 72.584998 | I17: =I14+I15-I16 -> 71.490109 | ... BI17: =BI14+BI15-BI16 -> 4.0412118e-14
A19: Interest | B19: 0.1
A20: EMI | B20: =PMT(B19/12,5*12,-B14) -> 1.6997636
B23: =PMT(10.5%/12,30*12,-80) -> 0.73179144

Sheet IS
A1: Income Statement (All numbers in INR lacs) | B1: FY 2020 | C1: FY 2021 | D1: FY 2022 | E1: FY 2023 | F1: FY 2024 | G1: FY 2025E | H1: FY 2026E | I1: FY 2027E | J1: FY 2028E | K1: FY 2029E
A2: 'Total Revenue' | B2: 3452 | C2: 749 | D2: 1656 | E2: 3830 | F2: 6264 | G2: =S!G2 -> 7229.0156 | H2: =S!H2 -> 7730.7944 | I2: =S!I2 -> 8261.149 | J2: =S!J2 -> 8821.5627 | K2: =S!K2 -> 9413.5916
A3: '- Raw Materials' | B3: 264 | C3: 26 | D3: 0 | E3: 0 | F3: 0 | G3: =G$2*S!G16 -> 0 | H3: =H$2*S!H16 -> 0 | I3: =I$2*S!I16 -> 0 | J3: =J$2*S!J16 -> 0 | K3: =K$2*S!K16 -> 0
A4: '- Power & Fuel Cost' | B4: 206 | C4: 57 | D4: 101 | E4: 233 | F4: 385 | G4: =G$2*S!G17 -> 433.74094 | H4: =H$2*S!H17 -> 463.84766 | I4: =I$2*S!I17 -> 495.66894 | J4: =J$2*S!J17 -> 529.29376 | K4: =K$2*S!K17 -> 564.8155
A5: '- Employee Cost' | B5: 394 | C5: 217 | D5: 265 | E5: 439 | F5: 657 | G5: =G$2*S!G18 -> 795.19172 | H5: =H$2*S!H18 -> 850.38738 | I5: =I$2*S!I18 -> 908.72639 | J5: =J$2*S!J18 -> 970.37189 | K5: =K$2*S!K18 -> 1035.4951
A6: '- Selling & Administrative Expenses' | B6: 271 | C6: 73 | D6: 108 | E6: 250 | F6: 382 | G6: =G$2*S!G19 -> 433.74094 | H6: =H$2*S!H19 -> 463.84766 | I6: =I$2*S!I19 -> 495.66894 | J6: =J$2*S!J19 -> 529.29376 | K6: =K$2*S!K19 -> 564.8155
A7: '- Operating & Other expenses' | B7: 1205 | C7: 243 | D7: 749 | E7: 1792 | F7: 2872 | G7: =G$2*S!G20 -> 3253.057 | H7: =H$2*S!H20 -> 3478.8575 | I7: =I$2*S!I20 -> 3717.517 | J7: =J$2*S!J20 -> 3969.7032 | K7: =K$2*S!K20 -> 4236.1162
A8: '= EBITDA' | B8: 1114 | C8: 134 | D8: 432 | E8: 1116 | F8: 1967 | G8: =G2-SUM(G3:G7) -> 2313.285 | H8: =H2-SUM(H3:H7) -> 2473.8542 | I8: =I2-SUM(I3:I7) -> 2643.5677 | J8: =J2-SUM(J3:J7) -> 2822.9001 | K8: =K2-SUM(K3:K7) -> 3012.3493
A9: '- Depreciation/Amortization' | B9: 542 | C9: 575 | D9: 614 | E9: 753 | F9: 1219 | G9: =S!G25+S!G37 -> 1206.8856 | H9: =S!H25+S!H37 -> 1199.3199 | I9: =S!I25+S!I37 -> 1192.1013 | J9: =S!J25+S!J37 -> 1185.2139 | K9: =S!K25+S!K37 -> 1178.6426
A10: '= PBIT' | B10: 571 | C10: -441 | D10: -183 | E10: 363 | F10: 747 | G10: =G8-G9 -> 1106.3994 | H10: =H8-H9 -> 1274.5343 | I10: =I8-I9 -> 1451.4664 | J10: =J8-J9 -> 1637.6861 | K10: =K8-K9 -> 1833.7067
A11: '- Interest & Other Items' | B11: 482 | C11: 498 | D11: 498 | E11: 572 | F11: 791 | G11: =S!G44 -> 740.85865 | H11: =S!H44 -> 697.62145 | I11: =S!I44 -> 654.38425 | J11: =S!J44 -> 611.14705 | K11: =S!K44 -> 567.90984
A12: '= PBT' | B12: 90 | C12: -939 | D12: -681 | E12: -209 | F12: -44 | G12: =G10-G11 -> 365.54071 | H12: =H10-H11 -> 576.91285 | I12: =I10-I11 -> 797.08212 | J12: =J10-J11 -> 1026.5391 | K12: =K10-K11 -> 1265.7969
A13: '- Taxes & Other Items' | B13: 62 | C13: -191 | D13: -192 | E13: 126 | F13: -12 | G13: =G12*25% -> 91.385178 | H13: =H12*25% -> 144.22821 | I13: =I12*25% -> 199.27053 | J13: =J12*25% -> 256.63477 | K13: =K12*25% -> 316.44922
A14: '= Net Income' | B14: 27 | C14: -748 | D14: -488 | E14: -335 | F14: -32 | G14: =G12-G13 -> 274.15553 | H14: =H12-H13 -> 432.68464 | I14: =I12-I13 -> 597.81159 | J14: =J12-J13 -> 769.9043 | K14: =K12-K13 -> 949.34766

Sheet BS
A1: Balance Sheet (All numbers in INR lacs) | B1: FY 2020 | C1: FY 2021 | D1: FY 2022 | E1: FY 2023 | F1: FY 2024 | G1: FY 2025E | H1: FY 2026E | I1: FY 2027E | J1: FY 2028E | K1: FY 2029E
A2: 'Cash and Short Term Investments' | B2: 323.47 | C2: 732.31 | D2: 578.58 | E2: 361.8 | F2: 419.9 | G2: =CFS!G19 -> 516.15297 | H2: =CFS!H19 -> 742.68279 | I2: =CFS!I19 -> 1129.2011 | J2: =CFS!J19 -> 1683.1127 | K2: =CFS!K19 -> 2412.1977
A3: '+ Total Receivables' | B3: 189.11 | C3: 30.69 | D3: 81.76 | E3: 182.5 | F3: 234.6 | G3: =$F$3/IS!$F$2*IS!G2 -> 270.74187 | H3: =$F$3/IS!$F$2*IS!H2 -> 289.53454 | I3: =$F$3/IS!$F$2*IS!I2 -> 309.39744 | J3: =$F$3/IS!$F$2*IS!J2 -> 330.38611 | K3: =$F$3/IS!$F$2*IS!K2 -> 352.55884
A4: '+ Total Inventory' | B4: 30.67 | C4: 24.95 | D4: 34.2 | E4: 66.4 | F4: 72.5 | G4: =$F$4/IS!$F$7*IS!G7 -> 82.119302 | H4: =$F$4/IS!$F$7*IS!H7 -> 87.819348 | I4: =$F$4/IS!$F$7*IS!I7 -> 93.844006 | J4: =$F$4/IS!$F$7*IS!J7 -> 100.21013 | K4: =$F$4/IS!$F$7*IS!K7 -> 106.93539
A5: '+ Other Current Assets' | B5: 210.36 | C5: 214.32 | D5: 171.53 | E5: 239.1 | F5: 266.9 | G5: =F5 -> 266.9 | H5: =G5 -> 266.9 | I5: =H5 -> 266.9 | J5: =I5 -> 266.9 | K5: =J5 -> 266.9
A6: '= Total Current Assets (A1)' | B6: 753.61 | C6: 1002.27 | D6: 866.07 | E6: 849.8 | F6: 993.9 | G6: =SUM(G2:G5) -> 1135.9141 | H6: =SUM(H2:H5) -> 1386.9367 | I6: =SUM(I2:I5) -> 1799.3425 | J6: =SUM(J2:J5) -> 2380.609 | K6: =SUM(K2:K5) -> 3138.592
A7: 'Loans & Advances' | B7: - | C7: - | D7: - | E7: - | F7: - | G7: =F7 -> - | H7: =G7 -> - | I7: =H7 -> - | J7: =I7 -> - | K7: =J7 -> -
A8: '+ Net Property/Plant/Equipment' | B8: 4898.4 | C8: 4555.53 | D8: 4343.43 | E8: 8641.4 | F8: 8916.9 | G8: =S!G26 -> 8752.0144 | H8: =S!H26 -> 8594.6945 | I8: =S!I26 -> 8444.5932 | J8: =S!J26 -> 8301.3792 | K8: =S!K26 -> 8164.7366
A9: '+ Goodwill & Intangibles' | B9: 1142.34 | C9: 1136.77 | D9: 1128.44 | E9: 5814.7 | F9: 5807.6 | G9: =S!G35 -> 5807.6 | H9: =S!H35 -> 5807.6 | I9: =S!I35 -> 5807.6 | J9: =S!J35 -> 5807.6 | K9: =S!K35 -> 5807.6
A10: '+ Long Term Investments' | B10: 1.09 | C10: 0.3 | D10: 0 | E10: 0 | F10: 0 | G10: =F10 -> 0 | H10: =G10 -> 0 | I10: =H10 -> 0 | J10: =I10 -> 0 | K10: =J10 -> 0
A11: '+ Deferred Tax Assets (Net)' | B11: 204.88 | C11: 398.66 | D11: 592.57 | E11: 473.5 | F11: 488.1 | G11: =F11 -> 488.1 | H11: =G11 -> 488.1 | I11: =H11 -> 488.1 | J11: =I11 -> 488.1 | K11: =J11 -> 488.1
A12: '+ Other Assets' | B12: 427.45 | C12: 408.32 | D12: 392.81 | E12: 694.1 | F12: 611.2 | G12: =F12 -> 611.2 | H12: =G12 -> 611.2 | I12: =H12 -> 611.2 | J12: =I12 -> 611.2 | K12: =J12 -> 611.2
A13: '= Non Current Assets (A2)' | B13: 6674.16 | C13: 6499.58 | D13: 6457.25 | E13: 15623.7 | F13: 15823.8 | G13: =SUM(G7:G12) -> 15658.914 | H13: =SUM(H7:H12) -> 15501.594 | I13: =SUM(I7:I12) -> 15351.493 | J13: =SUM(J7:J12) -> 15208.279 | K13: =SUM(K7:K12) -> 15071.637
A14: 'Total Assets (A1 + A2)' | B14: 7427.77 | C14: 7501.85 | D14: 7323.32 | E14: 16473.5 | F14: 16817.7 | G14: =G13+G6 -> 16794.829 | H14: =H13+H6 -> 16888.531 | I14: =I13+I6 -> 17150.836 | J14: =J13+J6 -> 17588.888 | K14: =K13+K6 -> 18210.229
A16: 'Accounts Payable' | B16: 380.98 | C16: 250.16 | D16: 343.23 | E16: 733 | F16: 776.1 | G16: =$F$16/IS!$F$7*IS!G7 -> 879.07297 | H16: =$F$16/IS!$F$7*IS!H7 -> 940.09097 | I16: =$F$16/IS!$F$7*IS!I7 -> 1004.5839 | J16: =$F$16/IS!$F$7*IS!J7 -> 1072.7321 | K16: =$F$16/IS!$F$7*IS!K7 -> 1144.7249
A17: '+ Total Deposits' | B17: - | C17: - | D17: - | E17: - | F17: - | G17: =F17 -> - | H17: =G17 -> - | I17: =H17 -> - | J17: =I17 -> - | K17: =J17 -> -
A18: '+ Other Current Liabilities' | B18: 909.5 | C18: 880.35 | D18: 1091.24 | E18: 1318.3 | F18: 1574.2 | G18: =F18 -> 1574.2 | H18: =G18 -> 1574.2 | I18: =H18 -> 1574.2 | J18: =I18 -> 1574.2 | K18: =J18 -> 1574.2
A19: '= Current Liabilities' | B19: 1290.48 | C19: 1130.51 | D19: 1434.47 | E19: 2051.3 | F19: 2350.3 | G19: =SUM(G16:G18) -> 2453.273 | H19: =SUM(H16:H18) -> 2514.291 | I19: =SUM(I16:I18) -> 2578.7839 | J19: =SUM(J16:J18) -> 2646.9321 | K19: =SUM(K16:K18) -> 2718.9249
A20: 'Total Long Term Debt' | B20: 4482.55 | C20: 4389.41 | D20: 4447.17 | E20: 7056.3 | F20: 7053.9 | G20: =S!G42 -> 6653.9 | H20: =S!H42 -> 6253.9 | I20: =S!I42 -> 5853.9 | J20: =S!J42 -> 5453.9 | K20: =S!K42 -> 5053.9
A21: '+ Deferred Tax Liabilities (Net)' | B21: - | C21: - | D21: - | E21: - | F21: - | G21: =F21 -> - | H21: =G21 -> - | I21: =H21 -> - | J21: =I21 -> - | K21: =J21 -> -
A22: '+ Other Liabilities' | B22: 174.23 | C22: 148.53 | D22: 71.57 | E22: 36.4 | F22: 90.3 | G22: =F22 -> 90.3 | H22: =G22 -> 90.3 | I22: =H22 -> 90.3 | J22: =I22 -> 90.3 | K22: =J22 -> 90.3
A23: '= Non Current Liabilities' | B23: 4656.78 | C23: 4537.94 | D23: 4518.74 | E23: 7092.7 | F23: 7144.2 | G23: =SUM(G20:G22) -> 6744.2 | H23: =SUM(H20:H22) -> 6344.2 | I23: =SUM(I20:I22) -> 5944.2 | J23: =SUM(J20:J22) -> 5544.2 | K23: =SUM(K20:K22) -> 5144.2
A24: 'Total Liabilities' | B24: 5947.26 | C24: 5668.45 | D24: 5953.21 | E24: 9144 | F24: 9494.5 | G24: =G23+G19 -> 9197.473 | H24: =H23+H19 -> 8858.491 | I24: =I23+I19 -> 8522.9839 | J24: =J23+J19 -> 8191.1321 | K24: =K23+K19 -> 7863.1249
A25: 'Common Stock' | B25: 51.35 | C25: 60.76 | D25: 61 | E25: 98 | F25: 98.1 | G25: =F25 -> 98.1 | H25: =G25 -> 98.1 | I25: =H25 -> 98.1 | J25: =I25 -> 98.1 | K25: =J25 -> 98.1
A26: '+ Additional Paid-in Capital' | B26: 1226.27 | C26: 2314.67 | D26: 2337.8 | E26: 8584.2 | F26: 8609 | G26: =F26 -> 8609 | H26: =G26 -> 8609 | I26: =H26 -> 8609 | J26: =I26 -> 8609 | K26: =J26 -> 8609
A27: '+ Reserves & Surplus' | B27: 202.6 | C27: -542.04 | D27: -1028.92 | E27: -1352.7 | F27: -1383.6 | G27: =IS!G14+F27 -> -1109.4445 | H27: =IS!H14+G27 -> -676.75983 | I27: =IS!I14+H27 -> -78.948244 | J27: =IS!J14+I27 -> 690.95606 | K27: =IS!K14+J27 -> 1640.3037
A28: '+ Minority Interest' | B28: 0.29 | C28: 0.01 | D28: -0.26 | E28: -0.7 | F28: -0.3 | G28: =F28 -> -0.3 | H28: =G28 -> -0.3 | I28: =H28 -> -0.3 | J28: =I28 -> -0.3 | K28: =J28 -> -0.3
A29: '+ Other Equity' | B29: 0 | C29: 0 | D29: 0.49 | E29: 0.7 | F29: 0 | G29: =F29 -> 0 | H29: =G29 -> 0 | I29: =H29 -> 0 | J29: =I29 -> 0 | K29: =J29 -> 0
A30: 'Total Equity' | B30: 1480.51 | C30: 1833.4 | D30: 1370.11 | E30: 7329.5 | F30: 7323.2 | G30: =SUM(G25:G29) -> 7597.3555 | H30: =SUM(H25:H29) -> 8030.0402 | I30: =SUM(I25:I29) -> 8627.8518 | J30: =SUM(J25:J29) -> 9397.7561 | K30: =SUM(K25:K29) -> 10347.104
A31: 'Total Liabilities & Shareholder's Equity' | B31: 7427.77 | C31: 7501.85 | D31: 7323.32 | E31: 16473.5 | F31: 16817.7 | G31: =G30+G24 -> 16794.829 | H31: =H30+H24 -> 16888.531 | I31: =I30+I24 -> 17150.836 | J31: =J30+J24 -> 17588.888 | K31: =K30+K24 -> 18210.229
A34: check | B34: =B31-B14 -> 0 | C34: =C31-C14 -> 0 | D34: =D31-D14 -> 0 | E34: =E31-E14 -> 0 | F34: =F31-F14 -> 0 | G34: =G31-G14 -> 0 | H34: =H31-H14 -> 0 | I34: =I31-I14 -> 0 | ... K34: =K31-K14 -> 0

Sheet CFS
A1: Cash Flow Statement (All numbers in INR lacs) | B1: FY 2020 | C1: FY 2021 | D1: FY 2022 | E1: FY 2023 | F1: FY 2024 | G1: FY 2025E | H1: FY 2026E | I1: FY 2027E | J1: FY 2028E | K1: FY 2029E
A2: Net Profit | G2: =IS!G14 -> 274.15553 | H2: =IS!H14 -> 432.68464 | I2: =IS!I14 -> 597.81159 | J2: =IS!J14 -> 769.9043 | K2: =IS!K14 -> 949.34766
A3: Add: Depreciation / Armortisation | G3: =IS!G9 -> 1206.8856 | H3: =IS!H9 -> 1199.3199 | I3: =IS!I9 -> 1192.1013 | J3: =IS!J9 -> 1185.2139 | K3: =IS!K9 -> 1178.6426
A4: Add: Interest cost | G4: =IS!G11 -> 740.85865 | H4: =IS!H11 -> 697.62145 | I4: =IS!I11 -> 654.38425 | J4: =IS!J11 -> 611.14705 | K4: =IS!K11 -> 567.90984
A5: Add/Less: Changes in working capital | G5: =BS!F3-BS!G3+BS!F4-BS!G4+BS!G16-BS!F16 -> 57.211797 | H5: =BS!G3-BS!H3+BS!G4-BS!H4+BS!H16-BS!G16 -> 36.525289 | I5: =BS!H3-BS!I3+BS!H4-BS!I4+BS!I16-BS!H16 -> 38.605374 | J5: =BS!I3-BS!J3+BS!I4-BS!J4+BS!J16-BS!I16 -> 40.793424 | K5: =BS!J3-BS!K3+BS!J4-BS!K4+BS!K16-BS!J16 -> 43.09475
A6: CFO | G6: =SUM(G2:G5) -> 2279.1116 | H6: =SUM(H2:H5) -> 2366.1513 | I6: =SUM(I2:I5) -> 2482.9025 | J6: =SUM(J2:J5) -> 2607.0587 | K6: =SUM(K2:K5) -> 2738.9949
A8: Net Purchases (Capex) | G8: =S!G24+S!G33 -> 1042 | H8: =S!H24+S!H33 -> 1042 | I8: =S!I24+S!I33 -> 1042 | J8: =S!J24+S!J33 -> 1042 | K8: =S!K24+S!K33 -> 1042
A9: CFI | G9: =-G8 -> -1042 | H9: =-H8 -> -1042 | I9: =-I8 -> -1042 | J9: =-J8 -> -1042 | K9: =-K8 -> -1042
A11: Interest cost | G11: =-G4 -> -740.85865 | H11: =-H4 -> -697.62145 | I11: =-I4 -> -654.38425 | J11: =-J4 -> -611.14705 | K11: =-K4 -> -567.90984
A12: Add: Debt raised
A13: Less: Debt repaid | G13: =-S!G41 -> -400 | H13: =-S!H41 -> -400 | I13: =-S!I41 -> -400 | J13: =-S!J41 -> -400 | K13: =-S!K41 -> -400
A14: Less: Dividend paid
A15: CFF | G15: =SUM(G11:G14) -> -1140.8587 | H15: =SUM(H11:H14) -> -1097.6215 | I15: =SUM(I11:I14) -> -1054.3842 | J15: =SUM(J11:J14) -> -1011.147 | K15: =SUM(K11:K14) -> -967.90984
A17: Beginning balance of cash | G17: =F19 -> 419.9 | H17: =G19 -> 516.15297 | I17: =H19 -> 742.68279 | J17: =I19 -> 1129.2011 | K17: =J19 -> 1683.1127
A18: CFO + CFI + CFF | G18: =G15+G9+G6 -> 96.252969 | H18: =H15+H9+H6 -> 226.52982 | I18: =I15+I9+I6 -> 386.51827 | J18: =J15+J9+J6 -> 553.91167 | K18: =K15+K9+K6 -> 729.08501
A19: Closing balance of cash | F19: =BS!F2 -> 419.9 | G19: =G17+G18 -> 516.15297 | H19: =H17+H18 -> 742.68279 | I19: =I17+I18 -> 1129.2011 | J19: =J17+J18 -> 1683.1127 | K19: =K17+K18 -> 2412.1977

Sheet FCFE
A1: FCFE (All numbers in INR lacs) | B1: FY 2020 | C1: FY 2021 | D1: FY 2022 | E1: FY 2023 | F1: FY 2024 | G1: FY 2025E | H1: FY 2026E | I1: FY 2027E | J1: FY 2028E | K1: FY 2029E
A2: Net Profit | G2: =IS!G14 -> 274.15553 | H2: =IS!H14 -> 432.68464 | I2: =IS!I14 -> 597.81159 | J2: =IS!J14 -> 769.9043 | K2: =IS!K14 -> 949.34766
A3: Add: Depreciation | G3: =IS!G9 -> 1206.8856 | H3: =IS!H9 -> 1199.3199 | I3: =IS!I9 -> 1192.1013 | J3: =IS!J9 -> 1185.2139 | K3: =IS!K9 -> 1178.6426
A4: Add/Less: Changes in Working Capital | G4: =CFS!G5 -> 57.211797 | H4: =CFS!H5 -> 36.525289 | I4: =CFS!I5 -> 38.605374 | J4: =CFS!J5 -> 40.793424 | K4: =CFS!K5 -> 43.09475
A5: Less: Capex | G5: =CFS!G9 -> -1042 | H5: =CFS!H9 -> -1042 | I5: =CFS!I9 -> -1042 | J5: =CFS!J9 -> -1042 | K5: =CFS!K9 -> -1042
A6: Add: Debt raised
A7: Less: Debt repaid | G7: =CFS!G13 -> -400 | H7: =CFS!H13 -> -400 | I7: =CFS!I13 -> -400 | J7: =CFS!J13 -> -400 | K7: =CFS!K13 -> -400
A8: FCFE | G8: =SUM(G2:G7) -> 96.252969 | H8: =SUM(H2:H7) -> 226.52982 | I8: =SUM(I2:I7) -> 386.51827 | J8: =SUM(J2:J7) -> 553.91167 | K8: =SUM(K2:K7) -> 729.08501
A9: Add: Terminal Value | K9: =K8*(1+B22)/(B23-B22) -> 7492.5732
A10: FCFE Including Terminal Value | G10: =G8+G9 -> 96.252969 | H10: =H8+H9 -> 226.52982 | I10: =I8+I9 -> 386.51827 | J10: =J8+J9 -> 553.91167 | K10: =K8+K9 -> 8221.6582
A12: Equity Value | B12: =NPV(B23,G10:K10) -> 5092.6026
A13: Number of Shares | B13: 9.8134446
A14: Intrinsic Value per share (INR) | B14: =B12/B13 -> 518.94139
A16: Current Market Price | B16: 974
H17: =B18 -> -0.46720596 | I17: 1 | J17: =I17+0.1 -> 1.1 | K17: =J17+0.1 -> 1.2 | L17: =K17+0.1 -> 1.3 | M17: =L17+0.1 -> 1.4 | N17: =M17+0.1 -> 1.5 | O17: =N17+0.1 -> 1.6 | P17: =O17+0.1 -> 1.7 | Q17: =P17+0.1 -> 1.8
A18: Upside/Downside | B18: =B14/B16-1 -> -0.46720596 | H18: 0.02 | I18: -0.42174495 | J18: -0.45606947 | K18: -0.48701289 | L18: -0.51504115 | M18: -0.54053864 | N18: -0.56382528 | O18: -0.58516947 | P18: -0.60479805 | Q18: -0.62290408
H19: =H18+0.5% -> 0.025 | I19: -0.39623134 | J19: -0.43354964 | K19: -0.46702749 | L19: -0.49721767 | M19: -0.52457206 | N19: -0.54946362 | O19: -0.57220291 | P19: -0.5930506 | Q19: -0.6122271
A20: Verdict | B20: =IF(B18>15%,"BUY",IF(B18>0%,"HOLD","SELL")) -> SELL | H20: =H19+0.5% -> 0.03 | I20: -0.36788287 | J20: -0.40866676 | K20: -0.44505547 | L20: -0.47771115 | M20: -0.50716963 | N20: -0.53386919 | O20: -0.55817177 | P20: -0.58037887 | Q20: -0.60074369
D21: P | E21: N | F21: O | H21: =H20+0.5% -> 0.035 | I21: -0.3361993 | J21: -0.3810283 | K21: -0.42078513 | L21: -0.45627138 | M21: -0.48812856 | N21: -0.51687617 | O21: -0.54293933 | P21: -0.56666933 | Q21: -0.58835892
A22: g | B22: 0.04 | D22: 0.03 | E22: 0.04 | F22: 0.05 | H22: =H21+0.5% -> 0.04 | I22: -0.30055527 | J22: -0.35014969 | K22: -0.39383594 | L22: -0.43259596 | M22: -0.46720596 | N22: -0.49828755 | O22: -0.52634443 | P22: -0.55178903 | Q22: -0.57496233
A23: ke | B23: =B24+B26*(B25-B24) -> 0.1412 | H23: =H22+0.5% -> 0.045 | I23: -0.26015871 | J23: -0.31542568 | K23: -0.36373848 | L23: -0.40631599 | M23: -0.44410846 | N23: -0.47786755 | O23: -0.50819569 | P23: -0.53558132 | Q23: -0.56042462
A24: Rf | B24: 0.067 | H24: =H23+0.5% -> 0.05 | I24: -0.21399121 | J24: -0.27609025 | K24: -0.32990684 | L24: -0.37697666 | M24: -0.41847833 | N24: -0.45533148 | O24: -0.48826417 | P24: -0.51786029 | Q24: -0.54459353
A25: Rm | B25: 0.12 | H25: =H24+0.5% -> 0.055 | I25: -0.16072102 | J25: -0.23115945 | K25: -0.29160012 | L25: -0.3440107 | M25: -0.38987487 | N25: -0.43033245 | O25: -0.46627361 | P25: -0.4984036 | Q25: -0.5272884
A26: Beta | B26: 1.4 | D26: 1.4 | E26: 1.2 | F26: 1 | H26: =H25+0.5% -> 0.06 | I26: -0.098572463 | J26: -0.17934797 | K26: -0.24786752 | L26: -0.30670141 | M26: -0.35774881 | N26: -0.40244337 | O26: -0.44188756 | P26: -0.47694313 | Q26: -0.50829333
H28: =B18 -> -0.46720596 | I28: 0.02 | J28: =I28+0.5% -> 0.025 | K28: =J28+0.5% -> 0.03 | L28: =K28+0.5% -> 0.035 | M28: =L28+0.5% -> 0.04 | N28: =M28+0.5% -> 0.045 | O28: =N28+0.5% -> 0.05 | P28: =O28+0.5% -> 0.055 | Q28: =P28+0.5% -> 0.06 | ... U28: =T28+0.5% -> 0.08
H29: 1 | I29: -0.42174495 | J29: -0.39623134 | K29: -0.36788287 | L29: -0.3361993 | M29: -0.30055527 | N29: -0.26015871 | O29: -0.21399121 | P29: -0.16072102 | Q29: -0.098572463 | R29: -0.025124169 | S29: 0.063013783 | T29: 0.17073795 | U29: 0.30539315
H30: =H29+0.1 -> 1.1 | I30: -0.45606947 | J30: -0.43354964 | K30: -0.40866676 | L30: -0.3810283 | M30: -0.35014969 | N30: -0.31542568 | O30: -0.27609025 | P30: -0.23115945 | Q30: -0.17934797 | R30: -0.11894421 | S30: -0.047617531 | T30: 0.037889406 | U30: 0.14227205
H31: =H30+0.1 -> 1.2 | I31: -0.48701289 | J31: -0.46702749 | K31: -0.44505547 | L31: -0.42078513 | M31: -0.39383594 | N31: -0.36373848 | O31: -0.32990684 | P31: -0.29160012 | Q31: -0.24786752 | R31: -0.19746836 | S31: -0.13875251 | T31: -0.069476254 | U31: 0.01349096
H32: =H31+0.1 -> 1.3 | I32: -0.51504115 | J32: -0.49721767 | K32: -0.47771115 | L32: -0.45627138 | M32: -0.43259596 | N32: -0.40631599 | O32: -0.37697666 | P32: -0.3440107 | Q32: -0.30670141 | R32: -0.26412987 | S32: -0.21509831 | T32: -0.1580156 | U32: -0.090721301
H33: =H32+0.1 -> 1.4 | I33: -0.54053864 | J33: -0.52457206 | K33: -0.50716963 | L33: -0.48812856 | M33: -0.46720596 | N33: -0.44410846 | O33: -0.41847833 | P33: -0.38987487 | Q33: -0.35774881 | R33: -0.32140674 | S33: -0.27996044 | T33: -0.23225338 | U33: -0.17675104
H34: =H33+0.1 -> 1.5 | I34: -0.56382528 | J34: -0.54946362 | K34: -0.53386919 | L34: -0.51687617 | M34: -0.49828755 | N34: -0.47786755 | O34: -0.45533148 | P34: -0.43033245 | Q34: -0.40244337 | R34: -0.37113231 | S34: -0.33572829 | T34: -0.29537267 | U34: -0.24894854
H35: =H34+0.1 -> 1.6 | I35: -0.58516947 | J35: -0.57220291 | K35: -0.55817177 | L35: -0.54293933 | M35: -0.52634443 | N35: -0.50819569 | O35: -0.48826417 | P35: -0.46627361 | Q35: -0.44188756 | R35: -0.41469206 | S35: -0.38417193 | T35: -0.34967782 | U35: -0.31037952
H36: =H35+0.1 -> 1.7 | I36: -0.60479805 | J36: -0.5930506 | K36: -0.58037887 | L36: -0.56666933 | M36: -0.55178903 | N36: -0.53558132 | O36: -0.51786029 | P36: -0.4984036 | Q36: -0.47694313 | R36: -0.45315253 | S36: -0.42663053 | T36: -0.39687807 | U36: -0.36326667
H37: =H36+0.1 -> 1.8 | I37: -0.62290408 | J37: -0.6122271 | K37: -0.60074369 | L37: -0.58835892 | M37: -0.57496233 | N37: -0.56042462 | O37: -0.54459353 | P37: -0.5272884 | Q37: -0.50829333 | R37: -0.48734803 | S37: -0.46413593 | T37: -0.43826799 | U37: -0.40926073
H38: =H37+0.1 -> 1.9 | I38: -0.63965283 | J38: -0.62992003 | K38: -0.61948041 | L38: -0.60825408 | M38: -0.59614863 | N38: -0.5830566 | O38: -0.56885224 | P38: -0.55338751 | Q38: -0.53648688 | R38: -0.51794061 | S38: -0.49749606 | T38: -0.47484605 | U38: -0.44961338
H39: =H38+0.1 -> 2 | I39: -0.65518666 | J39: -0.64629009 | K39: -0.63677139 | L39: -0.62656292 | M39: -0.6155869 | N39: -0.60375337 | O39: -0.59095777 | P39: -0.5770778 | Q39: -0.56196952 | R39: -0.54546231 | S39: -0.52735247 | T39: -0.50739468 | U39: -0.48529089
H40: =H39+0.1 -> 2.1 | I40: -0.66962881 | J40: -0.66147574 | K40: -0.6527729 | L40: -0.64346275 | M40: -0.63347941 | N40: -0.62274713 | O40: -0.61117836 | P40: -0.59867132 | Q40: -0.58510705 | R40: -0.57034558 | S40: -0.55422109 | T40: -0.53653567 | U40: -0.51705112
H41: =H40+0.1 -> 2.2 | I41: -0.68308653 | J41: -0.67559688 | K41: -0.66761963 | L41: -0.65910554 | M41: -0.64999856 | N41: -0.6402345 | O41: -0.6297396 | P41: -0.61842862 | Q41: -0.6062025 | R41: -0.59294552 | S41: -0.57852154 | T41: -0.5627694 | U41: -0.54549677
... H46: =H45+0.1 -> 2.7 | I46: -0.73852309 | J46: -0.73346841 | K46: -0.72813306 | L46: -0.72249301 | M46: -0.71652139 | N46: -0.71018807 | O46: -0.70345917 | P46: -0.69629642 | Q46: -0.68865648 | R46: -0.68049001 | S46: -0.67174063 | T46: -0.66234363 | U46: -0.65222434

Sheet Notes
A1: 1 | B1: 4 step approach
B2: 1. EBITDA Forecast (Revenue drivers, Cost drivers)
B3: 2. EBIT Forecast (Fixed asset schedule)
B4: 3. PAT Forecast (Debt schedule)
B5: 4. BS & CFS Forecast (Working capital)
A6: 2 | B6: FCFE - Income statement is created on accrual basis
B7: (PAT + Depreciation +/- Changes in working capital - Capex + Debt raised - Debt repaid)
B8: We also talked about FCFF
B9: FCFF = EBIT*(1-t) + Depreciaiton +/- Changes in working capital - Capex
A10: 3 | B10: Ke
B11: Capital Asset Pricing Model : Ke = Rf + beta* (Rm - Rf)
B12: WACC = wd*kd*(1-t) + we*ke
A13: 4 | B13: Business is a going concern --> we need to incorporate infinite life of the business
B14: For the same we calculated terminal value --> Sum of infinite GP ---> TV = C1 / (ke - g)
A15: 5 | B15: Value of anything is PV(Future Cash flows) ---> NPV
A16: 6 | B16: Compared Intrinsic Value with CMP --> Verdict
C18: Discounted Cash flow
C19: Cash | D19: Discount rate | E19: Discounted Value
C20: FCFF | D20: WACC | E20: Enterprise Value
C21: FCFE | D21: ke | E21: Equity Value
C22: D | D22: ke | E22: Share Price
B24: Relative Valuation
B25: 95% of the analysts use relative valuation
B26: He also says, DCF valuation is more fundamental in nature - but still analysts don’t use it as much
B27: 1. simple 2. it is easy to sell

Sheet CFA
I1: (Ethics) | J1: (Quant) | K1: (Derivatives) | L1: (Economics)
C2: Buy Side | E2: Markets | G2: Sell Side
E4: Equity
E5: (Equity) | G5: (CF) | I5: (FRA)
A6: Investor | C6: PM | G6: IB | I6: Company | L6: Project
C7: (PM) | E7: Debt | I7: Government
E8: (FIS)
E10: Alternatives
E11: (Alternatives)
